Workbook

Sheet README
A1: Northstar Consumer Brands Ltd — FP&A Operating Plan, Rolling Forecast & Scenario Modelling
A3: Portfolio case study | UK consumer/FMCG | Model date: 2 Oct 2026
A5: 1. Business case
A6: Northstar Consumer Brands Ltd is a fictional UK multi-division consumer business. Management needs a 2026 operating plan, rolling forecast and scenario model that explains revenue, gross margin and EBITDA performance by month and division. The model uses synthetic portfolio data so every assumption and calculation can be discussed transparently in interviews.
A12: 2. What this workbook demonstrates
A13: Driver-based revenue planning | B13: Units × ASP with division-level growth assumptions
A14: Budgeting | B14: 2026 monthly operating budget linked to 2025 actual run-rate
A15: Rolling forecast | B15: Jan–Sep actuals + Oct–Dec scenario-adjusted forecast
A16: Variance analysis | B16: Budget vs forecast revenue, gross profit and EBITDA
A17: Scenario planning | B17: Base / Upside / Downside operating assumptions
A18: Management reporting | B18: Executive KPI dashboard and decision-ready summaries
A19: Excel modelling | B19: Linked schedules, formula discipline and finance formatting conventions
A21: 3. Model navigation
A22: Assumptions | B22: Editable scenario and 2026 budget drivers
A23: Historical Actuals | B23: Synthetic monthly actuals from Jan-2024 to Sep-2026
A24: Budget 2026 | B24: Driver-based full-year 2026 budget
A25: Rolling Forecast | B25: Actuals through Sep-2026 plus Q4 forecast
A26: Variance Analysis | B26: Monthly and divisional budget-vs-forecast bridge
A27: Dashboard | B27: Executive KPI summary and charts
A28: Data Dictionary | B28: Definitions, units and modelling notes
A30: 4. Portfolio / interview note
A31: This is an independent portfolio project, not a live company engagement. Financial figures are synthetic. Use it to demonstrate modelling logic, FP&A judgement and management communication—not to claim realised business savings. A recruiter-safe phrasing is: 'Built a driver-based FP&A model covering revenue, COGS, payroll and operating expenses; produced a rolling forecast, scenario analysis and budget-versus-forecast variance reporting for a multi-division consumer business.'
A37: 5. Build 2 additions
A38: Build 2 adds detailed headcount/payroll planning, a capital expenditure and depreciation schedule, working-capital forecasting, a 13-week liquidity forecast, and an investment-appraisal business case. The payroll schedule now feeds the 2026 budget, while working capital and the cash forecast pull directly from the rolling forecast. This creates a more realistic FP&A model linking operating drivers to cash.
A46: 6. Build 3 additions
A47: Build 3 adds a full-year Price–Volume–Mix bridge, a gross-profit driver bridge, a probability-weighted Risks & Opportunities register, formula-driven management commentary and a CFO-style management pack. The project now moves beyond reporting into business partnering: explaining performance drivers, quantifying forecast uncertainty, prioritising actions and presenting an adjusted management outlook.
A56: 7. Final portfolio release
A57: Final release prepared for CV, LinkedIn and interview use. The workbook now includes a recruiter-facing Portfolio Summary sheet and is distributed with a README, project description, CV bullets, LinkedIn launch post, interview explanation and selected screenshots. All inputs are synthetic and should be described as an independent portfolio case study.

Sheet Assumptions
A1: Assumptions & Scenario Controls
A3: Blue font = hardcoded input | Black = formula | Green = cross-sheet link
A5: Active scenario
A6: Selected Scenario | B6: Base
A8: Scenario multipliers for Q4 rolling forecast
A9: Scenario | B9: Volume | C9: ASP / Price | D9: Unit Cost | E9: Marketing | F9: Other Opex
A10: Base | B10: 1 | C10: 1 | D10: 1 | E10: 1 | F10: 1
A11: Upside | B11: 1.05 | C11: 1.01 | D11: 0.99 | E11: 1 | F11: 0.99
A12: Downside | B12: 0.93 | C12: 0.99 | D12: 1.045 | E12: 1.06 | F12: 1.03
A14: Active scenario multipliers
A15: Metric | B15: Volume | C15: ASP / Price | D15: Unit Cost | E15: Marketing | F15: Other Opex
A16: Active | B16: =IF($B$6="Upside",B11,IF($B$6="Downside",B12,B10)) -> 1 | C16: =IF($B$6="Upside",C11,IF($B$6="Downside",C12,C10)) -> 1 | D16: =IF($B$6="Upside",D11,IF($B$6="Downside",D12,D10)) -> 1 | E16: =IF($B$6="Upside",E11,IF($B$6="Downside",E12,E10)) -> 1 | F16: =IF($B$6="Upside",F11,IF($B$6="Downside",F12,F10)) -> 1
A18: 2026 division budget assumptions
A19: Division | B19: Unit Growth | C19: ASP Growth | D19: Unit Cost Inflation | E19: Marketing % Revenue | F19: Payroll Growth | G19: Other Opex Growth
A20: Personal Care | B20: 0.055 | C20: 0.03 | D20: 0.035 | E20: 0.073 | F20: 0.04 | G20: 0.035
A21: Home Care | B21: 0.042 | C21: 0.028 | D21: 0.038 | E21: 0.061 | F21: 0.04 | G21: 0.035
A22: Nutrition & Wellness | B22: 0.08 | C22: 0.035 | D22: 0.042 | E22: 0.085 | F22: 0.045 | G22: 0.04
A23: Baby & Kids | B23: 0.068 | C23: 0.032 | D23: 0.04 | E23: 0.092 | F23: 0.045 | G23: 0.04
A24: Leisure & Lifestyle | B24: 0.035 | C24: 0.025 | D24: 0.045 | E24: 0.067 | F24: 0.04 | G24: 0.045
A26: Modelling notes
A27: Historical period | B27: Jan-2024 to Sep-2026 actuals
A28: Budget period | B28: Jan-2026 to Dec-2026
A29: Rolling forecast | B29: Jan-Sep actual; Oct-Dec forecast
A30: Units | B30: Physical units sold
A31: Financial units | B31: £000 unless otherwise stated
A32: Dataset source | B32: Synthetic portfolio dataset generated for this project

Sheet Historical Actuals
A1: Historical Actuals — Monthly Division Performance
A3: Period | B3: Division | C3: Units | D3: ASP (£/unit) | E3: Revenue (£000) | F3: Unit Cost (£/unit) | G3: COGS (£000) | H3: Gross Profit (£000) | I3: GP % | J3: Marketing (£000) | K3: Payroll (£000) | L3: Other Opex (£000) | M3: EBITDA (£000) | N3: EBITDA % | O3: Status
A4: 45292 | B4: Personal Care | C4: 110811 | D4: 8.34 | E4: =C4*D4/1000 -> 924.16374 | F4: 4.23 | G4: =C4*F4/1000 -> 468.73053 | H4: =E4-G4 -> 455.43321 | I4: =IFERROR(H4/E4,0) -> 0.49280576 | J4: 65.3 | K4: 119.4 | L4: 85 | M4: =H4-J4-K4-L4 -> 185.73321 | N4: =IFERROR(M4/E4,0) -> 0.20097435 | O4: Actual
A5: 45292 | B5: Home Care | C5: 88864 | D5: 10.13 | E5: =C5*D5/1000 -> 900.19232 | F5: 5.54 | G5: =C5*F5/1000 -> 492.30656 | H5: =E5-G5 -> 407.88576 | I5: =IFERROR(H5/E5,0) -> 0.45310958 | J5: 50.8 | K5: 100.6 | L5: 72 | M5: =H5-J5-K5-L5 -> 184.48576 | N5: =IFERROR(M5/E5,0) -> 0.20494038 | O5: Actual
A6: 45292 | B6: Nutrition & Wellness | C6: 64741 | D6: 14.73 | E6: =C6*D6/1000 -> 953.63493 | F6: 7.63 | G6: =C6*F6/1000 -> 493.97383 | H6: =E6-G6 -> 459.6611 | I6: =IFERROR(H6/E6,0) -> 0.4820095 | J6: 79.7 | K6: 90.7 | L6: 66.4 | M6: =H6-J6-K6-L6 -> 222.8611 | N6: =IFERROR(M6/E6,0) -> 0.23369645 | O6: Actual
A7: 45292 | B7: Baby & Kids | C7: 57959 | D7: 12.3 | E7: =C7*D7/1000 -> 712.8957 | F7: 6.4 | G7: =C7*F7/1000 -> 370.9376 | H7: =E7-G7 -> 341.9581 | I7: =IFERROR(H7/E7,0) -> 0.4796748 | J7: 66.9 | K7: 83.3 | L7: 59.5 | M7: =H7-J7-K7-L7 -> 132.2581 | N7: =IFERROR(M7/E7,0) -> 0.18552237 | O7: Actual
A8: 45292 | B8: Leisure & Lifestyle | C8: 46069 | D8: 19.45 | E8: =C8*D8/1000 -> 896.04205 | F8: 10.79 | G8: =C8*F8/1000 -> 497.08451 | H8: =E8-G8 -> 398.95754 | I8: =IFERROR(H8/E8,0) -> 0.44524422 | J8: 57 | K8: 77.3 | L8: 58.4 | M8: =H8-J8-K8-L8 -> 206.25754 | N8: =IFERROR(M8/E8,0) -> 0.23018734 | O8: Actual
A9: 45323 | B9: Personal Care | C9: 114510 | D9: 8.43 | E9: =C9*D9/1000 -> 965.3193 | F9: 4.25 | G9: =C9*F9/1000 -> 486.6675 | H9: =E9-G9 -> 478.6518 | I9: =IFERROR(H9/E9,0) -> 0.49584816 | J9: 76.8 | K9: 117.3 | L9: 84.3 | M9: =H9-J9-K9-L9 -> 200.2518 | N9: =IFERROR(M9/E9,0) -> 0.20744618 | O9: Actual
A10: 45323 | B10: Home Care | C10: 90387 | D10: 10.22 | E10: =C10*D10/1000 -> 923.75514 | F10: 5.6 | G10: =C10*F10/1000 -> 506.1672 | H10: =E10-G10 -> 417.58794 | I10: =IFERROR(H10/E10,0) -> 0.45205479 | J10: 57 | K10: 103 | L10: 69.7 | M10: =H10-J10-K10-L10 -> 187.88794 | N10: =IFERROR(M10/E10,0) -> 0.20339583 | O10: Actual
A11: 45323 | B11: Nutrition & Wellness | C11: 67097 | D11: 14.75 | E11: =C11*D11/1000 -> 989.68075 | F11: 7.52 | G11: =C11*F11/1000 -> 504.56944 | H11: =E11-G11 -> 485.11131 | I11: =IFERROR(H11/E11,0) -> 0.49016949 | J11: 78.6 | K11: 90.2 | L11: 65 | M11: =H11-J11-K11-L11 -> 251.31131 | N11: =IFERROR(M11/E11,0) -> 0.25393169 | O11: Actual
A12: 45323 | B12: Baby & Kids | C12: 58500 | D12: 12.37 | E12: =C12*D12/1000 -> 723.645 | F12: 6.33 | G12: =C12*F12/1000 -> 370.305 | H12: =E12-G12 -> 353.34 | I12: =IFERROR(H12/E12,0) -> 0.48827809 | J12: 62.8 | K12: 83 | L12: 62.9 | M12: =H12-J12-K12-L12 -> 144.64 | N12: =IFERROR(M12/E12,0) -> 0.19987701 | O12: Actual
A13: 45323 | B13: Leisure & Lifestyle | C13: 46073 | D13: 19.53 | E13: =C13*D13/1000 -> 899.80569 | F13: 10.81 | G13: =C13*F13/1000 -> 498.04913 | H13: =E13-G13 -> 401.75656 | I13: =IFERROR(H13/E13,0) -> 0.44649258 | J13: 63.4 | K13: 74.7 | L13: 57.5 | M13: =H13-J13-K13-L13 -> 206.15656 | N13: =IFERROR(M13/E13,0) -> 0.22911231 | O13: Actual
A14: 45352 | B14: Personal Care | C14: 120823 | D14: 8.42 | E14: =C14*D14/1000 -> 1017.3297 | F14: 4.26 | G14: =C14*F14/1000 -> 514.70598 | H14: =E14-G14 -> 502.62368 | I14: =IFERROR(H14/E14,0) -> 0.49406176 | J14: 77.5 | K14: 120 | L14: 85.6 | M14: =H14-J14-K14-L14 -> 219.52368 | N14: =IFERROR(M14/E14,0) -> 0.21578421 | O14: Actual
A15: 45352 | B15: Home Care | C15: 90324 | D15: 10.12 | E15: =C15*D15/1000 -> 914.07888 | F15: 5.53 | G15: =C15*F15/1000 -> 499.49172 | H15: =E15-G15 -> 414.58716 | I15: =IFERROR(H15/E15,0) -> 0.45355731 | J15: 53.7 | K15: 100.5 | L15: 74.2 | M15: =H15-J15-K15-L15 -> 186.18716 | N15: =IFERROR(M15/E15,0) -> 0.20368829 | O15: Actual
... A168: 46266 | B168: Leisure & Lifestyle | C168: 55276 | D168: 20.59 | E168: =C168*D168/1000 -> 1138.1328 | F168: 11.85 | G168: =C168*F168/1000 -> 655.0206 | H168: =E168-G168 -> 483.11224 | I168: =IFERROR(H168/E168,0) -> 0.4244779 | J168: 76.4 | K168: 83.1 | L168: 60.6 | M168: =H168-J168-K168-L168 -> 263.01224 | N168: =IFERROR(M168/E168,0) -> 0.23109099 | O168: Actual

Sheet Budget 2026
A1: 2026 Operating Budget — Driver-Based by Division
A3: Period | B3: Division | C3: PY Units | D3: Budget Units | E3: PY ASP | F3: Budget ASP | G3: PY Unit Cost | H3: Budget Unit Cost | I3: Revenue (£000) | J3: COGS (£000) | K3: Gross Profit (£000) | L3: GP % | M3: Marketing (£000) | N3: Payroll (£000) | O3: Other Opex (£000) | P3: EBITDA (£000)
A4: 46023 | B4: Personal Care | C4: ='Historical Actuals'!C64 -> 116513 | D4: =C4*(1+Assumptions!$B$20) -> 122921.21 | E4: ='Historical Actuals'!D64 -> 8.59 | F4: =E4*(1+Assumptions!$C$20) -> 8.8477 | G4: ='Historical Actuals'!F64 -> 4.42 | H4: =G4*(1+Assumptions!$D$20) -> 4.5747 | I4: =D4*F4/1000 -> 1087.57 | J4: =D4*H4/1000 -> 562.32768 | K4: =I4-J4 -> 525.24235 | L4: =IFERROR(K4/I4,0) -> 0.48295037 | M4: =I4*Assumptions!$E$20 -> 79.392612 | N4: ='Headcount & Payroll'!B37 -> 213.95031 | O4: ='Historical Actuals'!L64*(1+Assumptions!$G$20) -> 90.459 | P4: =K4-M4-N4-O4 -> 141.44043
A5: 46023 | B5: Home Care | C5: ='Historical Actuals'!C65 -> 89340 | D5: =C5*(1+Assumptions!$B$21) -> 93092.28 | E5: ='Historical Actuals'!D65 -> 10.5 | F5: =E5*(1+Assumptions!$C$21) -> 10.794 | G5: ='Historical Actuals'!F65 -> 5.69 | H5: =G5*(1+Assumptions!$D$21) -> 5.90622 | I5: =D5*F5/1000 -> 1004.8381 | J5: =D5*H5/1000 -> 549.82349 | K5: =I5-J5 -> 455.01458 | L5: =IFERROR(K5/I5,0) -> 0.45282379 | M5: =I5*Assumptions!$E$21 -> 61.295122 | N5: ='Headcount & Payroll'!B38 -> 178.82989 | O5: ='Historical Actuals'!L65*(1+Assumptions!$G$21) -> 78.3495 | P5: =K5-M5-N5-O5 -> 136.54007
A6: 46023 | B6: Nutrition & Wellness | C6: ='Historical Actuals'!C66 -> 71975 | D6: =C6*(1+Assumptions!$B$22) -> 77733 | E6: ='Historical Actuals'!D66 -> 15.23 | F6: =E6*(1+Assumptions!$C$22) -> 15.76305 | G6: ='Historical Actuals'!F66 -> 7.86 | H6: =G6*(1+Assumptions!$D$22) -> 8.19012 | I6: =D6*F6/1000 -> 1225.3092 | J6: =D6*H6/1000 -> 636.6426 | K6: =I6-J6 -> 588.66657 | L6: =IFERROR(K6/I6,0) -> 0.48042289 | M6: =I6*Assumptions!$E$22 -> 104.15128 | N6: ='Headcount & Payroll'!B39 -> 164.60602 | O6: ='Historical Actuals'!L66*(1+Assumptions!$G$22) -> 70.2 | P6: =K6-M6-N6-O6 -> 249.70927
A7: 46023 | B7: Baby & Kids | C7: ='Historical Actuals'!C67 -> 59518 | D7: =C7*(1+Assumptions!$B$23) -> 63565.224 | E7: ='Historical Actuals'!D67 -> 12.79 | F7: =E7*(1+Assumptions!$C$23) -> 13.19928 | G7: ='Historical Actuals'!F67 -> 6.63 | H7: =G7*(1+Assumptions!$D$23) -> 6.8952 | I7: =D7*F7/1000 -> 839.01519 | J7: =D7*H7/1000 -> 438.29493 | K7: =I7-J7 -> 400.72026 | L7: =IFERROR(K7/I7,0) -> 0.47760787 | M7: =I7*Assumptions!$E$23 -> 77.189397 | N7: ='Headcount & Payroll'!B40 -> 140.077 | O7: ='Historical Actuals'!L67*(1+Assumptions!$G$23) -> 65.208 | P7: =K7-M7-N7-O7 -> 118.24586
A8: 46023 | B8: Leisure & Lifestyle | C8: ='Historical Actuals'!C68 -> 47394 | D8: =C8*(1+Assumptions!$B$24) -> 49052.79 | E8: ='Historical Actuals'!D68 -> 19.94 | F8: =E8*(1+Assumptions!$C$24) -> 20.4385 | G8: ='Historical Actuals'!F68 -> 11.21 | H8: =G8*(1+Assumptions!$D$24) -> 11.71445 | I8: =D8*F8/1000 -> 1002.5654 | J8: =D8*H8/1000 -> 574.62646 | K8: =I8-J8 -> 427.93899 | L8: =IFERROR(K8/I8,0) -> 0.42684395 | M8: =I8*Assumptions!$E$24 -> 67.171885 | N8: ='Headcount & Payroll'!B41 -> 118.89419 | O8: ='Historical Actuals'!L68*(1+Assumptions!$G$24) -> 63.536 | P8: =K8-M8-N8-O8 -> 178.33692
A9: 46054 | B9: Personal Care | C9: ='Historical Actuals'!C69 -> 120448 | D9: =C9*(1+Assumptions!$B$20) -> 127072.64 | E9: ='Historical Actuals'!D69 -> 8.63 | F9: =E9*(1+Assumptions!$C$20) -> 8.8889 | G9: ='Historical Actuals'!F69 -> 4.39 | H9: =G9*(1+Assumptions!$D$20) -> 4.54365 | I9: =D9*F9/1000 -> 1129.536 | J9: =D9*H9/1000 -> 577.3736 | K9: =I9-J9 -> 552.16239 | L9: =IFERROR(K9/I9,0) -> 0.48884001 | M9: =I9*Assumptions!$E$20 -> 82.456127 | N9: ='Headcount & Payroll'!C37 -> 213.95031 | O9: ='Historical Actuals'!L69*(1+Assumptions!$G$20) -> 88.596 | P9: =K9-M9-N9-O9 -> 167.15995
A10: 46054 | B10: Home Care | C10: ='Historical Actuals'!C70 -> 92400 | D10: =C10*(1+Assumptions!$B$21) -> 96280.8 | E10: ='Historical Actuals'!D70 -> 10.48 | F10: =E10*(1+Assumptions!$C$21) -> 10.77344 | G10: ='Historical Actuals'!F70 -> 5.78 | H10: =G10*(1+Assumptions!$D$21) -> 5.99964 | I10: =D10*F10/1000 -> 1037.2754 | J10: =D10*H10/1000 -> 577.65014 | K10: =I10-J10 -> 459.62528 | L10: =IFERROR(K10/I10,0) -> 0.44310824 | M10: =I10*Assumptions!$E$21 -> 63.273801 | N10: ='Headcount & Payroll'!C38 -> 178.82989 | O10: ='Historical Actuals'!L70*(1+Assumptions!$G$21) -> 75.555 | P10: =K10-M10-N10-O10 -> 141.96659
A11: 46054 | B11: Nutrition & Wellness | C11: ='Historical Actuals'!C71 -> 72163 | D11: =C11*(1+Assumptions!$B$22) -> 77936.04 | E11: ='Historical Actuals'!D71 -> 15.28 | F11: =E11*(1+Assumptions!$C$22) -> 15.8148 | G11: ='Historical Actuals'!F71 -> 7.94 | H11: =G11*(1+Assumptions!$D$22) -> 8.27348 | I11: =D11*F11/1000 -> 1232.5429 | J11: =D11*H11/1000 -> 644.80227 | K11: =I11-J11 -> 587.74062 | L11: =IFERROR(K11/I11,0) -> 0.47685206 | M11: =I11*Assumptions!$E$22 -> 104.76615 | N11: ='Headcount & Payroll'!C39 -> 164.60602 | O11: ='Historical Actuals'!L71*(1+Assumptions!$G$22) -> 71.136 | P11: =K11-M11-N11-O11 -> 247.23246
A12: 46054 | B12: Baby & Kids | C12: ='Historical Actuals'!C72 -> 62174 | D12: =C12*(1+Assumptions!$B$23) -> 66401.832 | E12: ='Historical Actuals'!D72 -> 12.69 | F12: =E12*(1+Assumptions!$C$23) -> 13.09608 | G12: ='Historical Actuals'!F72 -> 6.64 | H12: =G12*(1+Assumptions!$D$23) -> 6.9056 | I12: =D12*F12/1000 -> 869.6037 | J12: =D12*H12/1000 -> 458.54449 | K12: =I12-J12 -> 411.05921 | L12: =IFERROR(K12/I12,0) -> 0.47269717 | M12: =I12*Assumptions!$E$23 -> 80.003541 | N12: ='Headcount & Payroll'!C40 -> 140.077 | O12: ='Historical Actuals'!L72*(1+Assumptions!$G$23) -> 64.376 | P12: =K12-M12-N12-O12 -> 126.60268
A13: 46054 | B13: Leisure & Lifestyle | C13: ='Historical Actuals'!C73 -> 47720 | D13: =C13*(1+Assumptions!$B$24) -> 49390.2 | E13: ='Historical Actuals'!D73 -> 19.85 | F13: =E13*(1+Assumptions!$C$24) -> 20.34625 | G13: ='Historical Actuals'!F73 -> 11.24 | H13: =G13*(1+Assumptions!$D$24) -> 11.7458 | I13: =D13*F13/1000 -> 1004.9054 | J13: =D13*H13/1000 -> 580.12741 | K13: =I13-J13 -> 424.77795 | L13: =IFERROR(K13/I13,0) -> 0.42270443 | M13: =I13*Assumptions!$E$24 -> 67.328659 | N13: ='Headcount & Payroll'!C41 -> 118.89419 | O13: ='Historical Actuals'!L73*(1+Assumptions!$G$24) -> 60.819 | P13: =K13-M13-N13-O13 -> 177.7361
A14: 46082 | B14: Personal Care | C14: ='Historical Actuals'!C74 -> 121346 | D14: =C14*(1+Assumptions!$B$20) -> 128020.03 | E14: ='Historical Actuals'!D74 -> 8.64 | F14: =E14*(1+Assumptions!$C$20) -> 8.8992 | G14: ='Historical Actuals'!F74 -> 4.38 | H14: =G14*(1+Assumptions!$D$20) -> 4.5333 | I14: =D14*F14/1000 -> 1139.2759 | J14: =D14*H14/1000 -> 580.3532 | K14: =I14-J14 -> 558.92265 | L14: =IFERROR(K14/I14,0) -> 0.49059466 | M14: =I14*Assumptions!$E$20 -> 83.167137 | N14: ='Headcount & Payroll'!D37 -> 223.26838 | O14: ='Historical Actuals'!L74*(1+Assumptions!$G$20) -> 88.389 | P14: =K14-M14-N14-O14 -> 164.09813
A15: 46082 | B15: Home Care | C15: ='Historical Actuals'!C75 -> 97823 | D15: =C15*(1+Assumptions!$B$21) -> 101931.57 | E15: ='Historical Actuals'!D75 -> 10.38 | F15: =E15*(1+Assumptions!$C$21) -> 10.67064 | G15: ='Historical Actuals'!F75 -> 5.8 | H15: =G15*(1+Assumptions!$D$21) -> 6.0204 | I15: =D15*F15/1000 -> 1087.675 | J15: =D15*H15/1000 -> 613.6688 | K15: =I15-J15 -> 474.00625 | L15: =IFERROR(K15/I15,0) -> 0.43579767 | M15: =I15*Assumptions!$E$21 -> 66.348178 | N15: ='Headcount & Payroll'!D38 -> 187.6939 | O15: ='Historical Actuals'!L75*(1+Assumptions!$G$21) -> 76.6935 | P15: =K15-M15-N15-O15 -> 143.27067
A16: 46082 | B16: Nutrition & Wellness | C16: ='Historical Actuals'!C76 -> 73634 | D16: =C16*(1+Assumptions!$B$22) -> 79524.72 | E16: ='Historical Actuals'!D76 -> 15.3 | F16: =E16*(1+Assumptions!$C$22) -> 15.8355 | G16: ='Historical Actuals'!F76 -> 7.89 | H16: =G16*(1+Assumptions!$D$22) -> 8.22138 | I16: =D16*F16/1000 -> 1259.3137 | J16: =D16*H16/1000 -> 653.80294 | K16: =I16-J16 -> 605.51076 | L16: =IFERROR(K16/I16,0) -> 0.48082599 | M16: =I16*Assumptions!$E$22 -> 107.04166 | N16: ='Headcount & Payroll'!D39 -> 177.23081 | O16: ='Historical Actuals'!L76*(1+Assumptions!$G$22) -> 72.8 | P16: =K16-M16-N16-O16 -> 248.43828
A17: 46082 | B17: Baby & Kids | C17: ='Historical Actuals'!C77 -> 63999 | D17: =C17*(1+Assumptions!$B$23) -> 68350.932 | E17: ='Historical Actuals'!D77 -> 12.78 | F17: =E17*(1+Assumptions!$C$23) -> 13.18896 | G17: ='Historical Actuals'!F77 -> 6.62 | H17: =G17*(1+Assumptions!$D$23) -> 6.8848 | I17: =D17*F17/1000 -> 901.47771 | J17: =D17*H17/1000 -> 470.5825 | K17: =I17-J17 -> 430.89521 | L17: =IFERROR(K17/I17,0) -> 0.47798765 | M17: =I17*Assumptions!$E$23 -> 82.935949 | N17: ='Headcount & Payroll'!D40 -> 152.75115 | O17: ='Historical Actuals'!L77*(1+Assumptions!$G$23) -> 67.704 | P17: =K17-M17-N17-O17 -> 127.50412
A18: 46082 | B18: Leisure & Lifestyle | C18: ='Historical Actuals'!C78 -> 52191 | D18: =C18*(1+Assumptions!$B$24) -> 54017.685 | E18: ='Historical Actuals'!D78 -> 20.04 | F18: =E18*(1+Assumptions!$C$24) -> 20.541 | G18: ='Historical Actuals'!F78 -> 11.37 | H18: =G18*(1+Assumptions!$D$24) -> 11.88165 | I18: =D18*F18/1000 -> 1109.5773 | J18: =D18*H18/1000 -> 641.81923 | K18: =I18-J18 -> 467.75804 | L18: =IFERROR(K18/I18,0) -> 0.42156419 | M18: =I18*Assumptions!$E$24 -> 74.341677 | N18: ='Headcount & Payroll'!D41 -> 127.77794 | O18: ='Historical Actuals'!L78*(1+Assumptions!$G$24) -> 62.909 | P18: =K18-M18-N18-O18 -> 202.72943
A19: 46113 | B19: Personal Care | C19: ='Historical Actuals'!C79 -> 126739 | D19: =C19*(1+Assumptions!$B$20) -> 133709.64 | E19: ='Historical Actuals'!D79 -> 8.65 | F19: =E19*(1+Assumptions!$C$20) -> 8.9095 | G19: ='Historical Actuals'!F79 -> 4.41 | H19: =G19*(1+Assumptions!$D$20) -> 4.56435 | I19: =D19*F19/1000 -> 1191.2861 | J19: =D19*H19/1000 -> 610.29762 | K19: =I19-J19 -> 580.98846 | L19: =IFERROR(K19/I19,0) -> 0.48769852 | M19: =I19*Assumptions!$E$20 -> 86.963884 | N19: ='Headcount & Payroll'!E37 -> 223.26838 | O19: ='Historical Actuals'!L79*(1+Assumptions!$G$20) -> 90.873 | P19: =K19-M19-N19-O19 -> 179.8832
A20: 46113 | B20: Home Care | C20: ='Historical Actuals'!C80 -> 99562 | D20: =C20*(1+Assumptions!$B$21) -> 103743.6 | E20: ='Historical Actuals'!D80 -> 10.47 | F20: =E20*(1+Assumptions!$C$21) -> 10.76316 | G20: ='Historical Actuals'!F80 -> 5.78 | H20: =G20*(1+Assumptions!$D$21) -> 5.99964 | I20: =D20*F20/1000 -> 1116.609 | J20: =D20*H20/1000 -> 622.42428 | K20: =I20-J20 -> 494.18473 | L20: =IFERROR(K20/I20,0) -> 0.44257634 | M20: =I20*Assumptions!$E$21 -> 68.11315 | N20: ='Headcount & Payroll'!E38 -> 187.6939 | O20: ='Historical Actuals'!L80*(1+Assumptions!$G$21) -> 75.969 | P20: =K20-M20-N20-O20 -> 162.40869
A21: 46113 | B21: Nutrition & Wellness | C21: ='Historical Actuals'!C81 -> 74888 | D21: =C21*(1+Assumptions!$B$22) -> 80879.04 | E21: ='Historical Actuals'!D81 -> 15.14 | F21: =E21*(1+Assumptions!$C$22) -> 15.6699 | G21: ='Historical Actuals'!F81 -> 7.9 | H21: =G21*(1+Assumptions!$D$22) -> 8.2318 | I21: =D21*F21/1000 -> 1267.3665 | J21: =D21*H21/1000 -> 665.78008 | K21: =I21-J21 -> 601.58639 | L21: =IFERROR(K21/I21,0) -> 0.47467438 | M21: =I21*Assumptions!$E$22 -> 107.72615 | N21: ='Headcount & Payroll'!E39 -> 177.23081 | O21: ='Historical Actuals'!L81*(1+Assumptions!$G$22) -> 71.968 | P21: =K21-M21-N21-O21 -> 244.66143
A22: 46113 | B22: Baby & Kids | C22: ='Historical Actuals'!C82 -> 65780 | D22: =C22*(1+Assumptions!$B$23) -> 70253.04 | E22: ='Historical Actuals'!D82 -> 12.63 | F22: =E22*(1+Assumptions!$C$23) -> 13.03416 | G22: ='Historical Actuals'!F82 -> 6.58 | H22: =G22*(1+Assumptions!$D$23) -> 6.8432 | I22: =D22*F22/1000 -> 915.68936 | J22: =D22*H22/1000 -> 480.7556 | K22: =I22-J22 -> 434.93376 | L22: =IFERROR(K22/I22,0) -> 0.47497959 | M22: =I22*Assumptions!$E$23 -> 84.243421 | N22: ='Headcount & Payroll'!E40 -> 152.75115 | O22: ='Historical Actuals'!L82*(1+Assumptions!$G$23) -> 64.272 | P22: =K22-M22-N22-O22 -> 133.66719
A23: 46113 | B23: Leisure & Lifestyle | C23: ='Historical Actuals'!C83 -> 51025 | D23: =C23*(1+Assumptions!$B$24) -> 52810.875 | E23: ='Historical Actuals'!D83 -> 20.14 | F23: =E23*(1+Assumptions!$C$24) -> 20.6435 | G23: ='Historical Actuals'!F83 -> 11.34 | H23: =G23*(1+Assumptions!$D$24) -> 11.8503 | I23: =D23*F23/1000 -> 1090.2013 | J23: =D23*H23/1000 -> 625.82471 | K23: =I23-J23 -> 464.37659 | L23: =IFERROR(K23/I23,0) -> 0.4259549 | M23: =I23*Assumptions!$E$24 -> 73.043487 | N23: ='Headcount & Payroll'!E41 -> 127.77794 | O23: ='Historical Actuals'!L83*(1+Assumptions!$G$24) -> 63.8495 | P23: =K23-M23-N23-O23 -> 199.70566
A24: 46143 | B24: Personal Care | C24: ='Historical Actuals'!C84 -> 125946 | D24: =C24*(1+Assumptions!$B$20) -> 132873.03 | E24: ='Historical Actuals'!D84 -> 8.55 | F24: =E24*(1+Assumptions!$C$20) -> 8.8065 | G24: ='Historical Actuals'!F84 -> 4.4 | H24: =G24*(1+Assumptions!$D$20) -> 4.554 | I24: =D24*F24/1000 -> 1170.1463 | J24: =D24*H24/1000 -> 605.10378 | K24: =I24-J24 -> 565.04256 | L24: =IFERROR(K24/I24,0) -> 0.48288196 | M24: =I24*Assumptions!$E$20 -> 85.420683 | N24: ='Headcount & Payroll'!F37 -> 223.26838 | O24: ='Historical Actuals'!L84*(1+Assumptions!$G$20) -> 92.8395 | P24: =K24-M24-N24-O24 -> 163.514
A25: 46143 | B25: Home Care | C25: ='Historical Actuals'!C85 -> 100105 | D25: =C25*(1+Assumptions!$B$21) -> 104309.41 | E25: ='Historical Actuals'!D85 -> 10.51 | F25: =E25*(1+Assumptions!$C$21) -> 10.80428 | G25: ='Historical Actuals'!F85 -> 5.77 | H25: =G25*(1+Assumptions!$D$21) -> 5.98926 | I25: =D25*F25/1000 -> 1126.9881 | J25: =D25*H25/1000 -> 624.73618 | K25: =I25-J25 -> 502.2519 | L25: =IFERROR(K25/I25,0) -> 0.44565857 | M25: =I25*Assumptions!$E$21 -> 68.746272 | N25: ='Headcount & Payroll'!F38 -> 187.6939 | O25: ='Historical Actuals'!L85*(1+Assumptions!$G$21) -> 75.6585 | P25: =K25-M25-N25-O25 -> 170.15323
A26: 46143 | B26: Nutrition & Wellness | C26: ='Historical Actuals'!C86 -> 78035 | D26: =C26*(1+Assumptions!$B$22) -> 84277.8 | E26: ='Historical Actuals'!D86 -> 15.07 | F26: =E26*(1+Assumptions!$C$22) -> 15.59745 | G26: ='Historical Actuals'!F86 -> 7.86 | H26: =G26*(1+Assumptions!$D$22) -> 8.19012 | I26: =D26*F26/1000 -> 1314.5188 | J26: =D26*H26/1000 -> 690.2453 | K26: =I26-J26 -> 624.27348 | L26: =IFERROR(K26/I26,0) -> 0.47490648 | M26: =I26*Assumptions!$E$22 -> 111.7341 | N26: ='Headcount & Payroll'!F39 -> 177.23081 | O26: ='Historical Actuals'!L86*(1+Assumptions!$G$22) -> 69.368 | P26: =K26-M26-N26-O26 -> 265.94057
A27: 46143 | B27: Baby & Kids | C27: ='Historical Actuals'!C87 -> 66636 | D27: =C27*(1+Assumptions!$B$23) -> 71167.248 | E27: ='Historical Actuals'!D87 -> 12.65 | F27: =E27*(1+Assumptions!$C$23) -> 13.0548 | G27: ='Historical Actuals'!F87 -> 6.61 | H27: =G27*(1+Assumptions!$D$23) -> 6.8744 | I27: =D27*F27/1000 -> 929.07419 | J27: =D27*H27/1000 -> 489.23213 | K27: =I27-J27 -> 439.84206 | L27: =IFERROR(K27/I27,0) -> 0.47341974 | M27: =I27*Assumptions!$E$23 -> 85.474825 | N27: ='Headcount & Payroll'!F40 -> 152.75115 | O27: ='Historical Actuals'!L87*(1+Assumptions!$G$23) -> 65.936 | P27: =K27-M27-N27-O27 -> 135.68009
A28: 46143 | B28: Leisure & Lifestyle | C28: ='Historical Actuals'!C88 -> 51102 | D28: =C28*(1+Assumptions!$B$24) -> 52890.57 | E28: ='Historical Actuals'!D88 -> 20.05 | F28: =E28*(1+Assumptions!$C$24) -> 20.55125 | G28: ='Historical Actuals'!F88 -> 11.22 | H28: =G28*(1+Assumptions!$D$24) -> 11.7249 | I28: =D28*F28/1000 -> 1086.9673 | J28: =D28*H28/1000 -> 620.13664 | K28: =I28-J28 -> 466.83068 | L28: =IFERROR(K28/I28,0) -> 0.42947996 | M28: =I28*Assumptions!$E$24 -> 72.826811 | N28: ='Headcount & Payroll'!F41 -> 127.77794 | O28: ='Historical Actuals'!L88*(1+Assumptions!$G$24) -> 62.1775 | P28: =K28-M28-N28-O28 -> 204.04843
A29: 46174 | B29: Personal Care | C29: ='Historical Actuals'!C89 -> 126862 | D29: =C29*(1+Assumptions!$B$20) -> 133839.41 | E29: ='Historical Actuals'!D89 -> 8.59 | F29: =E29*(1+Assumptions!$C$20) -> 8.8477 | G29: ='Historical Actuals'!F89 -> 4.44 | H29: =G29*(1+Assumptions!$D$20) -> 4.5954 | I29: =D29*F29/1000 -> 1184.1709 | J29: =D29*H29/1000 -> 615.04562 | K29: =I29-J29 -> 569.12532 | L29: =IFERROR(K29/I29,0) -> 0.48061078 | M29: =I29*Assumptions!$E$20 -> 86.444479 | N29: ='Headcount & Payroll'!G37 -> 215.50003 | O29: ='Historical Actuals'!L89*(1+Assumptions!$G$20) -> 92.115 | P29: =K29-M29-N29-O29 -> 175.06581
A30: 46174 | B30: Home Care | C30: ='Historical Actuals'!C90 -> 100850 | D30: =C30*(1+Assumptions!$B$21) -> 105085.7 | E30: ='Historical Actuals'!D90 -> 10.4 | F30: =E30*(1+Assumptions!$C$21) -> 10.6912 | G30: ='Historical Actuals'!F90 -> 5.69 | H30: =G30*(1+Assumptions!$D$21) -> 5.90622 | I30: =D30*F30/1000 -> 1123.4922 | J30: =D30*H30/1000 -> 620.65926 | K30: =I30-J30 -> 502.83297 | L30: =IFERROR(K30/I30,0) -> 0.44756248 | M30: =I30*Assumptions!$E$21 -> 68.533026 | N30: ='Headcount & Payroll'!G38 -> 180.19206 | O30: ='Historical Actuals'!L90*(1+Assumptions!$G$21) -> 76.2795 | P30: =K30-M30-N30-O30 -> 177.82838
A31: 46174 | B31: Nutrition & Wellness | C31: ='Historical Actuals'!C91 -> 80749 | D31: =C31*(1+Assumptions!$B$22) -> 87208.92 | E31: ='Historical Actuals'!D91 -> 15.25 | F31: =E31*(1+Assumptions!$C$22) -> 15.78375 | G31: ='Historical Actuals'!F91 -> 7.92 | H31: =G31*(1+Assumptions!$D$22) -> 8.25264 | I31: =D31*F31/1000 -> 1376.4838 | J31: =D31*H31/1000 -> 719.70382 | K31: =I31-J31 -> 656.77997 | L31: =IFERROR(K31/I31,0) -> 0.47714326 | M31: =I31*Assumptions!$E$22 -> 117.00112 | N31: ='Headcount & Payroll'!G39 -> 169.65001 | O31: ='Historical Actuals'!L91*(1+Assumptions!$G$22) -> 69.576 | P31: =K31-M31-N31-O31 -> 300.55283
A32: 46174 | B32: Baby & Kids | C32: ='Historical Actuals'!C92 -> 65799 | D32: =C32*(1+Assumptions!$B$23) -> 70273.332 | E32: ='Historical Actuals'!D92 -> 12.65 | F32: =E32*(1+Assumptions!$C$23) -> 13.0548 | G32: ='Historical Actuals'!F92 -> 6.53 | H32: =G32*(1+Assumptions!$D$23) -> 6.7912 | I32: =D32*F32/1000 -> 917.40429 | J32: =D32*H32/1000 -> 477.24025 | K32: =I32-J32 -> 440.16404 | L32: =IFERROR(K32/I32,0) -> 0.47979287 | M32: =I32*Assumptions!$E$23 -> 84.401195 | N32: ='Headcount & Payroll'!G40 -> 149.00023 | O32: ='Historical Actuals'!L92*(1+Assumptions!$G$23) -> 64.376 | P32: =K32-M32-N32-O32 -> 142.38662
A33: 46174 | B33: Leisure & Lifestyle | C33: ='Historical Actuals'!C93 -> 54630 | D33: =C33*(1+Assumptions!$B$24) -> 56542.05 | E33: ='Historical Actuals'!D93 -> 20.09 | F33: =E33*(1+Assumptions!$C$24) -> 20.59225 | G33: ='Historical Actuals'!F93 -> 11.22 | H33: =G33*(1+Assumptions!$D$24) -> 11.7249 | I33: =D33*F33/1000 -> 1164.328 | J33: =D33*H33/1000 -> 662.94988 | K33: =I33-J33 -> 501.37815 | L33: =IFERROR(K33/I33,0) -> 0.43061589 | M33: =I33*Assumptions!$E$24 -> 78.009978 | N33: ='Headcount & Payroll'!G41 -> 127.77794 | O33: ='Historical Actuals'!L93*(1+Assumptions!$G$24) -> 61.028 | P33: =K33-M33-N33-O33 -> 234.56223
A34: 46204 | B34: Personal Care | C34: ='Historical Actuals'!C94 -> 133630 | D34: =C34*(1+Assumptions!$B$20) -> 140979.65 | E34: ='Historical Actuals'!D94 -> 8.68 | F34: =E34*(1+Assumptions!$C$20) -> 8.9404 | G34: ='Historical Actuals'!F94 -> 4.37 | H34: =G34*(1+Assumptions!$D$20) -> 4.52295 | I34: =D34*F34/1000 -> 1260.4145 | J34: =D34*H34/1000 -> 637.64391 | K34: =I34-J34 -> 622.77055 | L34: =IFERROR(K34/I34,0) -> 0.49409982 | M34: =I34*Assumptions!$E$20 -> 92.010256 | N34: ='Headcount & Payroll'!H37 -> 215.50003 | O34: ='Historical Actuals'!L94*(1+Assumptions!$G$20) -> 91.08 | P34: =K34-M34-N34-O34 -> 224.18027
A35: 46204 | B35: Home Care | C35: ='Historical Actuals'!C95 -> 106930 | D35: =C35*(1+Assumptions!$B$21) -> 111421.06 | E35: ='Historical Actuals'!D95 -> 10.45 | F35: =E35*(1+Assumptions!$C$21) -> 10.7426 | G35: ='Historical Actuals'!F95 -> 5.79 | H35: =G35*(1+Assumptions!$D$21) -> 6.01002 | I35: =D35*F35/1000 -> 1196.9519 | J35: =D35*H35/1000 -> 669.6428 | K35: =I35-J35 -> 527.30908 | L35: =IFERROR(K35/I35,0) -> 0.44054326 | M35: =I35*Assumptions!$E$21 -> 73.014065 | N35: ='Headcount & Payroll'!H38 -> 180.19206 | O35: ='Historical Actuals'!L95*(1+Assumptions!$G$21) -> 77.832 | P35: =K35-M35-N35-O35 -> 196.27095
A36: 46204 | B36: Nutrition & Wellness | C36: ='Historical Actuals'!C96 -> 78422 | D36: =C36*(1+Assumptions!$B$22) -> 84695.76 | E36: ='Historical Actuals'!D96 -> 15.25 | F36: =E36*(1+Assumptions!$C$22) -> 15.78375 | G36: ='Historical Actuals'!F96 -> 7.96 | H36: =G36*(1+Assumptions!$D$22) -> 8.29432 | I36: =D36*F36/1000 -> 1336.8167 | J36: =D36*H36/1000 -> 702.49374 | K36: =I36-J36 -> 634.32297 | L36: =IFERROR(K36/I36,0) -> 0.47450257 | M36: =I36*Assumptions!$E$22 -> 113.62942 | N36: ='Headcount & Payroll'!H39 -> 169.65001 | O36: ='Historical Actuals'!L96*(1+Assumptions!$G$22) -> 73.424 | P36: =K36-M36-N36-O36 -> 277.61953
A37: 46204 | B37: Baby & Kids | C37: ='Historical Actuals'!C97 -> 70093 | D37: =C37*(1+Assumptions!$B$23) -> 74859.324 | E37: ='Historical Actuals'!D97 -> 12.69 | F37: =E37*(1+Assumptions!$C$23) -> 13.09608 | G37: ='Historical Actuals'!F97 -> 6.58 | H37: =G37*(1+Assumptions!$D$23) -> 6.8432 | I37: =D37*F37/1000 -> 980.3637 | J37: =D37*H37/1000 -> 512.27733 | K37: =I37-J37 -> 468.08637 | L37: =IFERROR(K37/I37,0) -> 0.47746196 | M37: =I37*Assumptions!$E$23 -> 90.19346 | N37: ='Headcount & Payroll'!H40 -> 149.00023 | O37: ='Historical Actuals'!L97*(1+Assumptions!$G$23) -> 64.896 | P37: =K37-M37-N37-O37 -> 163.99668
A38: 46204 | B38: Leisure & Lifestyle | C38: ='Historical Actuals'!C98 -> 55722 | D38: =C38*(1+Assumptions!$B$24) -> 57672.27 | E38: ='Historical Actuals'!D98 -> 20.11 | F38: =E38*(1+Assumptions!$C$24) -> 20.61275 | G38: ='Historical Actuals'!F98 -> 11.21 | H38: =G38*(1+Assumptions!$D$24) -> 11.71445 | I38: =D38*F38/1000 -> 1188.7841 | J38: =D38*H38/1000 -> 675.59892 | K38: =I38-J38 -> 513.18516 | L38: =IFERROR(K38/I38,0) -> 0.43168912 | M38: =I38*Assumptions!$E$24 -> 79.648534 | N38: ='Headcount & Payroll'!H41 -> 127.77794 | O38: ='Historical Actuals'!L98*(1+Assumptions!$G$24) -> 64.163 | P38: =K38-M38-N38-O38 -> 241.59569
A39: 46235 | B39: Personal Care | C39: ='Historical Actuals'!C99 -> 127601 | D39: =C39*(1+Assumptions!$B$20) -> 134619.05 | E39: ='Historical Actuals'!D99 -> 8.61 | F39: =E39*(1+Assumptions!$C$20) -> 8.8683 | G39: ='Historical Actuals'!F99 -> 4.44 | H39: =G39*(1+Assumptions!$D$20) -> 4.5954 | I39: =D39*F39/1000 -> 1193.8422 | J39: =D39*H39/1000 -> 618.62841 | K39: =I39-J39 -> 575.21376 | L39: =IFERROR(K39/I39,0) -> 0.48181726 | M39: =I39*Assumptions!$E$20 -> 87.150478 | N39: ='Headcount & Payroll'!I37 -> 215.50003 | O39: ='Historical Actuals'!L99*(1+Assumptions!$G$20) -> 91.908 | P39: =K39-M39-N39-O39 -> 180.65525
A40: 46235 | B40: Home Care | C40: ='Historical Actuals'!C100 -> 99964 | D40: =C40*(1+Assumptions!$B$21) -> 104162.49 | E40: ='Historical Actuals'!D100 -> 10.46 | F40: =E40*(1+Assumptions!$C$21) -> 10.75288 | G40: ='Historical Actuals'!F100 -> 5.75 | H40: =G40*(1+Assumptions!$D$21) -> 5.9685 | I40: =D40*F40/1000 -> 1120.0467 | J40: =D40*H40/1000 -> 621.69381 | K40: =I40-J40 -> 498.35292 | L40: =IFERROR(K40/I40,0) -> 0.4449394 | M40: =I40*Assumptions!$E$21 -> 68.322851 | N40: ='Headcount & Payroll'!I38 -> 180.19206 | O40: ='Historical Actuals'!L100*(1+Assumptions!$G$21) -> 79.074 | P40: =K40-M40-N40-O40 -> 170.76401
A41: 46235 | B41: Nutrition & Wellness | C41: ='Historical Actuals'!C101 -> 79423 | D41: =C41*(1+Assumptions!$B$22) -> 85776.84 | E41: ='Historical Actuals'!D101 -> 15.08 | F41: =E41*(1+Assumptions!$C$22) -> 15.6078 | G41: ='Historical Actuals'!F101 -> 7.96 | H41: =G41*(1+Assumptions!$D$22) -> 8.29432 | I41: =D41*F41/1000 -> 1338.7878 | J41: =D41*H41/1000 -> 711.46056 | K41: =I41-J41 -> 627.3272 | L41: =IFERROR(K41/I41,0) -> 0.46857853 | M41: =I41*Assumptions!$E$22 -> 113.79696 | N41: ='Headcount & Payroll'!I39 -> 169.65001 | O41: ='Historical Actuals'!L101*(1+Assumptions!$G$22) -> 71.552 | P41: =K41-M41-N41-O41 -> 272.32823
A42: 46235 | B42: Baby & Kids | C42: ='Historical Actuals'!C102 -> 65580 | D42: =C42*(1+Assumptions!$B$23) -> 70039.44 | E42: ='Historical Actuals'!D102 -> 12.63 | F42: =E42*(1+Assumptions!$C$23) -> 13.03416 | G42: ='Historical Actuals'!F102 -> 6.65 | H42: =G42*(1+Assumptions!$D$23) -> 6.916 | I42: =D42*F42/1000 -> 912.90527 | J42: =D42*H42/1000 -> 484.39277 | K42: =I42-J42 -> 428.5125 | L42: =IFERROR(K42/I42,0) -> 0.46939427 | M42: =I42*Assumptions!$E$23 -> 83.987285 | N42: ='Headcount & Payroll'!I40 -> 149.00023 | O42: ='Historical Actuals'!L102*(1+Assumptions!$G$23) -> 67.08 | P42: =K42-M42-N42-O42 -> 128.44499
A43: 46235 | B43: Leisure & Lifestyle | C43: ='Historical Actuals'!C103 -> 51753 | D43: =C43*(1+Assumptions!$B$24) -> 53564.355 | E43: ='Historical Actuals'!D103 -> 20.13 | F43: =E43*(1+Assumptions!$C$24) -> 20.63325 | G43: ='Historical Actuals'!F103 -> 11.37 | H43: =G43*(1+Assumptions!$D$24) -> 11.88165 | I43: =D43*F43/1000 -> 1105.2067 | J43: =D43*H43/1000 -> 636.43292 | K43: =I43-J43 -> 468.77381 | L43: =IFERROR(K43/I43,0) -> 0.42415034 | M43: =I43*Assumptions!$E$24 -> 74.048851 | N43: ='Headcount & Payroll'!I41 -> 127.77794 | O43: ='Historical Actuals'!L103*(1+Assumptions!$G$24) -> 64.6855 | P43: =K43-M43-N43-O43 -> 202.26152
A44: 46266 | B44: Personal Care | C44: ='Historical Actuals'!C104 -> 119733 | D44: =C44*(1+Assumptions!$B$20) -> 126318.31 | E44: ='Historical Actuals'!D104 -> 8.65 | F44: =E44*(1+Assumptions!$C$20) -> 8.9095 | G44: ='Historical Actuals'!F104 -> 4.41 | H44: =G44*(1+Assumptions!$D$20) -> 4.56435 | I44: =D44*F44/1000 -> 1125.433 | J44: =D44*H44/1000 -> 576.561 | K44: =I44-J44 -> 548.87203 | L44: =IFERROR(K44/I44,0) -> 0.48769852 | M44: =I44*Assumptions!$E$20 -> 82.156611 | N44: ='Headcount & Payroll'!J37 -> 215.50003 | O44: ='Historical Actuals'!L104*(1+Assumptions!$G$20) -> 90.873 | P44: =K44-M44-N44-O44 -> 160.34238
A45: 46266 | B45: Home Care | C45: ='Historical Actuals'!C105 -> 97680 | D45: =C45*(1+Assumptions!$B$21) -> 101782.56 | E45: ='Historical Actuals'!D105 -> 10.51 | F45: =E45*(1+Assumptions!$C$21) -> 10.80428 | G45: ='Historical Actuals'!F105 -> 5.7 | H45: =G45*(1+Assumptions!$D$21) -> 5.9166 | I45: =D45*F45/1000 -> 1099.6873 | J45: =D45*H45/1000 -> 602.20669 | K45: =I45-J45 -> 497.48058 | L45: =IFERROR(K45/I45,0) -> 0.45238368 | M45: =I45*Assumptions!$E$21 -> 67.080924 | N45: ='Headcount & Payroll'!J38 -> 180.19206 | O45: ='Historical Actuals'!L105*(1+Assumptions!$G$21) -> 76.0725 | P45: =K45-M45-N45-O45 -> 174.1351
A46: 46266 | B46: Nutrition & Wellness | C46: ='Historical Actuals'!C106 -> 76538 | D46: =C46*(1+Assumptions!$B$22) -> 82661.04 | E46: ='Historical Actuals'!D106 -> 15.18 | F46: =E46*(1+Assumptions!$C$22) -> 15.7113 | G46: ='Historical Actuals'!F106 -> 7.89 | H46: =G46*(1+Assumptions!$D$22) -> 8.22138 | I46: =D46*F46/1000 -> 1298.7124 | J46: =D46*H46/1000 -> 679.58782 | K46: =I46-J46 -> 619.12458 | L46: =IFERROR(K46/I46,0) -> 0.47672185 | M46: =I46*Assumptions!$E$22 -> 110.39055 | N46: ='Headcount & Payroll'!J39 -> 169.65001 | O46: ='Historical Actuals'!L106*(1+Assumptions!$G$22) -> 70.2 | P46: =K46-M46-N46-O46 -> 268.88401
A47: 46266 | B47: Baby & Kids | C47: ='Historical Actuals'!C107 -> 65764 | D47: =C47*(1+Assumptions!$B$23) -> 70235.952 | E47: ='Historical Actuals'!D107 -> 12.68 | F47: =E47*(1+Assumptions!$C$23) -> 13.08576 | G47: ='Historical Actuals'!F107 -> 6.55 | H47: =G47*(1+Assumptions!$D$23) -> 6.812 | I47: =D47*F47/1000 -> 919.09081 | J47: =D47*H47/1000 -> 478.44731 | K47: =I47-J47 -> 440.64351 | L47: =IFERROR(K47/I47,0) -> 0.47943413 | M47: =I47*Assumptions!$E$23 -> 84.556355 | N47: ='Headcount & Payroll'!J40 -> 149.00023 | O47: ='Historical Actuals'!L107*(1+Assumptions!$G$23) -> 63.96 | P47: =K47-M47-N47-O47 -> 143.12692
A48: 46266 | B48: Leisure & Lifestyle | C48: ='Historical Actuals'!C108 -> 51441 | D48: =C48*(1+Assumptions!$B$24) -> 53241.435 | E48: ='Historical Actuals'!D108 -> 20.09 | F48: =E48*(1+Assumptions!$C$24) -> 20.59225 | G48: ='Historical Actuals'!F108 -> 11.23 | H48: =G48*(1+Assumptions!$D$24) -> 11.73535 | I48: =D48*F48/1000 -> 1096.3609 | J48: =D48*H48/1000 -> 624.80687 | K48: =I48-J48 -> 471.55407 | L48: =IFERROR(K48/I48,0) -> 0.43010841 | M48: =I48*Assumptions!$E$24 -> 73.456183 | N48: ='Headcount & Payroll'!J41 -> 127.77794 | O48: ='Historical Actuals'!L108*(1+Assumptions!$G$24) -> 63.745 | P48: =K48-M48-N48-O48 -> 206.57495
A49: 46296 | B49: Personal Care | C49: ='Historical Actuals'!C109 -> 132521 | D49: =C49*(1+Assumptions!$B$20) -> 139809.65 | E49: ='Historical Actuals'!D109 -> 8.62 | F49: =E49*(1+Assumptions!$C$20) -> 8.8786 | G49: ='Historical Actuals'!F109 -> 4.39 | H49: =G49*(1+Assumptions!$D$20) -> 4.54365 | I49: =D49*F49/1000 -> 1241.314 | J49: =D49*H49/1000 -> 635.24614 | K49: =I49-J49 -> 606.06786 | L49: =IFERROR(K49/I49,0) -> 0.48824702 | M49: =I49*Assumptions!$E$20 -> 90.615922 | N49: ='Headcount & Payroll'!K37 -> 215.50003 | O49: ='Historical Actuals'!L109*(1+Assumptions!$G$20) -> 88.2855 | P49: =K49-M49-N49-O49 -> 211.66641
A50: 46296 | B50: Home Care | C50: ='Historical Actuals'!C110 -> 99372 | D50: =C50*(1+Assumptions!$B$21) -> 103545.62 | E50: ='Historical Actuals'!D110 -> 10.38 | F50: =E50*(1+Assumptions!$C$21) -> 10.67064 | G50: ='Historical Actuals'!F110 -> 5.77 | H50: =G50*(1+Assumptions!$D$21) -> 5.98926 | I50: =D50*F50/1000 -> 1104.8981 | J50: =D50*H50/1000 -> 620.16166 | K50: =I50-J50 -> 484.73641 | L50: =IFERROR(K50/I50,0) -> 0.43871595 | M50: =I50*Assumptions!$E$21 -> 67.398783 | N50: ='Headcount & Payroll'!K38 -> 180.19206 | O50: ='Historical Actuals'!L110*(1+Assumptions!$G$21) -> 77.418 | P50: =K50-M50-N50-O50 -> 159.72757
A51: 46296 | B51: Nutrition & Wellness | C51: ='Historical Actuals'!C111 -> 80242 | D51: =C51*(1+Assumptions!$B$22) -> 86661.36 | E51: ='Historical Actuals'!D111 -> 15.09 | F51: =E51*(1+Assumptions!$C$22) -> 15.61815 | G51: ='Historical Actuals'!F111 -> 7.96 | H51: =G51*(1+Assumptions!$D$22) -> 8.29432 | I51: =D51*F51/1000 -> 1353.4901 | J51: =D51*H51/1000 -> 718.79705 | K51: =I51-J51 -> 634.69307 | L51: =IFERROR(K51/I51,0) -> 0.4689307 | M51: =I51*Assumptions!$E$22 -> 115.04666 | N51: ='Headcount & Payroll'!K39 -> 169.65001 | O51: ='Historical Actuals'!L111*(1+Assumptions!$G$22) -> 71.448 | P51: =K51-M51-N51-O51 -> 278.5484
A52: 46296 | B52: Baby & Kids | C52: ='Historical Actuals'!C112 -> 67292 | D52: =C52*(1+Assumptions!$B$23) -> 71867.856 | E52: ='Historical Actuals'!D112 -> 12.71 | F52: =E52*(1+Assumptions!$C$23) -> 13.11672 | G52: ='Historical Actuals'!F112 -> 6.54 | H52: =G52*(1+Assumptions!$D$23) -> 6.8016 | I52: =D52*F52/1000 -> 942.67054 | J52: =D52*H52/1000 -> 488.81641 | K52: =I52-J52 -> 453.85413 | L52: =IFERROR(K52/I52,0) -> 0.48145573 | M52: =I52*Assumptions!$E$23 -> 86.72569 | N52: ='Headcount & Payroll'!K40 -> 149.00023 | O52: ='Historical Actuals'!L112*(1+Assumptions!$G$23) -> 65.52 | P52: =K52-M52-N52-O52 -> 152.60822
A53: 46296 | B53: Leisure & Lifestyle | C53: ='Historical Actuals'!C113 -> 54568 | D53: =C53*(1+Assumptions!$B$24) -> 56477.88 | E53: ='Historical Actuals'!D113 -> 19.98 | F53: =E53*(1+Assumptions!$C$24) -> 20.4795 | G53: ='Historical Actuals'!F113 -> 11.2 | H53: =G53*(1+Assumptions!$D$24) -> 11.704 | I53: =D53*F53/1000 -> 1156.6387 | J53: =D53*H53/1000 -> 661.01711 | K53: =I53-J53 -> 495.62164 | L53: =IFERROR(K53/I53,0) -> 0.42850167 | M53: =I53*Assumptions!$E$24 -> 77.494796 | N53: ='Headcount & Payroll'!K41 -> 127.77794 | O53: ='Historical Actuals'!L113*(1+Assumptions!$G$24) -> 61.237 | P53: =K53-M53-N53-O53 -> 229.1119
A54: 46327 | B54: Personal Care | C54: ='Historical Actuals'!C114 -> 138715 | D54: =C54*(1+Assumptions!$B$20) -> 146344.32 | E54: ='Historical Actuals'!D114 -> 8.59 | F54: =E54*(1+Assumptions!$C$20) -> 8.8477 | G54: ='Historical Actuals'!F114 -> 4.46 | H54: =G54*(1+Assumptions!$D$20) -> 4.6161 | I54: =D54*F54/1000 -> 1294.8107 | J54: =D54*H54/1000 -> 675.54004 | K54: =I54-J54 -> 619.27065 | L54: =IFERROR(K54/I54,0) -> 0.47827119 | M54: =I54*Assumptions!$E$20 -> 94.52118 | N54: ='Headcount & Payroll'!L37 -> 215.50003 | O54: ='Historical Actuals'!L114*(1+Assumptions!$G$20) -> 90.666 | P54: =K54-M54-N54-O54 -> 218.58343
A55: 46327 | B55: Home Care | C55: ='Historical Actuals'!C115 -> 111700 | D55: =C55*(1+Assumptions!$B$21) -> 116391.4 | E55: ='Historical Actuals'!D115 -> 10.42 | F55: =E55*(1+Assumptions!$C$21) -> 10.71176 | G55: ='Historical Actuals'!F115 -> 5.76 | H55: =G55*(1+Assumptions!$D$21) -> 5.97888 | I55: =D55*F55/1000 -> 1246.7567 | J55: =D55*H55/1000 -> 695.89021 | K55: =I55-J55 -> 550.86653 | L55: =IFERROR(K55/I55,0) -> 0.44183962 | M55: =I55*Assumptions!$E$21 -> 76.052161 | N55: ='Headcount & Payroll'!L38 -> 180.19206 | O55: ='Historical Actuals'!L115*(1+Assumptions!$G$21) -> 79.074 | P55: =K55-M55-N55-O55 -> 215.54831
A56: 46327 | B56: Nutrition & Wellness | C56: ='Historical Actuals'!C116 -> 88160 | D56: =C56*(1+Assumptions!$B$22) -> 95212.8 | E56: ='Historical Actuals'!D116 -> 15.14 | F56: =E56*(1+Assumptions!$C$22) -> 15.6699 | G56: ='Historical Actuals'!F116 -> 7.91 | H56: =G56*(1+Assumptions!$D$22) -> 8.24222 | I56: =D56*F56/1000 -> 1491.9751 | J56: =D56*H56/1000 -> 784.76484 | K56: =I56-J56 -> 707.21021 | L56: =IFERROR(K56/I56,0) -> 0.47400941 | M56: =I56*Assumptions!$E$22 -> 126.81788 | N56: ='Headcount & Payroll'!L39 -> 169.65001 | O56: ='Historical Actuals'!L116*(1+Assumptions!$G$22) -> 73.32 | P56: =K56-M56-N56-O56 -> 337.42232
A57: 46327 | B57: Baby & Kids | C57: ='Historical Actuals'!C117 -> 71139 | D57: =C57*(1+Assumptions!$B$23) -> 75976.452 | E57: ='Historical Actuals'!D117 -> 12.66 | F57: =E57*(1+Assumptions!$C$23) -> 13.06512 | G57: ='Historical Actuals'!F117 -> 6.62 | H57: =G57*(1+Assumptions!$D$23) -> 6.8848 | I57: =D57*F57/1000 -> 992.64146 | J57: =D57*H57/1000 -> 523.08268 | K57: =I57-J57 -> 469.55879 | L57: =IFERROR(K57/I57,0) -> 0.47303967 | M57: =I57*Assumptions!$E$23 -> 91.323015 | N57: ='Headcount & Payroll'!L40 -> 149.00023 | O57: ='Historical Actuals'!L117*(1+Assumptions!$G$23) -> 63.752 | P57: =K57-M57-N57-O57 -> 165.48354
A58: 46327 | B58: Leisure & Lifestyle | C58: ='Historical Actuals'!C118 -> 55469 | D58: =C58*(1+Assumptions!$B$24) -> 57410.415 | E58: ='Historical Actuals'!D118 -> 19.99 | F58: =E58*(1+Assumptions!$C$24) -> 20.48975 | G58: ='Historical Actuals'!F118 -> 11.34 | H58: =G58*(1+Assumptions!$D$24) -> 11.8503 | I58: =D58*F58/1000 -> 1176.3251 | J58: =D58*H58/1000 -> 680.33064 | K58: =I58-J58 -> 495.99441 | L58: =IFERROR(K58/I58,0) -> 0.42164741 | M58: =I58*Assumptions!$E$24 -> 78.813778 | N58: ='Headcount & Payroll'!L41 -> 127.77794 | O58: ='Historical Actuals'!L118*(1+Assumptions!$G$24) -> 63.6405 | P58: =K58-M58-N58-O58 -> 225.76219
A59: 46357 | B59: Personal Care | C59: ='Historical Actuals'!C119 -> 147573 | D59: =C59*(1+Assumptions!$B$20) -> 155689.51 | E59: ='Historical Actuals'!D119 -> 8.61 | F59: =E59*(1+Assumptions!$C$20) -> 8.8683 | G59: ='Historical Actuals'!F119 -> 4.43 | H59: =G59*(1+Assumptions!$D$20) -> 4.58505 | I59: =D59*F59/1000 -> 1380.7013 | J59: =D59*H59/1000 -> 713.84421 | K59: =I59-J59 -> 666.85712 | L59: =IFERROR(K59/I59,0) -> 0.48298434 | M59: =I59*Assumptions!$E$20 -> 100.7912 | N59: ='Headcount & Payroll'!M37 -> 215.50003 | O59: ='Historical Actuals'!L119*(1+Assumptions!$G$20) -> 90.7695 | P59: =K59-M59-N59-O59 -> 259.79639
A60: 46357 | B60: Home Care | C60: ='Historical Actuals'!C120 -> 116638 | D60: =C60*(1+Assumptions!$B$21) -> 121536.8 | E60: ='Historical Actuals'!D120 -> 10.54 | F60: =E60*(1+Assumptions!$C$21) -> 10.83512 | G60: ='Historical Actuals'!F120 -> 5.75 | H60: =G60*(1+Assumptions!$D$21) -> 5.9685 | I60: =D60*F60/1000 -> 1316.8658 | J60: =D60*H60/1000 -> 725.39237 | K60: =I60-J60 -> 591.4734 | L60: =IFERROR(K60/I60,0) -> 0.44915239 | M60: =I60*Assumptions!$E$21 -> 80.328812 | N60: ='Headcount & Payroll'!M38 -> 180.19206 | O60: ='Historical Actuals'!L120*(1+Assumptions!$G$21) -> 79.3845 | P60: =K60-M60-N60-O60 -> 251.56803
A61: 46357 | B61: Nutrition & Wellness | C61: ='Historical Actuals'!C121 -> 91856 | D61: =C61*(1+Assumptions!$B$22) -> 99204.48 | E61: ='Historical Actuals'!D121 -> 15.08 | F61: =E61*(1+Assumptions!$C$22) -> 15.6078 | G61: ='Historical Actuals'!F121 -> 7.83 | H61: =G61*(1+Assumptions!$D$22) -> 8.15886 | I61: =D61*F61/1000 -> 1548.3637 | J61: =D61*H61/1000 -> 809.39546 | K61: =I61-J61 -> 738.96822 | L61: =IFERROR(K61/I61,0) -> 0.47725753 | M61: =I61*Assumptions!$E$22 -> 131.61091 | N61: ='Headcount & Payroll'!M39 -> 169.65001 | O61: ='Historical Actuals'!L121*(1+Assumptions!$G$22) -> 71.344 | P61: =K61-M61-N61-O61 -> 366.36329
A62: 46357 | B62: Baby & Kids | C62: ='Historical Actuals'!C122 -> 75383 | D62: =C62*(1+Assumptions!$B$23) -> 80509.044 | E62: ='Historical Actuals'!D122 -> 12.65 | F62: =E62*(1+Assumptions!$C$23) -> 13.0548 | G62: ='Historical Actuals'!F122 -> 6.62 | H62: =G62*(1+Assumptions!$D$23) -> 6.8848 | I62: =D62*F62/1000 -> 1051.0295 | J62: =D62*H62/1000 -> 554.28867 | K62: =I62-J62 -> 496.7408 | L62: =IFERROR(K62/I62,0) -> 0.4726231 | M62: =I62*Assumptions!$E$23 -> 96.694711 | N62: ='Headcount & Payroll'!M40 -> 149.00023 | O62: ='Historical Actuals'!L122*(1+Assumptions!$G$23) -> 65.624 | P62: =K62-M62-N62-O62 -> 185.42186
A63: 46357 | B63: Leisure & Lifestyle | C63: ='Historical Actuals'!C123 -> 60522 | D63: =C63*(1+Assumptions!$B$24) -> 62640.27 | E63: ='Historical Actuals'!D123 -> 19.87 | F63: =E63*(1+Assumptions!$C$24) -> 20.36675 | G63: ='Historical Actuals'!F123 -> 11.19 | H63: =G63*(1+Assumptions!$D$24) -> 11.69355 | I63: =D63*F63/1000 -> 1275.7787 | J63: =D63*H63/1000 -> 732.48713 | K63: =I63-J63 -> 543.29159 | L63: =IFERROR(K63/I63,0) -> 0.42585096 | M63: =I63*Assumptions!$E$24 -> 85.477174 | N63: ='Headcount & Payroll'!M41 -> 127.77794 | O63: ='Historical Actuals'!L123*(1+Assumptions!$G$24) -> 61.655 | P63: =K63-M63-N63-O63 -> 268.38148

Sheet Rolling Forecast
A1: 2026 Rolling Forecast — Jan–Sep Actual + Oct–Dec Scenario Forecast
A3: Period | B3: Division | C3: Source | D3: Units | E3: ASP (£/unit) | F3: Revenue (£000) | G3: Unit Cost (£/unit) | H3: COGS (£000) | I3: Gross Profit (£000) | J3: GP % | K3: Marketing (£000) | L3: Payroll (£000) | M3: Other Opex (£000) | N3: EBITDA (£000) | O3: EBITDA % | P3: Scenario
A4: 46023 | B4: Personal Care | C4: Actual | D4: ='Historical Actuals'!C124 -> 116195 | E4: ='Historical Actuals'!D124 -> 8.9 | F4: ='Historical Actuals'!E124 -> 1034.1355 | G4: ='Historical Actuals'!F124 -> 4.61 | H4: ='Historical Actuals'!G124 -> 535.65895 | I4: ='Historical Actuals'!H124 -> 498.47655 | J4: ='Historical Actuals'!I124 -> 0.48202247 | K4: ='Historical Actuals'!J124 -> 77.5 | ... O4: ='Historical Actuals'!N124 -> 0.1911515 | P4: Actual
A5: 46023 | B5: Home Care | C5: Actual | D5: ='Historical Actuals'!C125 -> 96461 | E5: ='Historical Actuals'!D125 -> 10.69 | F5: ='Historical Actuals'!E125 -> 1031.1681 | G5: ='Historical Actuals'!F125 -> 5.91 | H5: ='Historical Actuals'!G125 -> 570.08451 | I5: ='Historical Actuals'!H125 -> 461.08358 | J5: ='Historical Actuals'!I125 -> 0.44714687 | K5: ='Historical Actuals'!J125 -> 65.5 | ... O5: ='Historical Actuals'!N125 -> 0.20140614 | P5: Actual
A6: 46023 | B6: Nutrition & Wellness | C6: Actual | D6: ='Historical Actuals'!C126 -> 76766 | E6: ='Historical Actuals'!D126 -> 15.49 | F6: ='Historical Actuals'!E126 -> 1189.1053 | G6: ='Historical Actuals'!F126 -> 8.19 | H6: ='Historical Actuals'!G126 -> 628.71354 | I6: ='Historical Actuals'!H126 -> 560.3918 | J6: ='Historical Actuals'!I126 -> 0.47127179 | K6: ='Historical Actuals'!J126 -> 100.8 | ... O6: ='Historical Actuals'!N126 -> 0.24530358 | P6: Actual
A7: 46023 | B7: Baby & Kids | C7: Actual | D7: ='Historical Actuals'!C127 -> 63198 | E7: ='Historical Actuals'!D127 -> 13.01 | F7: ='Historical Actuals'!E127 -> 822.20598 | G7: ='Historical Actuals'!F127 -> 6.86 | H7: ='Historical Actuals'!G127 -> 433.53828 | I7: ='Historical Actuals'!H127 -> 388.6677 | J7: ='Historical Actuals'!I127 -> 0.4727133 | K7: ='Historical Actuals'!J127 -> 79.1 | ... O7: ='Historical Actuals'!N127 -> 0.18665359 | P7: Actual
A8: 46023 | B8: Leisure & Lifestyle | C8: Actual | D8: ='Historical Actuals'!C128 -> 50047 | E8: ='Historical Actuals'!D128 -> 20.66 | F8: ='Historical Actuals'!E128 -> 1033.971 | G8: ='Historical Actuals'!F128 -> 11.82 | H8: ='Historical Actuals'!G128 -> 591.55554 | I8: ='Historical Actuals'!H128 -> 442.41548 | J8: ='Historical Actuals'!I128 -> 0.42787996 | K8: ='Historical Actuals'!J128 -> 70.9 | ... O8: ='Historical Actuals'!N128 -> 0.2208142 | P8: Actual
A9: 46054 | B9: Personal Care | C9: Actual | D9: ='Historical Actuals'!C129 -> 120677 | E9: ='Historical Actuals'!D129 -> 8.9 | F9: ='Historical Actuals'!E129 -> 1074.0253 | G9: ='Historical Actuals'!F129 -> 4.56 | H9: ='Historical Actuals'!G129 -> 550.28712 | I9: ='Historical Actuals'!H129 -> 523.73818 | J9: ='Historical Actuals'!I129 -> 0.48764045 | K9: ='Historical Actuals'!J129 -> 79.7 | ... O9: ='Historical Actuals'!N129 -> 0.20720013 | P9: Actual
A10: 46054 | B10: Home Care | C10: Actual | D10: ='Historical Actuals'!C130 -> 97652 | E10: ='Historical Actuals'!D130 -> 10.72 | F10: ='Historical Actuals'!E130 -> 1046.8294 | G10: ='Historical Actuals'!F130 -> 5.93 | H10: ='Historical Actuals'!G130 -> 579.07636 | I10: ='Historical Actuals'!H130 -> 467.75308 | J10: ='Historical Actuals'!I130 -> 0.44682836 | K10: ='Historical Actuals'!J130 -> 62.4 | ... O10: ='Historical Actuals'!N130 -> 0.20638804 | P10: Actual
A11: 46054 | B11: Nutrition & Wellness | C11: Actual | D11: ='Historical Actuals'!C131 -> 77584 | E11: ='Historical Actuals'!D131 -> 15.5 | F11: ='Historical Actuals'!E131 -> 1202.552 | G11: ='Historical Actuals'!F131 -> 8.19 | H11: ='Historical Actuals'!G131 -> 635.41296 | I11: ='Historical Actuals'!H131 -> 567.13904 | J11: ='Historical Actuals'!I131 -> 0.4716129 | K11: ='Historical Actuals'!J131 -> 106.6 | ... O11: ='Historical Actuals'!N131 -> 0.24101996 | P11: Actual
A12: 46054 | B12: Baby & Kids | C12: Actual | D12: ='Historical Actuals'!C132 -> 63523 | E12: ='Historical Actuals'!D132 -> 13.14 | F12: ='Historical Actuals'!E132 -> 834.69222 | G12: ='Historical Actuals'!F132 -> 6.85 | H12: ='Historical Actuals'!G132 -> 435.13255 | I12: ='Historical Actuals'!H132 -> 399.55967 | J12: ='Historical Actuals'!I132 -> 0.47869102 | K12: ='Historical Actuals'!J132 -> 72.8 | ... O12: ='Historical Actuals'!N132 -> 0.20613547 | P12: Actual
A13: 46054 | B13: Leisure & Lifestyle | C13: Actual | D13: ='Historical Actuals'!C133 -> 52083 | E13: ='Historical Actuals'!D133 -> 20.38 | F13: ='Historical Actuals'!E133 -> 1061.4515 | G13: ='Historical Actuals'!F133 -> 11.87 | H13: ='Historical Actuals'!G133 -> 618.22521 | I13: ='Historical Actuals'!H133 -> 443.22633 | J13: ='Historical Actuals'!I133 -> 0.41756624 | K13: ='Historical Actuals'!J133 -> 76.9 | ... O13: ='Historical Actuals'!N133 -> 0.21105658 | P13: Actual
A14: 46082 | B14: Personal Care | C14: Actual | D14: ='Historical Actuals'!C134 -> 130294 | E14: ='Historical Actuals'!D134 -> 8.84 | F14: ='Historical Actuals'!E134 -> 1151.799 | G14: ='Historical Actuals'!F134 -> 4.6 | H14: ='Historical Actuals'!G134 -> 599.3524 | I14: ='Historical Actuals'!H134 -> 552.44656 | J14: ='Historical Actuals'!I134 -> 0.47963801 | K14: ='Historical Actuals'!J134 -> 85.3 | ... O14: ='Historical Actuals'!N134 -> 0.2163108 | P14: Actual
A15: 46082 | B15: Home Care | C15: Actual | D15: ='Historical Actuals'!C135 -> 104872 | E15: ='Historical Actuals'!D135 -> 10.69 | F15: ='Historical Actuals'!E135 -> 1121.0817 | G15: ='Historical Actuals'!F135 -> 5.98 | H15: ='Historical Actuals'!G135 -> 627.13456 | I15: ='Historical Actuals'!H135 -> 493.94712 | J15: ='Historical Actuals'!I135 -> 0.44059869 | K15: ='Historical Actuals'!J135 -> 67.1 | ... O15: ='Historical Actuals'!N135 -> 0.2116234 | P15: Actual
... A48: 46266 | B48: Leisure & Lifestyle | C48: Actual | D48: ='Historical Actuals'!C168 -> 55276 | E48: ='Historical Actuals'!D168 -> 20.59 | F48: ='Historical Actuals'!E168 -> 1138.1328 | G48: ='Historical Actuals'!F168 -> 11.85 | H48: ='Historical Actuals'!G168 -> 655.0206 | I48: ='Historical Actuals'!H168 -> 483.11224 | J48: ='Historical Actuals'!I168 -> 0.4244779 | K48: ='Historical Actuals'!J168 -> 76.4 | ... O48: ='Historical Actuals'!N168 -> 0.23109099 | P48: Actual
A49: 46296 | B49: Personal Care | C49: Forecast | D49: ='Budget 2026'!D49*Assumptions!$B$16 -> 139809.65 | E49: ='Budget 2026'!F49*Assumptions!$C$16 -> 8.8786 | F49: =D49*E49/1000 -> 1241.314 | G49: ='Budget 2026'!H49*Assumptions!$D$16 -> 4.54365 | H49: =D49*G49/1000 -> 635.24614 | I49: =F49-H49 -> 606.06786 | J49: =IFERROR(I49/F49,0) -> 0.48824702 | K49: ='Budget 2026'!M49*Assumptions!$E$16 -> 90.615922 | L49: ='Budget 2026'!N49 -> 215.50003 | M49: ='Budget 2026'!O49*Assumptions!$F$16 -> 88.2855 | N49: =I49-K49-L49-M49 -> 211.66641 | O49: =IFERROR(N49/F49,0) -> 0.17051802 | P49: =Assumptions!$B$6 -> Base
A50: 46296 | B50: Home Care | C50: Forecast | D50: ='Budget 2026'!D50*Assumptions!$B$16 -> 103545.62 | E50: ='Budget 2026'!F50*Assumptions!$C$16 -> 10.67064 | F50: =D50*E50/1000 -> 1104.8981 | G50: ='Budget 2026'!H50*Assumptions!$D$16 -> 5.98926 | H50: =D50*G50/1000 -> 620.16166 | I50: =F50-H50 -> 484.73641 | J50: =IFERROR(I50/F50,0) -> 0.43871595 | K50: ='Budget 2026'!M50*Assumptions!$E$16 -> 67.398783 | L50: ='Budget 2026'!N50 -> 180.19206 | M50: ='Budget 2026'!O50*Assumptions!$F$16 -> 77.418 | N50: =I50-K50-L50-M50 -> 159.72757 | O50: =IFERROR(N50/F50,0) -> 0.14456317 | P50: =Assumptions!$B$6 -> Base
A51: 46296 | B51: Nutrition & Wellness | C51: Forecast | D51: ='Budget 2026'!D51*Assumptions!$B$16 -> 86661.36 | E51: ='Budget 2026'!F51*Assumptions!$C$16 -> 15.61815 | F51: =D51*E51/1000 -> 1353.4901 | G51: ='Budget 2026'!H51*Assumptions!$D$16 -> 8.29432 | H51: =D51*G51/1000 -> 718.79705 | I51: =F51-H51 -> 634.69307 | J51: =IFERROR(I51/F51,0) -> 0.4689307 | K51: ='Budget 2026'!M51*Assumptions!$E$16 -> 115.04666 | L51: ='Budget 2026'!N51 -> 169.65001 | M51: ='Budget 2026'!O51*Assumptions!$F$16 -> 71.448 | N51: =I51-K51-L51-M51 -> 278.5484 | O51: =IFERROR(N51/F51,0) -> 0.2058001 | P51: =Assumptions!$B$6 -> Base
A52: 46296 | B52: Baby & Kids | C52: Forecast | D52: ='Budget 2026'!D52*Assumptions!$B$16 -> 71867.856 | E52: ='Budget 2026'!F52*Assumptions!$C$16 -> 13.11672 | F52: =D52*E52/1000 -> 942.67054 | G52: ='Budget 2026'!H52*Assumptions!$D$16 -> 6.8016 | H52: =D52*G52/1000 -> 488.81641 | I52: =F52-H52 -> 453.85413 | J52: =IFERROR(I52/F52,0) -> 0.48145573 | K52: ='Budget 2026'!M52*Assumptions!$E$16 -> 86.72569 | L52: ='Budget 2026'!N52 -> 149.00023 | M52: ='Budget 2026'!O52*Assumptions!$F$16 -> 65.52 | N52: =I52-K52-L52-M52 -> 152.60822 | O52: =IFERROR(N52/F52,0) -> 0.16188924 | P52: =Assumptions!$B$6 -> Base
A53: 46296 | B53: Leisure & Lifestyle | C53: Forecast | D53: ='Budget 2026'!D53*Assumptions!$B$16 -> 56477.88 | E53: ='Budget 2026'!F53*Assumptions!$C$16 -> 20.4795 | F53: =D53*E53/1000 -> 1156.6387 | G53: ='Budget 2026'!H53*Assumptions!$D$16 -> 11.704 | H53: =D53*G53/1000 -> 661.01711 | I53: =F53-H53 -> 495.62164 | J53: =IFERROR(I53/F53,0) -> 0.42850167 | K53: ='Budget 2026'!M53*Assumptions!$E$16 -> 77.494796 | L53: ='Budget 2026'!N53 -> 127.77794 | M53: ='Budget 2026'!O53*Assumptions!$F$16 -> 61.237 | N53: =I53-K53-L53-M53 -> 229.1119 | O53: =IFERROR(N53/F53,0) -> 0.19808424 | P53: =Assumptions!$B$6 -> Base
A54: 46327 | B54: Personal Care | C54: Forecast | D54: ='Budget 2026'!D54*Assumptions!$B$16 -> 146344.32 | E54: ='Budget 2026'!F54*Assumptions!$C$16 -> 8.8477 | F54: =D54*E54/1000 -> 1294.8107 | G54: ='Budget 2026'!H54*Assumptions!$D$16 -> 4.6161 | H54: =D54*G54/1000 -> 675.54004 | I54: =F54-H54 -> 619.27065 | J54: =IFERROR(I54/F54,0) -> 0.47827119 | K54: ='Budget 2026'!M54*Assumptions!$E$16 -> 94.52118 | L54: ='Budget 2026'!N54 -> 215.50003 | M54: ='Budget 2026'!O54*Assumptions!$F$16 -> 90.666 | N54: =I54-K54-L54-M54 -> 218.58343 | O54: =IFERROR(N54/F54,0) -> 0.16881497 | P54: =Assumptions!$B$6 -> Base
A55: 46327 | B55: Home Care | C55: Forecast | D55: ='Budget 2026'!D55*Assumptions!$B$16 -> 116391.4 | E55: ='Budget 2026'!F55*Assumptions!$C$16 -> 10.71176 | F55: =D55*E55/1000 -> 1246.7567 | G55: ='Budget 2026'!H55*Assumptions!$D$16 -> 5.97888 | H55: =D55*G55/1000 -> 695.89021 | I55: =F55-H55 -> 550.86653 | J55: =IFERROR(I55/F55,0) -> 0.44183962 | K55: ='Budget 2026'!M55*Assumptions!$E$16 -> 76.052161 | L55: ='Budget 2026'!N55 -> 180.19206 | M55: ='Budget 2026'!O55*Assumptions!$F$16 -> 79.074 | N55: =I55-K55-L55-M55 -> 215.54831 | O55: =IFERROR(N55/F55,0) -> 0.17288722 | P55: =Assumptions!$B$6 -> Base
A56: 46327 | B56: Nutrition & Wellness | C56: Forecast | D56: ='Budget 2026'!D56*Assumptions!$B$16 -> 95212.8 | E56: ='Budget 2026'!F56*Assumptions!$C$16 -> 15.6699 | F56: =D56*E56/1000 -> 1491.9751 | G56: ='Budget 2026'!H56*Assumptions!$D$16 -> 8.24222 | H56: =D56*G56/1000 -> 784.76484 | I56: =F56-H56 -> 707.21021 | J56: =IFERROR(I56/F56,0) -> 0.47400941 | K56: ='Budget 2026'!M56*Assumptions!$E$16 -> 126.81788 | L56: ='Budget 2026'!N56 -> 169.65001 | M56: ='Budget 2026'!O56*Assumptions!$F$16 -> 73.32 | N56: =I56-K56-L56-M56 -> 337.42232 | O56: =IFERROR(N56/F56,0) -> 0.22615815 | P56: =Assumptions!$B$6 -> Base
A57: 46327 | B57: Baby & Kids | C57: Forecast | D57: ='Budget 2026'!D57*Assumptions!$B$16 -> 75976.452 | E57: ='Budget 2026'!F57*Assumptions!$C$16 -> 13.06512 | F57: =D57*E57/1000 -> 992.64146 | G57: ='Budget 2026'!H57*Assumptions!$D$16 -> 6.8848 | H57: =D57*G57/1000 -> 523.08268 | I57: =F57-H57 -> 469.55879 | J57: =IFERROR(I57/F57,0) -> 0.47303967 | K57: ='Budget 2026'!M57*Assumptions!$E$16 -> 91.323015 | L57: ='Budget 2026'!N57 -> 149.00023 | M57: ='Budget 2026'!O57*Assumptions!$F$16 -> 63.752 | N57: =I57-K57-L57-M57 -> 165.48354 | O57: =IFERROR(N57/F57,0) -> 0.16671029 | P57: =Assumptions!$B$6 -> Base
A58: 46327 | B58: Leisure & Lifestyle | C58: Forecast | D58: ='Budget 2026'!D58*Assumptions!$B$16 -> 57410.415 | E58: ='Budget 2026'!F58*Assumptions!$C$16 -> 20.48975 | F58: =D58*E58/1000 -> 1176.3251 | G58: ='Budget 2026'!H58*Assumptions!$D$16 -> 11.8503 | H58: =D58*G58/1000 -> 680.33064 | I58: =F58-H58 -> 495.99441 | J58: =IFERROR(I58/F58,0) -> 0.42164741 | K58: ='Budget 2026'!M58*Assumptions!$E$16 -> 78.813778 | L58: ='Budget 2026'!N58 -> 127.77794 | M58: ='Budget 2026'!O58*Assumptions!$F$16 -> 63.6405 | N58: =I58-K58-L58-M58 -> 225.76219 | O58: =IFERROR(N58/F58,0) -> 0.19192161 | P58: =Assumptions!$B$6 -> Base
A59: 46357 | B59: Personal Care | C59: Forecast | D59: ='Budget 2026'!D59*Assumptions!$B$16 -> 155689.51 | E59: ='Budget 2026'!F59*Assumptions!$C$16 -> 8.8683 | F59: =D59*E59/1000 -> 1380.7013 | G59: ='Budget 2026'!H59*Assumptions!$D$16 -> 4.58505 | H59: =D59*G59/1000 -> 713.84421 | I59: =F59-H59 -> 666.85712 | J59: =IFERROR(I59/F59,0) -> 0.48298434 | K59: ='Budget 2026'!M59*Assumptions!$E$16 -> 100.7912 | L59: ='Budget 2026'!N59 -> 215.50003 | M59: ='Budget 2026'!O59*Assumptions!$F$16 -> 90.7695 | N59: =I59-K59-L59-M59 -> 259.79639 | O59: =IFERROR(N59/F59,0) -> 0.18816262 | P59: =Assumptions!$B$6 -> Base
A60: 46357 | B60: Home Care | C60: Forecast | D60: ='Budget 2026'!D60*Assumptions!$B$16 -> 121536.8 | E60: ='Budget 2026'!F60*Assumptions!$C$16 -> 10.83512 | F60: =D60*E60/1000 -> 1316.8658 | G60: ='Budget 2026'!H60*Assumptions!$D$16 -> 5.9685 | H60: =D60*G60/1000 -> 725.39237 | I60: =F60-H60 -> 591.4734 | J60: =IFERROR(I60/F60,0) -> 0.44915239 | K60: ='Budget 2026'!M60*Assumptions!$E$16 -> 80.328812 | L60: ='Budget 2026'!N60 -> 180.19206 | M60: ='Budget 2026'!O60*Assumptions!$F$16 -> 79.3845 | N60: =I60-K60-L60-M60 -> 251.56803 | O60: =IFERROR(N60/F60,0) -> 0.19103544 | P60: =Assumptions!$B$6 -> Base
... A63: 46357 | B63: Leisure & Lifestyle | C63: Forecast | D63: ='Budget 2026'!D63*Assumptions!$B$16 -> 62640.27 | E63: ='Budget 2026'!F63*Assumptions!$C$16 -> 20.36675 | F63: =D63*E63/1000 -> 1275.7787 | G63: ='Budget 2026'!H63*Assumptions!$D$16 -> 11.69355 | H63: =D63*G63/1000 -> 732.48713 | I63: =F63-H63 -> 543.29159 | J63: =IFERROR(I63/F63,0) -> 0.42585096 | K63: ='Budget 2026'!M63*Assumptions!$E$16 -> 85.477174 | L63: ='Budget 2026'!N63 -> 127.77794 | M63: ='Budget 2026'!O63*Assumptions!$F$16 -> 61.655 | N63: =I63-K63-L63-M63 -> 268.38148 | O63: =IFERROR(N63/F63,0) -> 0.21036679 | P63: =Assumptions!$B$6 -> Base

Sheet Variance Analysis
A1: Budget vs Rolling Forecast — Variance Analysis
A3: Monthly performance bridge
A4: Month | B4: Budget Revenue | C4: Forecast Revenue | D4: Revenue Var £ | E4: Revenue Var % | F4: Budget GP | G4: Forecast GP | H4: GP Var £ | I4: Budget EBITDA | J4: Forecast EBITDA | K4: EBITDA Var £ | L4: Budget EBITDA % | M4: Forecast EBITDA %
A5: 46023 | B5: =SUM('Budget 2026'!I4:I8) -> 5159.2979 | C5: =SUM('Rolling Forecast'!F4:F8) -> 5110.5859 | D5: =C5-B5 -> -48.711978 | E5: =IFERROR(D5/B5,0) -> -0.0094415905 | F5: =SUM('Budget 2026'!K4:K8) -> 2397.5828 | G5: =SUM('Rolling Forecast'!I4:I8) -> 2351.0351 | H5: =G5-F5 -> -46.547644 | I5: =SUM('Budget 2026'!P4:P8) -> 824.27256 | J5: =SUM('Rolling Forecast'!N4:N8) -> 1078.8351 | K5: =J5-I5 -> 254.56255 | L5: =IFERROR(I5/B5,0) -> 0.15976448 | M5: =IFERROR(J5/C5,0) -> 0.21109813
A6: 46054 | B6: =SUM('Budget 2026'!I9:I13) -> 5273.8634 | C6: =SUM('Rolling Forecast'!F9:F13) -> 5219.5505 | D6: =C6-B6 -> -54.312858 | E6: =IFERROR(D6/B6,0) -> -0.010298495 | F6: =SUM('Budget 2026'!K9:K13) -> 2435.3654 | G6: =SUM('Rolling Forecast'!I9:I13) -> 2401.4163 | H6: =G6-F6 -> -33.949148 | I6: =SUM('Budget 2026'!P9:P13) -> 860.69777 | J6: =SUM('Rolling Forecast'!N9:N13) -> 1124.5163 | K6: =J6-I6 -> 263.81853 | L6: =IFERROR(I6/B6,0) -> 0.16320062 | M6: =IFERROR(J6/C6,0) -> 0.21544313
A7: 46082 | B7: =SUM('Budget 2026'!I14:I18) -> 5497.3196 | C7: =SUM('Rolling Forecast'!F14:F18) -> 5543.7374 | D7: =C7-B7 -> 46.417864 | E7: =IFERROR(D7/B7,0) -> 0.0084437267 | F7: =SUM('Budget 2026'!K14:K18) -> 2537.0929 | G7: =SUM('Rolling Forecast'!I14:I18) -> 2557.479 | H7: =G7-F7 -> 20.386092 | I7: =SUM('Budget 2026'!P14:P18) -> 886.04063 | J7: =SUM('Rolling Forecast'!N14:N18) -> 1260.079 | K7: =J7-I7 -> 374.03837 | L7: =IFERROR(I7/B7,0) -> 0.16117685 | M7: =IFERROR(J7/C7,0) -> 0.22729774
A8: 46113 | B8: =SUM('Budget 2026'!I19:I23) -> 5581.1522 | C8: =SUM('Rolling Forecast'!F19:F23) -> 5554.7515 | D8: =C8-B8 -> -26.400742 | E8: =IFERROR(D8/B8,0) -> -0.004730339 | F8: =SUM('Budget 2026'!K19:K23) -> 2576.0699 | G8: =SUM('Rolling Forecast'!I19:I23) -> 2544.7213 | H8: =G8-F8 -> -31.34864 | I8: =SUM('Budget 2026'!P19:P23) -> 920.32617 | J8: =SUM('Rolling Forecast'!N19:N23) -> 1254.3213 | K8: =J8-I8 -> 333.99512 | L8: =IFERROR(I8/B8,0) -> 0.16489895 | M8: =IFERROR(J8/C8,0) -> 0.22581051
A9: 46143 | B9: =SUM('Budget 2026'!I24:I28) -> 5627.6947 | C9: =SUM('Rolling Forecast'!F24:F28) -> 5551.7411 | D9: =C9-B9 -> -75.953628 | E9: =IFERROR(D9/B9,0) -> -0.013496402 | F9: =SUM('Budget 2026'!K24:K28) -> 2598.2407 | G9: =SUM('Rolling Forecast'!I24:I28) -> 2551.2537 | H9: =G9-F9 -> -46.986944 | I9: =SUM('Budget 2026'!P24:P28) -> 939.33632 | J9: =SUM('Rolling Forecast'!N24:N28) -> 1240.5537 | K9: =J9-I9 -> 301.21741 | L9: =IFERROR(I9/B9,0) -> 0.16691316 | M9: =IFERROR(J9/C9,0) -> 0.2234531
A10: 46174 | B10: =SUM('Budget 2026'!I29:I33) -> 5765.8793 | C10: =SUM('Rolling Forecast'!F29:F33) -> 5700.2679 | D10: =C10-B10 -> -65.611378 | E10: =IFERROR(D10/B10,0) -> -0.011379249 | F10: =SUM('Budget 2026'!K29:K33) -> 2670.2805 | G10: =SUM('Rolling Forecast'!I29:I33) -> 2639.606 | H10: =G10-F10 -> -30.674435 | I10: =SUM('Budget 2026'!P29:P33) -> 1030.3959 | J10: =SUM('Rolling Forecast'!N29:N33) -> 1345.906 | K10: =J10-I10 -> 315.51014 | L10: =IFERROR(I10/B10,0) -> 0.17870577 | M10: =IFERROR(J10/C10,0) -> 0.23611277
A11: 46204 | B11: =SUM('Budget 2026'!I34:I38) -> 5963.3308 | C11: =SUM('Rolling Forecast'!F34:F38) -> 5898.7152 | D11: =C11-B11 -> -64.615633 | E11: =IFERROR(D11/B11,0) -> -0.010835494 | F11: =SUM('Budget 2026'!K34:K38) -> 2765.6741 | G11: =SUM('Rolling Forecast'!I34:I38) -> 2717.9397 | H11: =G11-F11 -> -47.734421 | I11: =SUM('Budget 2026'!P34:P38) -> 1103.6631 | J11: =SUM('Rolling Forecast'!N34:N38) -> 1390.4397 | K11: =J11-I11 -> 286.77659 | L11: =IFERROR(I11/B11,0) -> 0.18507494 | M11: =IFERROR(J11/C11,0) -> 0.23571908
A12: 46235 | B12: =SUM('Budget 2026'!I39:I43) -> 5670.7887 | C12: =SUM('Rolling Forecast'!F39:F43) -> 5671.2931 | D12: =C12-B12 -> 0.50441215 | E12: =IFERROR(D12/B12,0) -> 8.8949207e-05 | F12: =SUM('Budget 2026'!K39:K43) -> 2598.1802 | G12: =SUM('Rolling Forecast'!I39:I43) -> 2635.7712 | H12: =G12-F12 -> 37.591032 | I12: =SUM('Budget 2026'!P39:P43) -> 954.454 | J12: =SUM('Rolling Forecast'!N39:N43) -> 1333.0712 | K12: =J12-I12 -> 378.61723 | L12: =IFERROR(I12/B12,0) -> 0.16831063 | M12: =IFERROR(J12/C12,0) -> 0.23505596
A13: 46266 | B13: =SUM('Budget 2026'!I44:I48) -> 5539.2845 | C13: =SUM('Rolling Forecast'!F44:F48) -> 5528.9505 | D13: =C13-B13 -> -10.333994 | E13: =IFERROR(D13/B13,0) -> -0.0018655828 | F13: =SUM('Budget 2026'!K44:K48) -> 2577.6748 | G13: =SUM('Rolling Forecast'!I44:I48) -> 2555.0192 | H13: =G13-F13 -> -22.655528 | I13: =SUM('Budget 2026'!P44:P48) -> 953.06336 | J13: =SUM('Rolling Forecast'!N44:N48) -> 1262.6192 | K13: =J13-I13 -> 309.55587 | L13: =IFERROR(I13/B13,0) -> 0.17205532 | M13: =IFERROR(J13/C13,0) -> 0.22836508
A14: 46296 | B14: =SUM('Budget 2026'!I49:I53) -> 5799.0115 | C14: =SUM('Rolling Forecast'!F49:F53) -> 5799.0115 | D14: =C14-B14 -> 0 | E14: =IFERROR(D14/B14,0) -> 0 | F14: =SUM('Budget 2026'!K49:K53) -> 2674.9731 | G14: =SUM('Rolling Forecast'!I49:I53) -> 2674.9731 | H14: =G14-F14 -> 0 | I14: =SUM('Budget 2026'!P49:P53) -> 1031.6625 | J14: =SUM('Rolling Forecast'!N49:N53) -> 1031.6625 | K14: =J14-I14 -> 0 | L14: =IFERROR(I14/B14,0) -> 0.17790316 | M14: =IFERROR(J14/C14,0) -> 0.17790316
A15: 46327 | B15: =SUM('Budget 2026'!I54:I58) -> 6202.509 | C15: =SUM('Rolling Forecast'!F54:F58) -> 6202.509 | D15: =C15-B15 -> 0 | E15: =IFERROR(D15/B15,0) -> 0 | F15: =SUM('Budget 2026'!K54:K58) -> 2842.9006 | G15: =SUM('Rolling Forecast'!I54:I58) -> 2842.9006 | H15: =G15-F15 -> 0 | I15: =SUM('Budget 2026'!P54:P58) -> 1162.7998 | J15: =SUM('Rolling Forecast'!N54:N58) -> 1162.7998 | K15: =J15-I15 -> 0 | L15: =IFERROR(I15/B15,0) -> 0.18747249 | M15: =IFERROR(J15/C15,0) -> 0.18747249
A16: 46357 | B16: =SUM('Budget 2026'!I59:I63) -> 6572.739 | C16: =SUM('Rolling Forecast'!F59:F63) -> 6572.739 | D16: =C16-B16 -> 0 | E16: =IFERROR(D16/B16,0) -> 0 | F16: =SUM('Budget 2026'!K59:K63) -> 3037.3311 | G16: =SUM('Rolling Forecast'!I59:I63) -> 3037.3311 | H16: =G16-F16 -> 0 | I16: =SUM('Budget 2026'!P59:P63) -> 1331.531 | J16: =SUM('Rolling Forecast'!N59:N63) -> 1331.531 | K16: =J16-I16 -> 0 | L16: =IFERROR(I16/B16,0) -> 0.20258389 | M16: =IFERROR(J16/C16,0) -> 0.20258389
A19: Full-year summary by division
A20: Division | B20: Budget Revenue | C20: Forecast Revenue | D20: Revenue Var £ | E20: Budget EBITDA | F20: Forecast EBITDA | G20: EBITDA Var £
A21: Personal Care | B21: ='Budget 2026'!I4+'Budget 2026'!I9+'Budget 2026'!I14+'Budget 2026'!I19+'Budget 2026'!I24+'Budget 2026'!I29+'Budget 2026'!I34+'Budget 2026'!I39+'Budget 2026'!I44+'Budget 2026'!I49+'Budget 2026'!I54+'Budget 2026'!I59 -> 14398.501 | C21: ='Rolling Forecast'!F4+'Rolling Forecast'!F9+'Rolling Forecast'!F14+'Rolling Forecast'!F19+'Rolling Forecast'!F24+'Rolling Forecast'!F29+'Rolling Forecast'!F34+'Rolling Forecast'!F39+'Rolling Forecast'!F44+'Rolling Forecast'!F49+'Rolling Forecast'!F54+'Rolling Forecast'!F59 -> 14213.227 | D21: =C21-B21 -> -185.27342 | E21: ='Budget 2026'!P4+'Budget 2026'!P9+'Budget 2026'!P14+'Budget 2026'!P19+'Budget 2026'!P24+'Budget 2026'!P29+'Budget 2026'!P34+'Budget 2026'!P39+'Budget 2026'!P44+'Budget 2026'!P49+'Budget 2026'!P54+'Budget 2026'!P59 -> 2246.3856 | F21: ='Rolling Forecast'!N4+'Rolling Forecast'!N9+'Rolling Forecast'!N14+'Rolling Forecast'!N19+'Rolling Forecast'!N24+'Rolling Forecast'!N29+'Rolling Forecast'!N34+'Rolling Forecast'!N39+'Rolling Forecast'!N44+'Rolling Forecast'!N49+'Rolling Forecast'!N54+'Rolling Forecast'!N59 -> 2922.7013 | G21: =F21-E21 -> 676.3157
A22: Home Care | B22: ='Budget 2026'!I5+'Budget 2026'!I10+'Budget 2026'!I15+'Budget 2026'!I20+'Budget 2026'!I25+'Budget 2026'!I30+'Budget 2026'!I35+'Budget 2026'!I40+'Budget 2026'!I45+'Budget 2026'!I50+'Budget 2026'!I55+'Budget 2026'!I60 -> 13582.084 | C22: ='Rolling Forecast'!F5+'Rolling Forecast'!F10+'Rolling Forecast'!F15+'Rolling Forecast'!F20+'Rolling Forecast'!F25+'Rolling Forecast'!F30+'Rolling Forecast'!F35+'Rolling Forecast'!F40+'Rolling Forecast'!F45+'Rolling Forecast'!F50+'Rolling Forecast'!F55+'Rolling Forecast'!F60 -> 13627.938 | D22: =C22-B22 -> 45.853575 | E22: ='Budget 2026'!P5+'Budget 2026'!P10+'Budget 2026'!P15+'Budget 2026'!P20+'Budget 2026'!P25+'Budget 2026'!P30+'Budget 2026'!P35+'Budget 2026'!P40+'Budget 2026'!P45+'Budget 2026'!P50+'Budget 2026'!P55+'Budget 2026'!P60 -> 2100.1816 | F22: ='Rolling Forecast'!N5+'Rolling Forecast'!N10+'Rolling Forecast'!N15+'Rolling Forecast'!N20+'Rolling Forecast'!N25+'Rolling Forecast'!N30+'Rolling Forecast'!N35+'Rolling Forecast'!N40+'Rolling Forecast'!N45+'Rolling Forecast'!N50+'Rolling Forecast'!N55+'Rolling Forecast'!N60 -> 2752.5665 | G22: =F22-E22 -> 652.38488
A23: Nutrition & Wellness | B23: ='Budget 2026'!I6+'Budget 2026'!I11+'Budget 2026'!I16+'Budget 2026'!I21+'Budget 2026'!I26+'Budget 2026'!I31+'Budget 2026'!I36+'Budget 2026'!I41+'Budget 2026'!I46+'Budget 2026'!I51+'Budget 2026'!I56+'Budget 2026'!I61 -> 16043.681 | C23: ='Rolling Forecast'!F6+'Rolling Forecast'!F11+'Rolling Forecast'!F16+'Rolling Forecast'!F21+'Rolling Forecast'!F26+'Rolling Forecast'!F31+'Rolling Forecast'!F36+'Rolling Forecast'!F41+'Rolling Forecast'!F46+'Rolling Forecast'!F51+'Rolling Forecast'!F56+'Rolling Forecast'!F61 -> 15755.544 | D23: =C23-B23 -> -288.13647 | E23: ='Budget 2026'!P6+'Budget 2026'!P11+'Budget 2026'!P16+'Budget 2026'!P21+'Budget 2026'!P26+'Budget 2026'!P31+'Budget 2026'!P36+'Budget 2026'!P41+'Budget 2026'!P46+'Budget 2026'!P51+'Budget 2026'!P56+'Budget 2026'!P61 -> 3357.7006 | F23: ='Rolling Forecast'!N6+'Rolling Forecast'!N11+'Rolling Forecast'!N16+'Rolling Forecast'!N21+'Rolling Forecast'!N26+'Rolling Forecast'!N31+'Rolling Forecast'!N36+'Rolling Forecast'!N41+'Rolling Forecast'!N46+'Rolling Forecast'!N51+'Rolling Forecast'!N56+'Rolling Forecast'!N61 -> 3891.0698 | G23: =F23-E23 -> 533.36923
A24: Baby & Kids | B24: ='Budget 2026'!I7+'Budget 2026'!I12+'Budget 2026'!I17+'Budget 2026'!I22+'Budget 2026'!I27+'Budget 2026'!I32+'Budget 2026'!I37+'Budget 2026'!I42+'Budget 2026'!I47+'Budget 2026'!I52+'Budget 2026'!I57+'Budget 2026'!I62 -> 11170.966 | C24: ='Rolling Forecast'!F7+'Rolling Forecast'!F12+'Rolling Forecast'!F17+'Rolling Forecast'!F22+'Rolling Forecast'!F27+'Rolling Forecast'!F32+'Rolling Forecast'!F37+'Rolling Forecast'!F42+'Rolling Forecast'!F47+'Rolling Forecast'!F52+'Rolling Forecast'!F57+'Rolling Forecast'!F62 -> 11069.93 | D24: =C24-B24 -> -101.03541 | E24: ='Budget 2026'!P7+'Budget 2026'!P12+'Budget 2026'!P17+'Budget 2026'!P22+'Budget 2026'!P27+'Budget 2026'!P32+'Budget 2026'!P37+'Budget 2026'!P42+'Budget 2026'!P47+'Budget 2026'!P52+'Budget 2026'!P57+'Budget 2026'!P62 -> 1723.1688 | F24: ='Rolling Forecast'!N7+'Rolling Forecast'!N12+'Rolling Forecast'!N17+'Rolling Forecast'!N22+'Rolling Forecast'!N27+'Rolling Forecast'!N32+'Rolling Forecast'!N37+'Rolling Forecast'!N42+'Rolling Forecast'!N47+'Rolling Forecast'!N52+'Rolling Forecast'!N57+'Rolling Forecast'!N62 -> 2194.4725 | G24: =F24-E24 -> 471.30376
A25: Leisure & Lifestyle | B25: ='Budget 2026'!I8+'Budget 2026'!I13+'Budget 2026'!I18+'Budget 2026'!I23+'Budget 2026'!I28+'Budget 2026'!I33+'Budget 2026'!I38+'Budget 2026'!I43+'Budget 2026'!I48+'Budget 2026'!I53+'Budget 2026'!I58+'Budget 2026'!I63 -> 13457.639 | C25: ='Rolling Forecast'!F8+'Rolling Forecast'!F13+'Rolling Forecast'!F18+'Rolling Forecast'!F23+'Rolling Forecast'!F28+'Rolling Forecast'!F33+'Rolling Forecast'!F38+'Rolling Forecast'!F43+'Rolling Forecast'!F48+'Rolling Forecast'!F53+'Rolling Forecast'!F58+'Rolling Forecast'!F63 -> 13687.213 | D25: =C25-B25 -> 229.57379 | E25: ='Budget 2026'!P8+'Budget 2026'!P13+'Budget 2026'!P18+'Budget 2026'!P23+'Budget 2026'!P28+'Budget 2026'!P33+'Budget 2026'!P38+'Budget 2026'!P43+'Budget 2026'!P48+'Budget 2026'!P53+'Budget 2026'!P58+'Budget 2026'!P63 -> 2570.8065 | F25: ='Rolling Forecast'!N8+'Rolling Forecast'!N13+'Rolling Forecast'!N18+'Rolling Forecast'!N23+'Rolling Forecast'!N28+'Rolling Forecast'!N33+'Rolling Forecast'!N38+'Rolling Forecast'!N43+'Rolling Forecast'!N48+'Rolling Forecast'!N53+'Rolling Forecast'!N58+'Rolling Forecast'!N63 -> 3055.5248 | G25: =F25-E25 -> 484.71825

Sheet Dashboard
A1: Executive FP&A Dashboard — FY2026
A3: ="Scenario: "&Assumptions!B6&" | Rolling forecast: Jan-Sep actual + Oct-Dec forecast" -> Scenario: Base | Rolling forecast: Jan-Sep actual + Oct-Dec forecast
A5: FY26 Budget Revenue | D5: FY26 Forecast Revenue | G5: Revenue Variance | J5: Forecast GP %
A6: =ROUND(SUM('Budget 2026'!I4:I63),0) -> 68653 | D6: =ROUND(SUM('Rolling Forecast'!F4:F63),0) -> 68354 | G6: =ROUND(D6-A6,0) -> -299 | J6: =SUM('Rolling Forecast'!I4:I63)/SUM('Rolling Forecast'!F4:F63) -> 0.46097543
A9: FY26 Budget EBITDA | D9: FY26 Forecast EBITDA | G9: EBITDA Variance | J9: Forecast EBITDA %
A10: =ROUND(SUM('Budget 2026'!P4:P63),0) -> 11998 | D10: =ROUND(SUM('Rolling Forecast'!N4:N63),0) -> 14816 | G10: =ROUND(D10-A10,0) -> 2818 | J10: =SUM('Rolling Forecast'!N4:N63)/SUM('Rolling Forecast'!F4:F63) -> 0.21675933
A14: Monthly Revenue — Budget vs Rolling Forecast (£000)
A15: Month | B15: Budget Revenue | C15: Forecast Revenue
A16: Jan | B16: =ROUND('Variance Analysis'!B5,0) -> 5159 | C16: =ROUND('Variance Analysis'!C5,0) -> 5111
A17: Feb | B17: =ROUND('Variance Analysis'!B6,0) -> 5274 | C17: =ROUND('Variance Analysis'!C6,0) -> 5220
A18: Mar | B18: =ROUND('Variance Analysis'!B7,0) -> 5497 | C18: =ROUND('Variance Analysis'!C7,0) -> 5544
A19: Apr | B19: =ROUND('Variance Analysis'!B8,0) -> 5581 | C19: =ROUND('Variance Analysis'!C8,0) -> 5555
A20: May | B20: =ROUND('Variance Analysis'!B9,0) -> 5628 | C20: =ROUND('Variance Analysis'!C9,0) -> 5552
A21: Jun | B21: =ROUND('Variance Analysis'!B10,0) -> 5766 | C21: =ROUND('Variance Analysis'!C10,0) -> 5700
A22: Jul | B22: =ROUND('Variance Analysis'!B11,0) -> 5963 | C22: =ROUND('Variance Analysis'!C11,0) -> 5899
A23: Aug | B23: =ROUND('Variance Analysis'!B12,0) -> 5671 | C23: =ROUND('Variance Analysis'!C12,0) -> 5671
A24: Sep | B24: =ROUND('Variance Analysis'!B13,0) -> 5539 | C24: =ROUND('Variance Analysis'!C13,0) -> 5529
A25: Oct | B25: =ROUND('Variance Analysis'!B14,0) -> 5799 | C25: =ROUND('Variance Analysis'!C14,0) -> 5799
A26: Nov | B26: =ROUND('Variance Analysis'!B15,0) -> 6203 | C26: =ROUND('Variance Analysis'!C15,0) -> 6203
A27: Dec | B27: =ROUND('Variance Analysis'!B16,0) -> 6573 | C27: =ROUND('Variance Analysis'!C16,0) -> 6573
A30: FY2026 Revenue by Division (£000)
A31: Division | B31: Budget Revenue | C31: Forecast Revenue
A32: Personal Care | B32: =ROUND('Variance Analysis'!B21,0) -> 14399 | C32: =ROUND('Variance Analysis'!C21,0) -> 14213
A33: Home Care | B33: =ROUND('Variance Analysis'!B22,0) -> 13582 | C33: =ROUND('Variance Analysis'!C22,0) -> 13628
A34: Nutrition & Wellness | B34: =ROUND('Variance Analysis'!B23,0) -> 16044 | C34: =ROUND('Variance Analysis'!C23,0) -> 15756
A35: Baby & Kids | B35: =ROUND('Variance Analysis'!B24,0) -> 11171 | C35: =ROUND('Variance Analysis'!C24,0) -> 11070
A36: Leisure & Lifestyle | B36: =ROUND('Variance Analysis'!B25,0) -> 13458 | C36: =ROUND('Variance Analysis'!C25,0) -> 13687
A39: Monthly EBITDA — Budget vs Rolling Forecast (£000)
A40: Month | B40: Budget EBITDA | C40: Forecast EBITDA
A41: Jan | B41: =ROUND('Variance Analysis'!I5,0) -> 824 | C41: =ROUND('Variance Analysis'!J5,0) -> 1079
A42: Feb | B42: =ROUND('Variance Analysis'!I6,0) -> 861 | C42: =ROUND('Variance Analysis'!J6,0) -> 1125
A43: Mar | B43: =ROUND('Variance Analysis'!I7,0) -> 886 | C43: =ROUND('Variance Analysis'!J7,0) -> 1260
A44: Apr | B44: =ROUND('Variance Analysis'!I8,0) -> 920 | C44: =ROUND('Variance Analysis'!J8,0) -> 1254
A45: May | B45: =ROUND('Variance Analysis'!I9,0) -> 939 | C45: =ROUND('Variance Analysis'!J9,0) -> 1241
A46: Jun | B46: =ROUND('Variance Analysis'!I10,0) -> 1030 | C46: =ROUND('Variance Analysis'!J10,0) -> 1346
A47: Jul | B47: =ROUND('Variance Analysis'!I11,0) -> 1104 | C47: =ROUND('Variance Analysis'!J11,0) -> 1390
A48: Aug | B48: =ROUND('Variance Analysis'!I12,0) -> 954 | C48: =ROUND('Variance Analysis'!J12,0) -> 1333
A49: Sep | B49: =ROUND('Variance Analysis'!I13,0) -> 953 | C49: =ROUND('Variance Analysis'!J13,0) -> 1263
A50: Oct | B50: =ROUND('Variance Analysis'!I14,0) -> 1032 | C50: =ROUND('Variance Analysis'!J14,0) -> 1032
A51: Nov | B51: =ROUND('Variance Analysis'!I15,0) -> 1163 | C51: =ROUND('Variance Analysis'!J15,0) -> 1163
A52: Dec | B52: =ROUND('Variance Analysis'!I16,0) -> 1332 | C52: =ROUND('Variance Analysis'!J16,0) -> 1332
A55: Management interpretation prompts
A56: 1 | B56: Which months drive the largest revenue variance?
A57: 2 | B57: Which division contributes most to EBITDA variance?
A58: 3 | B58: Is performance being driven by volume, price, unit-cost inflation or operating spend?
A59: 4 | B59: How does the Q4 outlook change under Base, Upside and Downside scenarios?
A60: 5 | B60: What actions should management take before year-end?
A64: Build 2 — Workforce, Working Capital & Liquidity
A65: Dec Headcount | D65: FY2026 Capex | G65: Dec Cash Conversion Cycle | J65: Week 13 Ending Cash
A66: ='Headcount & Payroll'!M46 -> 206 | D66: ='Capex & Depreciation'!N33 -> 3080 | G66: ='Working Capital'!Q25 -> 39 | J66: ='13-Week Cash Forecast'!N28 -> 7123.1935
A70: Week | B70: Ending Cash
A71: 1 | B71: ='13-Week Cash Forecast'!N16 -> 2218.9571
A72: 2 | B72: ='13-Week Cash Forecast'!N17 -> 3031.9852
A73: 3 | B73: ='13-Week Cash Forecast'!N18 -> 4881.2929
A74: 4 | B74: ='13-Week Cash Forecast'!N19 -> 5139.2085
A75: 5 | B75: ='13-Week Cash Forecast'!N20 -> 5317.9774
A76: 6 | B76: ='13-Week Cash Forecast'!N21 -> 5531.1773
A77: 7 | B77: ='13-Week Cash Forecast'!N22 -> 5744.3773
A78: 8 | B78: ='13-Week Cash Forecast'!N23 -> 5957.5772
A79: 9 | B79: ='13-Week Cash Forecast'!N24 -> 6307.9687
A80: 10 | B80: ='13-Week Cash Forecast'!N25 -> 6324.2749
A81: 11 | B81: ='13-Week Cash Forecast'!N26 -> 6590.5811
A82: 12 | B82: ='13-Week Cash Forecast'!N27 -> 6856.8873
A83: 13 | B83: ='13-Week Cash Forecast'!N28 -> 7123.1935
A87: Build 3 — Driver Analysis & Management Outlook
A88: Volume Effect | D88: Mix Effect | G88: Price Effect | J88: R&O-adjusted EBITDA
A89: ='PVM Analysis'!H12 -> -255.6 | D89: ='PVM Analysis'!I12 -> 108.75 | G89: ='PVM Analysis'!J12 -> -152.15 | J89: ='Risks & Opportunities'!B27 -> 14831.585
A92: ="PVM and management outlook shown for active scenario: "&Assumptions!B6 -> PVM and management outlook shown for active scenario: Base

Sheet Data Dictionary
A1: Data Dictionary & Modelling Definitions
A3: Field | B3: Definition | C3: Unit | D3: Input / Formula | E3: Used In | F3: Portfolio Relevance | G3: Notes
A4: Units | B4: Physical units sold | C4: units | D4: Input | E4: Actuals/Budget/Forecast | F4: Revenue driver | G4: Synthetic historical input
A5: ASP | B5: Average selling price | C5: £ per unit | D5: Input / formula | E5: Actuals/Budget/Forecast | F5: Pricing driver | G5: Budget grows prior-year ASP
A6: Revenue | B6: Units × ASP | C6: £000 | D6: Formula | E6: All schedules | F6: Top-line planning | G6: Calculated, not hardcoded
A7: Unit Cost | B7: Direct cost per unit | C7: £ per unit | D7: Input / formula | E7: Actuals/Budget/Forecast | F7: COGS driver | G7: Inflation applied in budget
A8: COGS | B8: Units × Unit Cost | C8: £000 | D8: Formula | E8: All schedules | F8: Gross margin planning | G8: Calculated, not hardcoded
A9: Gross Profit | B9: Revenue − COGS | C9: £000 | D9: Formula | E9: All schedules | F9: Margin analysis | G9: Calculated
A10: GP % | B10: Gross Profit / Revenue | C10: % | D10: Formula | E10: All schedules | F10: Margin KPI | G10: Calculated
A11: Marketing | B11: Division marketing spend | C11: £000 | D11: Input / formula | E11: All schedules | F11: Discretionary opex | G11: Budget linked to revenue
A12: Payroll | B12: Division payroll cost | C12: £000 | D12: Input / formula | E12: All schedules | F12: People cost | G12: Budget growth assumption
A13: Other Opex | B13: Other operating expense | C13: £000 | D13: Input / formula | E13: All schedules | F13: Operating leverage | G13: Budget growth assumption
A14: EBITDA | B14: GP − Marketing − Payroll − Other Opex | C14: £000 | D14: Formula | E14: All schedules | F14: Core FP&A KPI | G14: Calculated
A15: Scenario | B15: Base / Upside / Downside | C15: text | D15: Input | E15: Forecast | F15: Sensitivity analysis | G15: Only affects Q4 forecast
A17: Additional Build 2 Fields
A18: Headcount | B18: Employees / FTE planned by cost centre | C18: FTE | D18: Input | E18: Headcount & Payroll | F18: Workforce planning | G18: Synthetic portfolio input
A19: Employer On-cost | B19: NI, pension and benefit load on salary | C19: % | D19: Input | E19: Headcount & Payroll | F19: Payroll planning | G19: Synthetic assumption
A20: Capex | B20: Capital investment spend | C20: £000 | D20: Input | E20: Capex & Depreciation | F20: Investment planning | G20: Synthetic project register
A21: Depreciation | B21: Straight-line depreciation from capital assets | C21: £000 | D21: Formula | E21: Capex & Depreciation | F21: P&L / asset planning | G21: Begins month after in-service
A22: DSO | B22: Days Sales Outstanding | C22: days | D22: Input / scenario | E22: Working Capital | F22: Receivables efficiency | G22: Simulated actual + scenario forecast
A23: Inventory Days | B23: Inventory held relative to COGS | C23: days | D23: Input / scenario | E23: Working Capital | F23: Inventory efficiency | G23: Simulated actual + scenario forecast
A24: DPO | B24: Days Payable Outstanding | C24: days | D24: Input / scenario | E24: Working Capital | F24: Supplier funding | G24: Simulated actual + scenario forecast
A25: Cash Conversion Cycle | B25: DSO + Inventory Days − DPO | C25: days | D25: Formula | E25: Working Capital | F25: Working-capital KPI | G25: Lower generally indicates faster cash conversion
A26: 13-Week Cash Forecast | B26: Weekly liquidity planning model | C26: £000 | D26: Formula | E26: 13-Week Cash Forecast | F26: Treasury / liquidity | G26: Q4 forecast
A27: NPV | B27: Present value of project free cash flows less initial capex | C27: £000 | D27: Formula | E27: Investment Appraisal | F27: Capital allocation | G27: Discounted at WACC
A28: IRR | B28: Discount rate at which project NPV equals zero | C28: % | D28: Formula | E28: Investment Appraisal | F28: Capital allocation | G28: Compared with WACC
A30: Additional Build 3 Fields
A31: Price Effect | B31: Revenue impact from change in average selling price | C31: £000 | D31: Formula | E31: PVM Analysis | F31: Commercial finance | G31: Forecast units × ASP delta
A32: Volume Effect | B32: Revenue impact from change in total portfolio units | C32: £000 | D32: Formula | E32: PVM Analysis | F32: Commercial finance | G32: Uses budget mix and budget ASP
A33: Mix Effect | B33: Revenue impact from change in divisional sales mix | C33: £000 | D33: Formula | E33: PVM Analysis | F33: Commercial finance | G33: Separates mix from total volume
A34: Unit Cost Effect | B34: Gross-profit impact from change in direct cost per unit | C34: £000 | D34: Formula | E34: PVM Analysis | F34: Margin analysis | G34: Negative when unit costs rise
A35: R&O Probability | B35: Management assessment of likelihood | C35: % | D35: Input | E35: Risks & Opportunities | F35: Forecast governance | G35: Synthetic management judgement
A36: Weighted EBITDA | B36: EBITDA impact × probability | C36: £000 | D36: Formula | E36: Risks & Opportunities | F36: Forecast uncertainty | G36: Probability-weighted overlay
A37: R&O-adjusted EBITDA | B37: Base forecast plus weighted opportunities and risks | C37: £000 | D37: Formula | E37: Risks & Opportunities | F37: Management outlook | G37: Not a committed forecast
A38: Management Commentary | B38: Formula-driven narrative generated from model outputs | C38: text | D38: Formula | E38: Management Commentary | F38: Business partnering | G38: Updates with model outputs
A39: Management Pack | B39: Executive summary of performance, drivers, cash, R&O and actions | C39: report | D39: Linked output | E39: Management Pack | F39: CFO reporting | G39: Portfolio-ready output

Sheet Headcount & Payroll
A1: 2026 Headcount & Payroll Planning
A3: Blue = planning input | Black = calculation | Source: synthetic portfolio assumptions designed for this case study
A5: Payroll assumptions
A6: Employer on-cost % | B6: 0.15
A7: Annual pay award | B7: 0.03
A8: Payroll unit | B8: £000
A9: Source | B9: Synthetic portfolio assumption
A12: Division | B12: Function | C12: Opening HC | D12: 2026 Avg Salary (£000) | E12: Employer On-cost % | F12: Planned Hires | G12: Planned Exits | H12: Jan HC | I12: Feb HC | J12: Mar HC | K12: Apr HC | L12: May HC | M12: Jun HC | N12: Jul HC | O12: Aug HC | P12: Sep HC | Q12: Oct HC | R12: Nov HC | S12: Dec HC | T12: Jan Payroll (£000) | U12: Feb Payroll (£000) | V12: Mar Payroll (£000) | W12: Apr Payroll (£000) | X12: May Payroll (£000) | Y12: Jun Payroll (£000) | Z12: Jul Payroll (£000) | AA12: Aug Payroll (£000) | AB12: Sep Payroll (£000) | AC12: Oct Payroll (£000) | AD12: Nov Payroll (£000) | AE12: Dec Payroll (£000)
A13: =S13*$D13*(1+$B$7)*(1+$B$6)/12 -> 68.701 | B13: Sales & Marketing | C13: 16 | D13: 43.5 | E13: 0.15 | F13: 1 | G13: 1 | H13: 16 | I13: 16 | J13: 17 | K13: 17 | L13: 17 | M13: 16 | N13: 16 | O13: 16 | P13: 16 | Q13: 16 | R13: 16 | S13: 16 | T13: =H13*$D13*(1+$B$7)*(1+$B$6)/12 -> 68.701 | U13: =I13*$D13*(1+$B$7)*(1+$B$6)/12 -> 68.701 | V13: =J13*$D13*(1+$B$7)*(1+$B$6)/12 -> 72.994813 | W13: =K13*$D13*(1+$B$7)*(1+$B$6)/12 -> 72.994813 | X13: =L13*$D13*(1+$B$7)*(1+$B$6)/12 -> 72.994813 | Y13: =M13*$D13*(1+$B$7)*(1+$B$6)/12 -> 68.701 | Z13: =N13*$D13*(1+$B$7)*(1+$B$6)/12 -> 68.701 | AA13: =O13*$D13*(1+$B$7)*(1+$B$6)/12 -> 68.701 | ... AE13: =S13*$D13*(1+$B$7)*(1+$B$6)/12 -> 68.701
A14: =S14*$D14*(1+$B$7)*(1+$B$6)/12 -> 72.9652 | B14: Operations | C14: 22 | D14: 35.2 | E14: 0.15 | F14: 0 | G14: 1 | H14: 22 | I14: 22 | J14: 22 | K14: 22 | L14: 22 | M14: 21 | N14: 21 | O14: 21 | P14: 21 | Q14: 21 | R14: 21 | S14: 21 | T14: =H14*$D14*(1+$B$7)*(1+$B$6)/12 -> 76.439733 | U14: =I14*$D14*(1+$B$7)*(1+$B$6)/12 -> 76.439733 | V14: =J14*$D14*(1+$B$7)*(1+$B$6)/12 -> 76.439733 | W14: =K14*$D14*(1+$B$7)*(1+$B$6)/12 -> 76.439733 | X14: =L14*$D14*(1+$B$7)*(1+$B$6)/12 -> 76.439733 | Y14: =M14*$D14*(1+$B$7)*(1+$B$6)/12 -> 72.9652 | Z14: =N14*$D14*(1+$B$7)*(1+$B$6)/12 -> 72.9652 | AA14: =O14*$D14*(1+$B$7)*(1+$B$6)/12 -> 72.9652 | ... AE14: =S14*$D14*(1+$B$7)*(1+$B$6)/12 -> 72.9652
A15: =S15*$D15*(1+$B$7)*(1+$B$6)/12 -> 33.6398 | B15: Finance & Admin | C15: 8 | D15: 42.6 | E15: 0.15 | F15: 0 | G15: 0 | H15: 8 | I15: 8 | J15: 8 | K15: 8 | L15: 8 | M15: 8 | N15: 8 | O15: 8 | P15: 8 | Q15: 8 | R15: 8 | S15: 8 | T15: =H15*$D15*(1+$B$7)*(1+$B$6)/12 -> 33.6398 | U15: =I15*$D15*(1+$B$7)*(1+$B$6)/12 -> 33.6398 | V15: =J15*$D15*(1+$B$7)*(1+$B$6)/12 -> 33.6398 | W15: =K15*$D15*(1+$B$7)*(1+$B$6)/12 -> 33.6398 | X15: =L15*$D15*(1+$B$7)*(1+$B$6)/12 -> 33.6398 | Y15: =M15*$D15*(1+$B$7)*(1+$B$6)/12 -> 33.6398 | Z15: =N15*$D15*(1+$B$7)*(1+$B$6)/12 -> 33.6398 | AA15: =O15*$D15*(1+$B$7)*(1+$B$6)/12 -> 33.6398 | ... AE15: =S15*$D15*(1+$B$7)*(1+$B$6)/12 -> 33.6398
A16: =S16*$D16*(1+$B$7)*(1+$B$6)/12 -> 40.194033 | B16: Product / R&D | C16: 7 | D16: 50.9 | E16: 0.15 | F16: 1 | G16: 0 | H16: 7 | I16: 7 | J16: 8 | K16: 8 | L16: 8 | M16: 8 | N16: 8 | O16: 8 | P16: 8 | Q16: 8 | R16: 8 | S16: 8 | T16: =H16*$D16*(1+$B$7)*(1+$B$6)/12 -> 35.169779 | U16: =I16*$D16*(1+$B$7)*(1+$B$6)/12 -> 35.169779 | V16: =J16*$D16*(1+$B$7)*(1+$B$6)/12 -> 40.194033 | W16: =K16*$D16*(1+$B$7)*(1+$B$6)/12 -> 40.194033 | X16: =L16*$D16*(1+$B$7)*(1+$B$6)/12 -> 40.194033 | Y16: =M16*$D16*(1+$B$7)*(1+$B$6)/12 -> 40.194033 | Z16: =N16*$D16*(1+$B$7)*(1+$B$6)/12 -> 40.194033 | AA16: =O16*$D16*(1+$B$7)*(1+$B$6)/12 -> 40.194033 | ... AE16: =S16*$D16*(1+$B$7)*(1+$B$6)/12 -> 40.194033
A17: =S17*$D17*(1+$B$7)*(1+$B$6)/12 -> 51.456654 | B17: Sales & Marketing | C17: 13 | D17: 40.1 | E17: 0.15 | F17: 1 | G17: 1 | H17: 13 | I17: 13 | J17: 14 | K17: 14 | L17: 14 | M17: 13 | N17: 13 | O17: 13 | P17: 13 | Q17: 13 | R17: 13 | S17: 13 | T17: =H17*$D17*(1+$B$7)*(1+$B$6)/12 -> 51.456654 | U17: =I17*$D17*(1+$B$7)*(1+$B$6)/12 -> 51.456654 | V17: =J17*$D17*(1+$B$7)*(1+$B$6)/12 -> 55.414858 | W17: =K17*$D17*(1+$B$7)*(1+$B$6)/12 -> 55.414858 | X17: =L17*$D17*(1+$B$7)*(1+$B$6)/12 -> 55.414858 | Y17: =M17*$D17*(1+$B$7)*(1+$B$6)/12 -> 51.456654 | Z17: =N17*$D17*(1+$B$7)*(1+$B$6)/12 -> 51.456654 | AA17: =O17*$D17*(1+$B$7)*(1+$B$6)/12 -> 51.456654 | ... AE17: =S17*$D17*(1+$B$7)*(1+$B$6)/12 -> 51.456654
A18: =S18*$D18*(1+$B$7)*(1+$B$6)/12 -> 63.785325 | B18: Operations | C18: 19 | D18: 35.9 | E18: 0.15 | F18: 0 | G18: 1 | H18: 19 | I18: 19 | J18: 19 | K18: 19 | L18: 19 | M18: 18 | N18: 18 | O18: 18 | P18: 18 | Q18: 18 | R18: 18 | S18: 18 | T18: =H18*$D18*(1+$B$7)*(1+$B$6)/12 -> 67.328954 | U18: =I18*$D18*(1+$B$7)*(1+$B$6)/12 -> 67.328954 | V18: =J18*$D18*(1+$B$7)*(1+$B$6)/12 -> 67.328954 | W18: =K18*$D18*(1+$B$7)*(1+$B$6)/12 -> 67.328954 | X18: =L18*$D18*(1+$B$7)*(1+$B$6)/12 -> 67.328954 | Y18: =M18*$D18*(1+$B$7)*(1+$B$6)/12 -> 63.785325 | Z18: =N18*$D18*(1+$B$7)*(1+$B$6)/12 -> 63.785325 | AA18: =O18*$D18*(1+$B$7)*(1+$B$6)/12 -> 63.785325 | ... AE18: =S18*$D18*(1+$B$7)*(1+$B$6)/12 -> 63.785325
A19: =S19*$D19*(1+$B$7)*(1+$B$6)/12 -> 30.609454 | B19: Finance & Admin | C19: 7 | D19: 44.3 | E19: 0.15 | F19: 0 | G19: 0 | H19: 7 | I19: 7 | J19: 7 | K19: 7 | L19: 7 | M19: 7 | N19: 7 | O19: 7 | P19: 7 | Q19: 7 | R19: 7 | S19: 7 | T19: =H19*$D19*(1+$B$7)*(1+$B$6)/12 -> 30.609454 | U19: =I19*$D19*(1+$B$7)*(1+$B$6)/12 -> 30.609454 | V19: =J19*$D19*(1+$B$7)*(1+$B$6)/12 -> 30.609454 | W19: =K19*$D19*(1+$B$7)*(1+$B$6)/12 -> 30.609454 | X19: =L19*$D19*(1+$B$7)*(1+$B$6)/12 -> 30.609454 | Y19: =M19*$D19*(1+$B$7)*(1+$B$6)/12 -> 30.609454 | Z19: =N19*$D19*(1+$B$7)*(1+$B$6)/12 -> 30.609454 | AA19: =O19*$D19*(1+$B$7)*(1+$B$6)/12 -> 30.609454 | ... AE19: =S19*$D19*(1+$B$7)*(1+$B$6)/12 -> 30.609454
A20: =S20*$D20*(1+$B$7)*(1+$B$6)/12 -> 34.340629 | B20: Product / R&D | C20: 6 | D20: 49.7 | E20: 0.15 | F20: 1 | G20: 0 | H20: 6 | I20: 6 | J20: 7 | K20: 7 | L20: 7 | M20: 7 | N20: 7 | O20: 7 | P20: 7 | Q20: 7 | R20: 7 | S20: 7 | T20: =H20*$D20*(1+$B$7)*(1+$B$6)/12 -> 29.434825 | U20: =I20*$D20*(1+$B$7)*(1+$B$6)/12 -> 29.434825 | V20: =J20*$D20*(1+$B$7)*(1+$B$6)/12 -> 34.340629 | W20: =K20*$D20*(1+$B$7)*(1+$B$6)/12 -> 34.340629 | X20: =L20*$D20*(1+$B$7)*(1+$B$6)/12 -> 34.340629 | Y20: =M20*$D20*(1+$B$7)*(1+$B$6)/12 -> 34.340629 | Z20: =N20*$D20*(1+$B$7)*(1+$B$6)/12 -> 34.340629 | AA20: =O20*$D20*(1+$B$7)*(1+$B$6)/12 -> 34.340629 | ... AE20: =S20*$D20*(1+$B$7)*(1+$B$6)/12 -> 34.340629
A21: =S21*$D21*(1+$B$7)*(1+$B$6)/12 -> 47.6169 | B21: Sales & Marketing | C21: 12 | D21: 40.2 | E21: 0.15 | F21: 1 | G21: 1 | H21: 12 | I21: 12 | J21: 13 | K21: 13 | L21: 13 | M21: 12 | N21: 12 | O21: 12 | P21: 12 | Q21: 12 | R21: 12 | S21: 12 | T21: =H21*$D21*(1+$B$7)*(1+$B$6)/12 -> 47.6169 | U21: =I21*$D21*(1+$B$7)*(1+$B$6)/12 -> 47.6169 | V21: =J21*$D21*(1+$B$7)*(1+$B$6)/12 -> 51.584975 | W21: =K21*$D21*(1+$B$7)*(1+$B$6)/12 -> 51.584975 | X21: =L21*$D21*(1+$B$7)*(1+$B$6)/12 -> 51.584975 | Y21: =M21*$D21*(1+$B$7)*(1+$B$6)/12 -> 47.6169 | Z21: =N21*$D21*(1+$B$7)*(1+$B$6)/12 -> 47.6169 | AA21: =O21*$D21*(1+$B$7)*(1+$B$6)/12 -> 47.6169 | ... AE21: =S21*$D21*(1+$B$7)*(1+$B$6)/12 -> 47.6169
A22: =S22*$D22*(1+$B$7)*(1+$B$6)/12 -> 50.57815 | B22: Operations | C22: 14 | D22: 36.6 | E22: 0.15 | F22: 1 | G22: 1 | H22: 14 | I22: 14 | J22: 15 | K22: 15 | L22: 15 | M22: 14 | N22: 14 | O22: 14 | P22: 14 | Q22: 14 | R22: 14 | S22: 14 | T22: =H22*$D22*(1+$B$7)*(1+$B$6)/12 -> 50.57815 | U22: =I22*$D22*(1+$B$7)*(1+$B$6)/12 -> 50.57815 | V22: =J22*$D22*(1+$B$7)*(1+$B$6)/12 -> 54.190875 | W22: =K22*$D22*(1+$B$7)*(1+$B$6)/12 -> 54.190875 | X22: =L22*$D22*(1+$B$7)*(1+$B$6)/12 -> 54.190875 | Y22: =M22*$D22*(1+$B$7)*(1+$B$6)/12 -> 50.57815 | Z22: =N22*$D22*(1+$B$7)*(1+$B$6)/12 -> 50.57815 | AA22: =O22*$D22*(1+$B$7)*(1+$B$6)/12 -> 50.57815 | ... AE22: =S22*$D22*(1+$B$7)*(1+$B$6)/12 -> 50.57815
A23: =S23*$D23*(1+$B$7)*(1+$B$6)/12 -> 26.059 | B23: Finance & Admin | C23: 6 | D23: 44 | E23: 0.15 | F23: 0 | G23: 0 | H23: 6 | I23: 6 | J23: 6 | K23: 6 | L23: 6 | M23: 6 | N23: 6 | O23: 6 | P23: 6 | Q23: 6 | R23: 6 | S23: 6 | T23: =H23*$D23*(1+$B$7)*(1+$B$6)/12 -> 26.059 | U23: =I23*$D23*(1+$B$7)*(1+$B$6)/12 -> 26.059 | V23: =J23*$D23*(1+$B$7)*(1+$B$6)/12 -> 26.059 | W23: =K23*$D23*(1+$B$7)*(1+$B$6)/12 -> 26.059 | X23: =L23*$D23*(1+$B$7)*(1+$B$6)/12 -> 26.059 | Y23: =M23*$D23*(1+$B$7)*(1+$B$6)/12 -> 26.059 | Z23: =N23*$D23*(1+$B$7)*(1+$B$6)/12 -> 26.059 | AA23: =O23*$D23*(1+$B$7)*(1+$B$6)/12 -> 26.059 | ... AE23: =S23*$D23*(1+$B$7)*(1+$B$6)/12 -> 26.059
A24: =S24*$D24*(1+$B$7)*(1+$B$6)/12 -> 45.395963 | B24: Product / R&D | C24: 8 | D24: 51.1 | E24: 0.15 | F24: 1 | G24: 0 | H24: 8 | I24: 8 | J24: 9 | K24: 9 | L24: 9 | M24: 9 | N24: 9 | O24: 9 | P24: 9 | Q24: 9 | R24: 9 | S24: 9 | T24: =H24*$D24*(1+$B$7)*(1+$B$6)/12 -> 40.351967 | U24: =I24*$D24*(1+$B$7)*(1+$B$6)/12 -> 40.351967 | V24: =J24*$D24*(1+$B$7)*(1+$B$6)/12 -> 45.395963 | W24: =K24*$D24*(1+$B$7)*(1+$B$6)/12 -> 45.395963 | X24: =L24*$D24*(1+$B$7)*(1+$B$6)/12 -> 45.395963 | Y24: =M24*$D24*(1+$B$7)*(1+$B$6)/12 -> 45.395963 | Z24: =N24*$D24*(1+$B$7)*(1+$B$6)/12 -> 45.395963 | AA24: =O24*$D24*(1+$B$7)*(1+$B$6)/12 -> 45.395963 | ... AE24: =S24*$D24*(1+$B$7)*(1+$B$6)/12 -> 45.395963
... A32: =S32*$D32*(1+$B$7)*(1+$B$6)/12 -> 28.428 | B32: Product / R&D | C32: 5 | D32: 48 | E32: 0.15 | F32: 1 | G32: 0 | H32: 5 | I32: 5 | J32: 6 | K32: 6 | L32: 6 | M32: 6 | N32: 6 | O32: 6 | P32: 6 | Q32: 6 | R32: 6 | S32: 6 | T32: =H32*$D32*(1+$B$7)*(1+$B$6)/12 -> 23.69 | U32: =I32*$D32*(1+$B$7)*(1+$B$6)/12 -> 23.69 | V32: =J32*$D32*(1+$B$7)*(1+$B$6)/12 -> 28.428 | W32: =K32*$D32*(1+$B$7)*(1+$B$6)/12 -> 28.428 | X32: =L32*$D32*(1+$B$7)*(1+$B$6)/12 -> 28.428 | Y32: =M32*$D32*(1+$B$7)*(1+$B$6)/12 -> 28.428 | Z32: =N32*$D32*(1+$B$7)*(1+$B$6)/12 -> 28.428 | AA32: =O32*$D32*(1+$B$7)*(1+$B$6)/12 -> 28.428 | ... AE32: =S32*$D32*(1+$B$7)*(1+$B$6)/12 -> 28.428
A35: Monthly payroll budget by division (£000)
A36: Division | B36: Jan | C36: Feb | D36: Mar | E36: Apr | F36: May | G36: Jun | H36: Jul | I36: Aug | J36: Sep | K36: Oct | L36: Nov | M36: Dec | N36: FY2026
A37: Personal Care | B37: =SUM(T13:T16) -> 213.95031 | C37: =SUM(U13:U16) -> 213.95031 | D37: =SUM(V13:V16) -> 223.26838 | E37: =SUM(W13:W16) -> 223.26838 | F37: =SUM(X13:X16) -> 223.26838 | G37: =SUM(Y13:Y16) -> 215.50003 | H37: =SUM(Z13:Z16) -> 215.50003 | I37: =SUM(AA13:AA16) -> 215.50003 | ... M37: =SUM(AE13:AE16) -> 215.50003 | N37: =SUM(B37:M37) -> 2606.206
A38: Home Care | B38: =SUM(T17:T20) -> 178.82989 | C38: =SUM(U17:U20) -> 178.82989 | D38: =SUM(V17:V20) -> 187.6939 | E38: =SUM(W17:W20) -> 187.6939 | F38: =SUM(X17:X20) -> 187.6939 | G38: =SUM(Y17:Y20) -> 180.19206 | H38: =SUM(Z17:Z20) -> 180.19206 | I38: =SUM(AA17:AA20) -> 180.19206 | ... M38: =SUM(AE17:AE20) -> 180.19206 | N38: =SUM(B38:M38) -> 2182.0859
A39: Nutrition & Wellness | B39: =SUM(T21:T24) -> 164.60602 | C39: =SUM(U21:U24) -> 164.60602 | D39: =SUM(V21:V24) -> 177.23081 | E39: =SUM(W21:W24) -> 177.23081 | F39: =SUM(X21:X24) -> 177.23081 | G39: =SUM(Y21:Y24) -> 169.65001 | H39: =SUM(Z21:Z24) -> 169.65001 | I39: =SUM(AA21:AA24) -> 169.65001 | ... M39: =SUM(AE21:AE24) -> 169.65001 | N39: =SUM(B39:M39) -> 2048.4546
A40: Baby & Kids | B40: =SUM(T25:T28) -> 140.077 | C40: =SUM(U25:U28) -> 140.077 | D40: =SUM(V25:V28) -> 152.75115 | E40: =SUM(W25:W28) -> 152.75115 | F40: =SUM(X25:X28) -> 152.75115 | G40: =SUM(Y25:Y28) -> 149.00023 | H40: =SUM(Z25:Z28) -> 149.00023 | I40: =SUM(AA25:AA28) -> 149.00023 | ... M40: =SUM(AE25:AE28) -> 149.00023 | N40: =SUM(B40:M40) -> 1781.409
A41: Leisure & Lifestyle | B41: =SUM(T29:T32) -> 118.89419 | C41: =SUM(U29:U32) -> 118.89419 | D41: =SUM(V29:V32) -> 127.77794 | E41: =SUM(W29:W32) -> 127.77794 | F41: =SUM(X29:X32) -> 127.77794 | G41: =SUM(Y29:Y32) -> 127.77794 | H41: =SUM(Z29:Z32) -> 127.77794 | I41: =SUM(AA29:AA32) -> 127.77794 | ... M41: =SUM(AE29:AE32) -> 127.77794 | N41: =SUM(B41:M41) -> 1515.5677
A44: Monthly total headcount
A45: Metric | B45: Jan | C45: Feb | D45: Mar | E45: Apr | F45: May | G45: Jun | H45: Jul | I45: Aug | J45: Sep | K45: Oct | L45: Nov | M45: Dec | N45: FY-end
A46: Total HC | B46: =SUM(H13:H32) -> 201 | C46: =SUM(I13:I32) -> 201 | D46: =SUM(J13:J32) -> 213 | E46: =SUM(K13:K32) -> 213 | F46: =SUM(L13:L32) -> 213 | G46: =SUM(M13:M32) -> 206 | H46: =SUM(N13:N32) -> 206 | I46: =SUM(O13:O32) -> 206 | ... M46: =SUM(S13:S32) -> 206 | N46: =M46 -> 206

Sheet Capex & Depreciation
A1: 2026 Capex & Depreciation Schedule
A3: Capital plan is synthetic and designed for portfolio modelling. Capex is recognised in the in-service month; depreciation begins the following month.
A5: Capital project register
A6: Project | B6: Type | C6: Division | D6: Capex (£000) | E6: In-service Month | F6: Useful Life (Years) | G6: Business Rationale
A7: Warehouse Automation | B7: Growth | C7: Home Care | D7: 900 | E7: 46113 | F7: 5 | G7: Reduce fulfilment cost and improve throughput
A8: E-commerce Platform Upgrade | B8: Growth | C8: Leisure & Lifestyle | D8: 420 | E8: 46054 | F8: 3 | G8: Improve conversion and direct-to-consumer capability
A9: Production Line Upgrade | B9: Maintenance | C9: Personal Care | D9: 650 | E9: 46204 | F9: 7 | G9: Increase reliability and reduce downtime
A10: Quality Lab Equipment | B10: Maintenance | C10: Baby & Kids | D10: 280 | E10: 46143 | F10: 5 | G10: Improve testing capacity and compliance
A11: Nutrition Product Pilot Line | B11: Growth | C11: Nutrition & Wellness | D11: 520 | E11: 46266 | F11: 5 | G11: Support new product launches
A12: Energy Efficiency Programme | B12: Efficiency | C12: Home Care | D12: 310 | E12: 46327 | F12: 6 | G12: Reduce utilities cost and carbon intensity
A15: Monthly project schedule (£000)
A16: Project | B16: Metric | C16: Jan | D16: Feb | E16: Mar | F16: Apr | G16: May | H16: Jun | I16: Jul | J16: Aug | K16: Sep | L16: Oct | M16: Nov | N16: Dec | O16: FY2026 | P16: Source | Q16: Notes
A17: Warehouse Automation | B17: Capex | C17: =IF(MONTH($E$7)=1,$D$7,0) -> 0 | D17: =IF(MONTH($E$7)=2,$D$7,0) -> 0 | E17: =IF(MONTH($E$7)=3,$D$7,0) -> 0 | F17: =IF(MONTH($E$7)=4,$D$7,0) -> 900 | G17: =IF(MONTH($E$7)=5,$D$7,0) -> 0 | H17: =IF(MONTH($E$7)=6,$D$7,0) -> 0 | I17: =IF(MONTH($E$7)=7,$D$7,0) -> 0 | J17: =IF(MONTH($E$7)=8,$D$7,0) -> 0 | K17: =IF(MONTH($E$7)=9,$D$7,0) -> 0 | L17: =IF(MONTH($E$7)=10,$D$7,0) -> 0 | M17: =IF(MONTH($E$7)=11,$D$7,0) -> 0 | N17: =IF(MONTH($E$7)=12,$D$7,0) -> 0 | O17: =SUM(C17:N17) -> 900 | P17: Synthetic portfolio input | Q17: Full capex in in-service month
A18: Warehouse Automation | B18: Depreciation | C18: =IF(1>MONTH($E$7),$D$7/($F$7*12),0) -> 0 | D18: =IF(2>MONTH($E$7),$D$7/($F$7*12),0) -> 0 | E18: =IF(3>MONTH($E$7),$D$7/($F$7*12),0) -> 0 | F18: =IF(4>MONTH($E$7),$D$7/($F$7*12),0) -> 0 | G18: =IF(5>MONTH($E$7),$D$7/($F$7*12),0) -> 15 | H18: =IF(6>MONTH($E$7),$D$7/($F$7*12),0) -> 15 | I18: =IF(7>MONTH($E$7),$D$7/($F$7*12),0) -> 15 | J18: =IF(8>MONTH($E$7),$D$7/($F$7*12),0) -> 15 | K18: =IF(9>MONTH($E$7),$D$7/($F$7*12),0) -> 15 | L18: =IF(10>MONTH($E$7),$D$7/($F$7*12),0) -> 15 | M18: =IF(11>MONTH($E$7),$D$7/($F$7*12),0) -> 15 | N18: =IF(12>MONTH($E$7),$D$7/($F$7*12),0) -> 15 | O18: =SUM(C18:N18) -> 120 | P18: Calculated | Q18: Straight-line; begins month after in-service
A19: E-commerce Platform Upgrade | B19: Capex | C19: =IF(MONTH($E$8)=1,$D$8,0) -> 0 | D19: =IF(MONTH($E$8)=2,$D$8,0) -> 420 | E19: =IF(MONTH($E$8)=3,$D$8,0) -> 0 | F19: =IF(MONTH($E$8)=4,$D$8,0) -> 0 | G19: =IF(MONTH($E$8)=5,$D$8,0) -> 0 | H19: =IF(MONTH($E$8)=6,$D$8,0) -> 0 | I19: =IF(MONTH($E$8)=7,$D$8,0) -> 0 | J19: =IF(MONTH($E$8)=8,$D$8,0) -> 0 | K19: =IF(MONTH($E$8)=9,$D$8,0) -> 0 | L19: =IF(MONTH($E$8)=10,$D$8,0) -> 0 | M19: =IF(MONTH($E$8)=11,$D$8,0) -> 0 | N19: =IF(MONTH($E$8)=12,$D$8,0) -> 0 | O19: =SUM(C19:N19) -> 420 | P19: Synthetic portfolio input | Q19: Full capex in in-service month
A20: E-commerce Platform Upgrade | B20: Depreciation | C20: =IF(1>MONTH($E$8),$D$8/($F$8*12),0) -> 0 | D20: =IF(2>MONTH($E$8),$D$8/($F$8*12),0) -> 0 | E20: =IF(3>MONTH($E$8),$D$8/($F$8*12),0) -> 11.666667 | F20: =IF(4>MONTH($E$8),$D$8/($F$8*12),0) -> 11.666667 | G20: =IF(5>MONTH($E$8),$D$8/($F$8*12),0) -> 11.666667 | H20: =IF(6>MONTH($E$8),$D$8/($F$8*12),0) -> 11.666667 | I20: =IF(7>MONTH($E$8),$D$8/($F$8*12),0) -> 11.666667 | J20: =IF(8>MONTH($E$8),$D$8/($F$8*12),0) -> 11.666667 | K20: =IF(9>MONTH($E$8),$D$8/($F$8*12),0) -> 11.666667 | L20: =IF(10>MONTH($E$8),$D$8/($F$8*12),0) -> 11.666667 | M20: =IF(11>MONTH($E$8),$D$8/($F$8*12),0) -> 11.666667 | N20: =IF(12>MONTH($E$8),$D$8/($F$8*12),0) -> 11.666667 | O20: =SUM(C20:N20) -> 116.66667 | P20: Calculated | Q20: Straight-line; begins month after in-service
A21: Production Line Upgrade | B21: Capex | C21: =IF(MONTH($E$9)=1,$D$9,0) -> 0 | D21: =IF(MONTH($E$9)=2,$D$9,0) -> 0 | E21: =IF(MONTH($E$9)=3,$D$9,0) -> 0 | F21: =IF(MONTH($E$9)=4,$D$9,0) -> 0 | G21: =IF(MONTH($E$9)=5,$D$9,0) -> 0 | H21: =IF(MONTH($E$9)=6,$D$9,0) -> 0 | I21: =IF(MONTH($E$9)=7,$D$9,0) -> 650 | J21: =IF(MONTH($E$9)=8,$D$9,0) -> 0 | K21: =IF(MONTH($E$9)=9,$D$9,0) -> 0 | L21: =IF(MONTH($E$9)=10,$D$9,0) -> 0 | M21: =IF(MONTH($E$9)=11,$D$9,0) -> 0 | N21: =IF(MONTH($E$9)=12,$D$9,0) -> 0 | O21: =SUM(C21:N21) -> 650 | P21: Synthetic portfolio input | Q21: Full capex in in-service month
A22: Production Line Upgrade | B22: Depreciation | C22: =IF(1>MONTH($E$9),$D$9/($F$9*12),0) -> 0 | D22: =IF(2>MONTH($E$9),$D$9/($F$9*12),0) -> 0 | E22: =IF(3>MONTH($E$9),$D$9/($F$9*12),0) -> 0 | F22: =IF(4>MONTH($E$9),$D$9/($F$9*12),0) -> 0 | G22: =IF(5>MONTH($E$9),$D$9/($F$9*12),0) -> 0 | H22: =IF(6>MONTH($E$9),$D$9/($F$9*12),0) -> 0 | I22: =IF(7>MONTH($E$9),$D$9/($F$9*12),0) -> 0 | J22: =IF(8>MONTH($E$9),$D$9/($F$9*12),0) -> 7.7380952 | K22: =IF(9>MONTH($E$9),$D$9/($F$9*12),0) -> 7.7380952 | L22: =IF(10>MONTH($E$9),$D$9/($F$9*12),0) -> 7.7380952 | M22: =IF(11>MONTH($E$9),$D$9/($F$9*12),0) -> 7.7380952 | N22: =IF(12>MONTH($E$9),$D$9/($F$9*12),0) -> 7.7380952 | O22: =SUM(C22:N22) -> 38.690476 | P22: Calculated | Q22: Straight-line; begins month after in-service
A23: Quality Lab Equipment | B23: Capex | C23: =IF(MONTH($E$10)=1,$D$10,0) -> 0 | D23: =IF(MONTH($E$10)=2,$D$10,0) -> 0 | E23: =IF(MONTH($E$10)=3,$D$10,0) -> 0 | F23: =IF(MONTH($E$10)=4,$D$10,0) -> 0 | G23: =IF(MONTH($E$10)=5,$D$10,0) -> 280 | H23: =IF(MONTH($E$10)=6,$D$10,0) -> 0 | I23: =IF(MONTH($E$10)=7,$D$10,0) -> 0 | J23: =IF(MONTH($E$10)=8,$D$10,0) -> 0 | K23: =IF(MONTH($E$10)=9,$D$10,0) -> 0 | L23: =IF(MONTH($E$10)=10,$D$10,0) -> 0 | M23: =IF(MONTH($E$10)=11,$D$10,0) -> 0 | N23: =IF(MONTH($E$10)=12,$D$10,0) -> 0 | O23: =SUM(C23:N23) -> 280 | P23: Synthetic portfolio input | Q23: Full capex in in-service month
A24: Quality Lab Equipment | B24: Depreciation | C24: =IF(1>MONTH($E$10),$D$10/($F$10*12),0) -> 0 | D24: =IF(2>MONTH($E$10),$D$10/($F$10*12),0) -> 0 | E24: =IF(3>MONTH($E$10),$D$10/($F$10*12),0) -> 0 | F24: =IF(4>MONTH($E$10),$D$10/($F$10*12),0) -> 0 | G24: =IF(5>MONTH($E$10),$D$10/($F$10*12),0) -> 0 | H24: =IF(6>MONTH($E$10),$D$10/($F$10*12),0) -> 4.6666667 | I24: =IF(7>MONTH($E$10),$D$10/($F$10*12),0) -> 4.6666667 | J24: =IF(8>MONTH($E$10),$D$10/($F$10*12),0) -> 4.6666667 | K24: =IF(9>MONTH($E$10),$D$10/($F$10*12),0) -> 4.6666667 | L24: =IF(10>MONTH($E$10),$D$10/($F$10*12),0) -> 4.6666667 | M24: =IF(11>MONTH($E$10),$D$10/($F$10*12),0) -> 4.6666667 | N24: =IF(12>MONTH($E$10),$D$10/($F$10*12),0) -> 4.6666667 | O24: =SUM(C24:N24) -> 32.666667 | P24: Calculated | Q24: Straight-line; begins month after in-service
A25: Nutrition Product Pilot Line | B25: Capex | C25: =IF(MONTH($E$11)=1,$D$11,0) -> 0 | D25: =IF(MONTH($E$11)=2,$D$11,0) -> 0 | E25: =IF(MONTH($E$11)=3,$D$11,0) -> 0 | F25: =IF(MONTH($E$11)=4,$D$11,0) -> 0 | G25: =IF(MONTH($E$11)=5,$D$11,0) -> 0 | H25: =IF(MONTH($E$11)=6,$D$11,0) -> 0 | I25: =IF(MONTH($E$11)=7,$D$11,0) -> 0 | J25: =IF(MONTH($E$11)=8,$D$11,0) -> 0 | K25: =IF(MONTH($E$11)=9,$D$11,0) -> 520 | L25: =IF(MONTH($E$11)=10,$D$11,0) -> 0 | M25: =IF(MONTH($E$11)=11,$D$11,0) -> 0 | N25: =IF(MONTH($E$11)=12,$D$11,0) -> 0 | O25: =SUM(C25:N25) -> 520 | P25: Synthetic portfolio input | Q25: Full capex in in-service month
A26: Nutrition Product Pilot Line | B26: Depreciation | C26: =IF(1>MONTH($E$11),$D$11/($F$11*12),0) -> 0 | D26: =IF(2>MONTH($E$11),$D$11/($F$11*12),0) -> 0 | E26: =IF(3>MONTH($E$11),$D$11/($F$11*12),0) -> 0 | F26: =IF(4>MONTH($E$11),$D$11/($F$11*12),0) -> 0 | G26: =IF(5>MONTH($E$11),$D$11/($F$11*12),0) -> 0 | H26: =IF(6>MONTH($E$11),$D$11/($F$11*12),0) -> 0 | I26: =IF(7>MONTH($E$11),$D$11/($F$11*12),0) -> 0 | J26: =IF(8>MONTH($E$11),$D$11/($F$11*12),0) -> 0 | K26: =IF(9>MONTH($E$11),$D$11/($F$11*12),0) -> 0 | L26: =IF(10>MONTH($E$11),$D$11/($F$11*12),0) -> 8.6666667 | M26: =IF(11>MONTH($E$11),$D$11/($F$11*12),0) -> 8.6666667 | N26: =IF(12>MONTH($E$11),$D$11/($F$11*12),0) -> 8.6666667 | O26: =SUM(C26:N26) -> 26 | P26: Calculated | Q26: Straight-line; begins month after in-service
A27: Energy Efficiency Programme | B27: Capex | C27: =IF(MONTH($E$12)=1,$D$12,0) -> 0 | D27: =IF(MONTH($E$12)=2,$D$12,0) -> 0 | E27: =IF(MONTH($E$12)=3,$D$12,0) -> 0 | F27: =IF(MONTH($E$12)=4,$D$12,0) -> 0 | G27: =IF(MONTH($E$12)=5,$D$12,0) -> 0 | H27: =IF(MONTH($E$12)=6,$D$12,0) -> 0 | I27: =IF(MONTH($E$12)=7,$D$12,0) -> 0 | J27: =IF(MONTH($E$12)=8,$D$12,0) -> 0 | K27: =IF(MONTH($E$12)=9,$D$12,0) -> 0 | L27: =IF(MONTH($E$12)=10,$D$12,0) -> 0 | M27: =IF(MONTH($E$12)=11,$D$12,0) -> 310 | N27: =IF(MONTH($E$12)=12,$D$12,0) -> 0 | O27: =SUM(C27:N27) -> 310 | P27: Synthetic portfolio input | Q27: Full capex in in-service month
A28: Energy Efficiency Programme | B28: Depreciation | C28: =IF(1>MONTH($E$12),$D$12/($F$12*12),0) -> 0 | D28: =IF(2>MONTH($E$12),$D$12/($F$12*12),0) -> 0 | E28: =IF(3>MONTH($E$12),$D$12/($F$12*12),0) -> 0 | F28: =IF(4>MONTH($E$12),$D$12/($F$12*12),0) -> 0 | G28: =IF(5>MONTH($E$12),$D$12/($F$12*12),0) -> 0 | H28: =IF(6>MONTH($E$12),$D$12/($F$12*12),0) -> 0 | I28: =IF(7>MONTH($E$12),$D$12/($F$12*12),0) -> 0 | J28: =IF(8>MONTH($E$12),$D$12/($F$12*12),0) -> 0 | K28: =IF(9>MONTH($E$12),$D$12/($F$12*12),0) -> 0 | L28: =IF(10>MONTH($E$12),$D$12/($F$12*12),0) -> 0 | M28: =IF(11>MONTH($E$12),$D$12/($F$12*12),0) -> 0 | N28: =IF(12>MONTH($E$12),$D$12/($F$12*12),0) -> 4.3055556 | O28: =SUM(C28:N28) -> 4.3055556 | P28: Calculated | Q28: Straight-line; begins month after in-service
A31: Monthly total capital plan (£000)
A32: Metric | B32: Jan | C32: Feb | D32: Mar | E32: Apr | F32: May | G32: Jun | H32: Jul | I32: Aug | J32: Sep | K32: Oct | L32: Nov | M32: Dec | N32: FY2026
A33: Capex | B33: =C17+C19+C21+C23+C25+C27 -> 0 | C33: =D17+D19+D21+D23+D25+D27 -> 420 | D33: =E17+E19+E21+E23+E25+E27 -> 0 | E33: =F17+F19+F21+F23+F25+F27 -> 900 | F33: =G17+G19+G21+G23+G25+G27 -> 280 | G33: =H17+H19+H21+H23+H25+H27 -> 0 | H33: =I17+I19+I21+I23+I25+I27 -> 650 | I33: =J17+J19+J21+J23+J25+J27 -> 0 | ... M33: =N17+N19+N21+N23+N25+N27 -> 0 | N33: =SUM(B33:M33) -> 3080
A34: Depreciation | B34: =C18+C20+C22+C24+C26+C28 -> 0 | C34: =D18+D20+D22+D24+D26+D28 -> 0 | D34: =E18+E20+E22+E24+E26+E28 -> 11.666667 | E34: =F18+F20+F22+F24+F26+F28 -> 11.666667 | F34: =G18+G20+G22+G24+G26+G28 -> 26.666667 | G34: =H18+H20+H22+H24+H26+H28 -> 31.333333 | H34: =I18+I20+I22+I24+I26+I28 -> 31.333333 | I34: =J18+J20+J22+J24+J26+J28 -> 39.071429 | ... M34: =N18+N20+N22+N24+N26+N28 -> 52.043651 | N34: =SUM(B34:M34) -> 338.32937

Sheet Working Capital
A1: Working Capital & Free Cash Flow Forecast
A3: Working-capital assumptions are synthetic. Jan–Sep operating-day inputs represent simulated actuals; Q4 uses the active scenario.
A5: Q4 working-capital scenario assumptions
A6: Scenario | B6: DSO | C6: Inventory Days | D6: DPO
A7: Base | B7: 34 | C7: 43 | D7: 38
A8: Upside | B8: 31 | C8: 40 | D8: 40
A9: Downside | B9: 39 | C9: 49 | D9: 34
A12: Monthly working-capital and cash conversion (£000)
A13: Month | B13: Revenue | C13: COGS | D13: DSO | E13: Accounts Receivable | F13: Inventory Days | G13: Inventory | H13: DPO | I13: Accounts Payable | J13: Net Working Capital | K13: Change in NWC | L13: EBITDA | M13: Cash Tax | N13: Operating CF pre-Capex | O13: Capex | P13: Free Cash Flow | Q13: Cash Conversion Cycle
A14: 46023 | B14: =SUM('Rolling Forecast'!F4:F8) -> 5110.5859 | C14: =SUM('Rolling Forecast'!H4:H8) -> 2759.5508 | D14: 36 | E14: =B14*D14/30.4 -> 6052.0097 | F14: 45 | G14: =C14*F14/30.4 -> 4084.8614 | H14: 37 | I14: =C14*H14/30.4 -> 3358.6638 | J14: =E14+G14-I14 -> 6778.2072 | K14: =0 -> 0 | L14: =SUM('Rolling Forecast'!N4:N8) -> 1078.8351 | M14: =IF(L14>0,L14*20%,0) -> 215.76702 | N14: =L14-K14-M14 -> 863.06809 | O14: ='Capex & Depreciation'!B33 -> 0 | P14: =N14-O14 -> 863.06809 | Q14: =D14+F14-H14 -> 44
A15: 46054 | B15: =SUM('Rolling Forecast'!F9:F13) -> 5219.5505 | C15: =SUM('Rolling Forecast'!H9:H13) -> 2818.1342 | D15: 35 | E15: =B15*D15/30.4 -> 6009.3509 | F15: 44 | G15: =C15*F15/30.4 -> 4078.8784 | H15: 38 | I15: =C15*H15/30.4 -> 3522.6678 | J15: =E15+G15-I15 -> 6565.5616 | K15: =J15-J14 -> -212.64564 | L15: =SUM('Rolling Forecast'!N9:N13) -> 1124.5163 | M15: =IF(L15>0,L15*20%,0) -> 224.90326 | N15: =L15-K15-M15 -> 1112.2587 | O15: ='Capex & Depreciation'!C33 -> 420 | P15: =N15-O15 -> 692.25868 | Q15: =D15+F15-H15 -> 41
A16: 46082 | B16: =SUM('Rolling Forecast'!F14:F18) -> 5543.7374 | C16: =SUM('Rolling Forecast'!H14:H18) -> 2986.2584 | D16: 35 | E16: =B16*D16/30.4 -> 6382.5924 | F16: 44 | G16: =C16*F16/30.4 -> 4322.2162 | H16: 38 | I16: =C16*H16/30.4 -> 3732.8231 | J16: =E16+G16-I16 -> 6971.9856 | K16: =J16-J15 -> 406.42396 | L16: =SUM('Rolling Forecast'!N14:N18) -> 1260.079 | M16: =IF(L16>0,L16*20%,0) -> 252.0158 | N16: =L16-K16-M16 -> 601.63924 | O16: ='Capex & Depreciation'!D33 -> 0 | P16: =N16-O16 -> 601.63924 | Q16: =D16+F16-H16 -> 41
A17: 46113 | B17: =SUM('Rolling Forecast'!F19:F23) -> 5554.7515 | C17: =SUM('Rolling Forecast'!H19:H23) -> 3010.0302 | D17: 34 | E17: =B17*D17/30.4 -> 6212.551 | F17: 43 | G17: =C17*F17/30.4 -> 4257.6085 | H17: 38 | I17: =C17*H17/30.4 -> 3762.5377 | J17: =E17+G17-I17 -> 6707.6218 | K17: =J17-J16 -> -264.36381 | L17: =SUM('Rolling Forecast'!N19:N23) -> 1254.3213 | M17: =IF(L17>0,L17*20%,0) -> 250.86426 | N17: =L17-K17-M17 -> 1267.8208 | O17: ='Capex & Depreciation'!E33 -> 900 | P17: =N17-O17 -> 367.82084 | Q17: =D17+F17-H17 -> 39
A18: 46143 | B18: =SUM('Rolling Forecast'!F24:F28) -> 5551.7411 | C18: =SUM('Rolling Forecast'!H24:H28) -> 3000.4873 | D18: 34 | E18: =B18*D18/30.4 -> 6209.1841 | F18: 42 | G18: =C18*F18/30.4 -> 4145.4101 | H18: 39 | I18: =C18*H18/30.4 -> 3849.3094 | J18: =E18+G18-I18 -> 6505.2848 | K18: =J18-J17 -> -202.33694 | L18: =SUM('Rolling Forecast'!N24:N28) -> 1240.5537 | M18: =IF(L18>0,L18*20%,0) -> 248.11075 | N18: =L18-K18-M18 -> 1194.7799 | O18: ='Capex & Depreciation'!F33 -> 280 | P18: =N18-O18 -> 914.77992 | Q18: =D18+F18-H18 -> 37
A19: 46174 | B19: =SUM('Rolling Forecast'!F29:F33) -> 5700.2679 | C19: =SUM('Rolling Forecast'!H29:H33) -> 3060.6619 | D19: 33 | E19: =B19*D19/30.4 -> 6187.7908 | F19: 42 | G19: =C19*F19/30.4 -> 4228.546 | H19: 39 | I19: =C19*H19/30.4 -> 3926.507 | J19: =E19+G19-I19 -> 6489.8298 | K19: =J19-J18 -> -15.454978 | L19: =SUM('Rolling Forecast'!N29:N33) -> 1345.906 | M19: =IF(L19>0,L19*20%,0) -> 269.1812 | N19: =L19-K19-M19 -> 1092.1798 | O19: ='Capex & Depreciation'!G33 -> 0 | P19: =N19-O19 -> 1092.1798 | Q19: =D19+F19-H19 -> 36
A20: 46204 | B20: =SUM('Rolling Forecast'!F34:F38) -> 5898.7152 | C20: =SUM('Rolling Forecast'!H34:H38) -> 3180.7755 | D20: 35 | E20: =B20*D20/30.4 -> 6791.2839 | F20: 43 | G20: =C20*F20/30.4 -> 4499.1232 | H20: 38 | I20: =C20*H20/30.4 -> 3975.9694 | J20: =E20+G20-I20 -> 7314.4378 | K20: =J20-J19 -> 824.60796 | L20: =SUM('Rolling Forecast'!N34:N38) -> 1390.4397 | M20: =IF(L20>0,L20*20%,0) -> 278.08794 | N20: =L20-K20-M20 -> 287.74381 | O20: ='Capex & Depreciation'!H33 -> 650 | P20: =N20-O20 -> -362.25619 | Q20: =D20+F20-H20 -> 40
A21: 46235 | B21: =SUM('Rolling Forecast'!F39:F43) -> 5671.2931 | C21: =SUM('Rolling Forecast'!H39:H43) -> 3035.5218 | D21: 34 | E21: =B21*D21/30.4 -> 6342.8936 | F21: 42 | G21: =C21*F21/30.4 -> 4193.8131 | H21: 38 | I21: =C21*H21/30.4 -> 3794.4023 | J21: =E21+G21-I21 -> 6742.3043 | K21: =J21-J20 -> -572.13346 | L21: =SUM('Rolling Forecast'!N39:N43) -> 1333.0712 | M21: =IF(L21>0,L21*20%,0) -> 266.61425 | N21: =L21-K21-M21 -> 1638.5904 | O21: ='Capex & Depreciation'!I33 -> 0 | P21: =N21-O21 -> 1638.5904 | Q21: =D21+F21-H21 -> 38
A22: 46266 | B22: =SUM('Rolling Forecast'!F44:F48) -> 5528.9505 | C22: =SUM('Rolling Forecast'!H44:H48) -> 2973.9312 | D22: 35 | E22: =B22*D22/30.4 -> 6365.568 | F22: 43 | G22: =C22*F22/30.4 -> 4206.5475 | H22: 38 | I22: =C22*H22/30.4 -> 3717.414 | J22: =E22+G22-I22 -> 6854.7014 | K22: =J22-J21 -> 112.39706 | L22: =SUM('Rolling Forecast'!N44:N48) -> 1262.6192 | M22: =IF(L22>0,L22*20%,0) -> 252.52385 | N22: =L22-K22-M22 -> 897.69833 | O22: ='Capex & Depreciation'!J33 -> 520 | P22: =N22-O22 -> 377.69833 | Q22: =D22+F22-H22 -> 40
A23: 46296 | B23: =SUM('Rolling Forecast'!F49:F53) -> 5799.0115 | C23: =SUM('Rolling Forecast'!H49:H53) -> 3124.0384 | D23: =IF(Assumptions!$B$6="Upside",$B$8,IF(Assumptions!$B$6="Downside",$B$9,$B$7)) -> 34 | E23: =B23*D23/30.4 -> 6485.7365 | F23: =IF(Assumptions!$B$6="Upside",$C$8,IF(Assumptions!$B$6="Downside",$C$9,$C$7)) -> 43 | G23: =C23*F23/30.4 -> 4418.8701 | H23: =IF(Assumptions!$B$6="Upside",$D$8,IF(Assumptions!$B$6="Downside",$D$9,$D$7)) -> 38 | I23: =C23*H23/30.4 -> 3905.048 | J23: =E23+G23-I23 -> 6999.5586 | K23: =J23-J22 -> 144.85724 | L23: =SUM('Rolling Forecast'!N49:N53) -> 1031.6625 | M23: =IF(L23>0,L23*20%,0) -> 206.3325 | N23: =L23-K23-M23 -> 680.47275 | O23: ='Capex & Depreciation'!K33 -> 0 | P23: =N23-O23 -> 680.47275 | Q23: =D23+F23-H23 -> 39
A24: 46327 | B24: =SUM('Rolling Forecast'!F54:F58) -> 6202.509 | C24: =SUM('Rolling Forecast'!H54:H58) -> 3359.6084 | D24: =IF(Assumptions!$B$6="Upside",$B$8,IF(Assumptions!$B$6="Downside",$B$9,$B$7)) -> 34 | E24: =B24*D24/30.4 -> 6937.0166 | F24: =IF(Assumptions!$B$6="Upside",$C$8,IF(Assumptions!$B$6="Downside",$C$9,$C$7)) -> 43 | G24: =C24*F24/30.4 -> 4752.0777 | H24: =IF(Assumptions!$B$6="Upside",$D$8,IF(Assumptions!$B$6="Downside",$D$9,$D$7)) -> 38 | I24: =C24*H24/30.4 -> 4199.5105 | J24: =E24+G24-I24 -> 7489.5838 | K24: =J24-J23 -> 490.02518 | L24: =SUM('Rolling Forecast'!N54:N58) -> 1162.7998 | M24: =IF(L24>0,L24*20%,0) -> 232.55996 | N24: =L24-K24-M24 -> 440.21465 | O24: ='Capex & Depreciation'!L33 -> 310 | P24: =N24-O24 -> 130.21465 | Q24: =D24+F24-H24 -> 39
A25: 46357 | B25: =SUM('Rolling Forecast'!F59:F63) -> 6572.739 | C25: =SUM('Rolling Forecast'!H59:H63) -> 3535.4078 | D25: =IF(Assumptions!$B$6="Upside",$B$8,IF(Assumptions!$B$6="Downside",$B$9,$B$7)) -> 34 | E25: =B25*D25/30.4 -> 7351.0896 | F25: =IF(Assumptions!$B$6="Upside",$C$8,IF(Assumptions!$B$6="Downside",$C$9,$C$7)) -> 43 | G25: =C25*F25/30.4 -> 5000.7413 | H25: =IF(Assumptions!$B$6="Upside",$D$8,IF(Assumptions!$B$6="Downside",$D$9,$D$7)) -> 38 | I25: =C25*H25/30.4 -> 4419.2598 | J25: =E25+G25-I25 -> 7932.5712 | K25: =J25-J24 -> 442.98737 | L25: =SUM('Rolling Forecast'!N59:N63) -> 1331.531 | M25: =IF(L25>0,L25*20%,0) -> 266.30621 | N25: =L25-K25-M25 -> 622.23747 | O25: ='Capex & Depreciation'!M33 -> 0 | P25: =N25-O25 -> 622.23747 | Q25: =D25+F25-H25 -> 39
A28: Working-capital KPI summary
A29: Metric | B29: Sep Actual | C29: Dec Forecast | D29: Change | E29: Interpretation
A30: Cash Conversion Cycle | B30: =Q22 -> 40 | C30: =Q25 -> 39 | D30: =C30-B30 -> -1 | E30: Lower is better
A31: Net Working Capital (£000) | B31: =J22 -> 6854.7014 | C31: =J25 -> 7932.5712 | D31: =C31-B31 -> 1077.8698 | E31: Cash tied up in operations

Sheet 13-Week Cash Forecast
A1: 13-Week Cash Flow Forecast — Q4 2026
A3: Liquidity planning model. Sales and cost run-rates are linked to the rolling forecast; collection/payment timing assumptions are synthetic.
A5: Liquidity assumptions
A6: Opening Cash (£000) | B6: 2000
A7: Minimum Cash Policy (£000) | B7: 1000
A8: Current-week Sales Collection | B8: 0.25
A9: Next-week Sales Collection | B9: 0.75
A10: Current-week Supplier Payment | B10: 0.3
A11: Next-week Supplier Payment | B11: 0.7
A12: Source | B12: Synthetic portfolio assumption
A14: Weekly liquidity forecast (£000)
A15: Week | B15: Week Start | C15: Fiscal Month | D15: Weekly Sales | E15: Cash Receipts | F15: Supplier Payments | G15: Payroll | H15: Marketing | I15: Other Opex | J15: Capex | K15: Tax / Other | L15: Net Cash Flow | M15: Opening Cash | N15: Ending Cash
A16: 1 | B16: 46300 | C16: 46296 | D16: =SUM('Rolling Forecast'!F49:F53)/4 -> 1449.7529 | E16: =D16*$B$8+'Working Capital'!E22*40% -> 2908.6654 | F16: =SUM('Rolling Forecast'!H49:H53)/4*$B$10+'Working Capital'!I22*55% -> 2278.8806 | G16: =SUM('Rolling Forecast'!L49:L53)/4 -> 210.53007 | H16: =SUM('Rolling Forecast'!K49:K53)/4 -> 109.32046 | I16: =SUM('Rolling Forecast'!M49:M53)/4 -> 90.977125 | J16: ='Capex & Depreciation'!K33/4 -> 0 | K16: 0 | L16: =E16-F16-G16-H16-I16-J16-K16 -> 218.95715 | M16: =$B$6 -> 2000 | N16: =M16+L16 -> 2218.9571 | P16: Week Start | Q16: Ending Cash
A17: 2 | B17: 46307 | C17: 46296 | D17: =SUM('Rolling Forecast'!F49:F53)/4 -> 1449.7529 | E17: =D17*$B$8+D16*$B$9+'Working Capital'!E22*35% -> 3677.7017 | F17: =SUM('Rolling Forecast'!H49:H53)/4*$B$10+SUM('Rolling Forecast'!H49:H53)/4*$B$11+'Working Capital'!I22*45% -> 2453.8459 | G17: =SUM('Rolling Forecast'!L49:L53)/4 -> 210.53007 | H17: =SUM('Rolling Forecast'!K49:K53)/4 -> 109.32046 | I17: =SUM('Rolling Forecast'!M49:M53)/4 -> 90.977125 | J17: ='Capex & Depreciation'!K33/4 -> 0 | K17: 0 | L17: =E17-F17-G17-H17-I17-J17-K17 -> 813.02809 | M17: =N16 -> 2218.9571 | N17: =M17+L17 -> 3031.9852 | P17: 46300 | Q17: =N16 -> 2218.9571
A18: 3 | B18: 46314 | C18: 46296 | D18: =SUM('Rolling Forecast'!F49:F53)/4 -> 1449.7529 | E18: =D18*$B$8+D17*$B$9+'Working Capital'!E22*25% -> 3041.1449 | F18: =SUM('Rolling Forecast'!H49:H53)/4*$B$10+SUM('Rolling Forecast'!H49:H53)/4*$B$11 -> 781.00959 | G18: =SUM('Rolling Forecast'!L49:L53)/4 -> 210.53007 | H18: =SUM('Rolling Forecast'!K49:K53)/4 -> 109.32046 | I18: =SUM('Rolling Forecast'!M49:M53)/4 -> 90.977125 | J18: ='Capex & Depreciation'!K33/4 -> 0 | K18: 0 | L18: =E18-F18-G18-H18-I18-J18-K18 -> 1849.3076 | M18: =N17 -> 3031.9852 | N18: =M18+L18 -> 4881.2929 | P18: 46307 | Q18: =N17 -> 3031.9852
A19: 4 | B19: 46321 | C19: 46296 | D19: =SUM('Rolling Forecast'!F49:F53)/4 -> 1449.7529 | E19: =D19*$B$8+D18*$B$9 -> 1449.7529 | F19: =SUM('Rolling Forecast'!H49:H53)/4*$B$10+SUM('Rolling Forecast'!H49:H53)/4*$B$11 -> 781.00959 | G19: =SUM('Rolling Forecast'!L49:L53)/4 -> 210.53007 | H19: =SUM('Rolling Forecast'!K49:K53)/4 -> 109.32046 | I19: =SUM('Rolling Forecast'!M49:M53)/4 -> 90.977125 | J19: ='Capex & Depreciation'!K33/4 -> 0 | K19: 0 | L19: =E19-F19-G19-H19-I19-J19-K19 -> 257.91562 | M19: =N18 -> 4881.2929 | N19: =M19+L19 -> 5139.2085 | P19: 46314 | Q19: =N18 -> 4881.2929
A20: 5 | B20: 46328 | C20: 46327 | D20: =SUM('Rolling Forecast'!F54:F58)/4 -> 1550.6272 | E20: =D20*$B$8+D19*$B$9 -> 1474.9715 | F20: =SUM('Rolling Forecast'!H54:H58)/4*$B$10+SUM('Rolling Forecast'!H49:H53)/4*$B$11 -> 798.67735 | G20: =SUM('Rolling Forecast'!L54:L58)/4 -> 210.53007 | H20: =SUM('Rolling Forecast'!K54:K58)/4 -> 116.882 | I20: =SUM('Rolling Forecast'!M54:M58)/4 -> 92.613125 | J20: ='Capex & Depreciation'!L33/4 -> 77.5 | K20: 0 | L20: =E20-F20-G20-H20-I20-J20-K20 -> 178.76892 | M20: =N19 -> 5139.2085 | N20: =M20+L20 -> 5317.9774 | P20: 46321 | Q20: =N19 -> 5139.2085
A21: 6 | B21: 46335 | C21: 46327 | D21: =SUM('Rolling Forecast'!F54:F58)/4 -> 1550.6272 | E21: =D21*$B$8+D20*$B$9 -> 1550.6272 | F21: =SUM('Rolling Forecast'!H54:H58)/4*$B$10+SUM('Rolling Forecast'!H54:H58)/4*$B$11 -> 839.9021 | G21: =SUM('Rolling Forecast'!L54:L58)/4 -> 210.53007 | H21: =SUM('Rolling Forecast'!K54:K58)/4 -> 116.882 | I21: =SUM('Rolling Forecast'!M54:M58)/4 -> 92.613125 | J21: ='Capex & Depreciation'!L33/4 -> 77.5 | K21: 0 | L21: =E21-F21-G21-H21-I21-J21-K21 -> 213.19995 | M21: =N20 -> 5317.9774 | N21: =M21+L21 -> 5531.1773 | P21: 46328 | Q21: =N20 -> 5317.9774
A22: 7 | B22: 46342 | C22: 46327 | D22: =SUM('Rolling Forecast'!F54:F58)/4 -> 1550.6272 | E22: =D22*$B$8+D21*$B$9 -> 1550.6272 | F22: =SUM('Rolling Forecast'!H54:H58)/4*$B$10+SUM('Rolling Forecast'!H54:H58)/4*$B$11 -> 839.9021 | G22: =SUM('Rolling Forecast'!L54:L58)/4 -> 210.53007 | H22: =SUM('Rolling Forecast'!K54:K58)/4 -> 116.882 | I22: =SUM('Rolling Forecast'!M54:M58)/4 -> 92.613125 | J22: ='Capex & Depreciation'!L33/4 -> 77.5 | K22: 0 | L22: =E22-F22-G22-H22-I22-J22-K22 -> 213.19995 | M22: =N21 -> 5531.1773 | N22: =M22+L22 -> 5744.3773 | P22: 46335 | Q22: =N21 -> 5531.1773
A23: 8 | B23: 46349 | C23: 46327 | D23: =SUM('Rolling Forecast'!F54:F58)/4 -> 1550.6272 | E23: =D23*$B$8+D22*$B$9 -> 1550.6272 | F23: =SUM('Rolling Forecast'!H54:H58)/4*$B$10+SUM('Rolling Forecast'!H54:H58)/4*$B$11 -> 839.9021 | G23: =SUM('Rolling Forecast'!L54:L58)/4 -> 210.53007 | H23: =SUM('Rolling Forecast'!K54:K58)/4 -> 116.882 | I23: =SUM('Rolling Forecast'!M54:M58)/4 -> 92.613125 | J23: ='Capex & Depreciation'!L33/4 -> 77.5 | K23: 0 | L23: =E23-F23-G23-H23-I23-J23-K23 -> 213.19995 | M23: =N22 -> 5744.3773 | N23: =M23+L23 -> 5957.5772 | P23: 46342 | Q23: =N22 -> 5744.3773
A24: 9 | B24: 46356 | C24: 46357 | D24: =SUM('Rolling Forecast'!F59:F63)/5 -> 1314.5478 | E24: =D24*$B$8+D23*$B$9 -> 1491.6074 | F24: =SUM('Rolling Forecast'!H59:H63)/5*$B$10+SUM('Rolling Forecast'!H54:H58)/4*$B$11 -> 800.05594 | G24: =SUM('Rolling Forecast'!L59:L63)/5 -> 168.42406 | H24: =SUM('Rolling Forecast'!K59:K63)/5 -> 98.980561 | I24: =SUM('Rolling Forecast'!M59:M63)/5 -> 73.7554 | J24: ='Capex & Depreciation'!M33/5 -> 0 | K24: 0 | L24: =E24-F24-G24-H24-I24-J24-K24 -> 350.39143 | M24: =N23 -> 5957.5772 | N24: =M24+L24 -> 6307.9687 | P24: 46349 | Q24: =N23 -> 5957.5772
A25: 10 | B25: 46363 | C25: 46357 | D25: =SUM('Rolling Forecast'!F59:F63)/5 -> 1314.5478 | E25: =D25*$B$8+D24*$B$9 -> 1314.5478 | F25: =SUM('Rolling Forecast'!H59:H63)/5*$B$10+SUM('Rolling Forecast'!H59:H63)/5*$B$11 -> 707.08157 | G25: =SUM('Rolling Forecast'!L59:L63)/5 -> 168.42406 | H25: =SUM('Rolling Forecast'!K59:K63)/5 -> 98.980561 | I25: =SUM('Rolling Forecast'!M59:M63)/5 -> 73.7554 | J25: ='Capex & Depreciation'!M33/5 -> 0 | K25: 250 | L25: =E25-F25-G25-H25-I25-J25-K25 -> 16.306209 | M25: =N24 -> 6307.9687 | N25: =M25+L25 -> 6324.2749 | P25: 46356 | Q25: =N24 -> 6307.9687
A26: 11 | B26: 46370 | C26: 46357 | D26: =SUM('Rolling Forecast'!F59:F63)/5 -> 1314.5478 | E26: =D26*$B$8+D25*$B$9 -> 1314.5478 | F26: =SUM('Rolling Forecast'!H59:H63)/5*$B$10+SUM('Rolling Forecast'!H59:H63)/5*$B$11 -> 707.08157 | G26: =SUM('Rolling Forecast'!L59:L63)/5 -> 168.42406 | H26: =SUM('Rolling Forecast'!K59:K63)/5 -> 98.980561 | I26: =SUM('Rolling Forecast'!M59:M63)/5 -> 73.7554 | J26: ='Capex & Depreciation'!M33/5 -> 0 | K26: 0 | L26: =E26-F26-G26-H26-I26-J26-K26 -> 266.30621 | M26: =N25 -> 6324.2749 | N26: =M26+L26 -> 6590.5811 | P26: 46363 | Q26: =N25 -> 6324.2749
A27: 12 | B27: 46377 | C27: 46357 | D27: =SUM('Rolling Forecast'!F59:F63)/5 -> 1314.5478 | E27: =D27*$B$8+D26*$B$9 -> 1314.5478 | F27: =SUM('Rolling Forecast'!H59:H63)/5*$B$10+SUM('Rolling Forecast'!H59:H63)/5*$B$11 -> 707.08157 | G27: =SUM('Rolling Forecast'!L59:L63)/5 -> 168.42406 | H27: =SUM('Rolling Forecast'!K59:K63)/5 -> 98.980561 | I27: =SUM('Rolling Forecast'!M59:M63)/5 -> 73.7554 | J27: ='Capex & Depreciation'!M33/5 -> 0 | K27: 0 | L27: =E27-F27-G27-H27-I27-J27-K27 -> 266.30621 | M27: =N26 -> 6590.5811 | N27: =M27+L27 -> 6856.8873 | P27: 46370 | Q27: =N26 -> 6590.5811
A28: 13 | B28: 46384 | C28: 46357 | D28: =SUM('Rolling Forecast'!F59:F63)/5 -> 1314.5478 | E28: =D28*$B$8+D27*$B$9 -> 1314.5478 | F28: =SUM('Rolling Forecast'!H59:H63)/5*$B$10+SUM('Rolling Forecast'!H59:H63)/5*$B$11 -> 707.08157 | G28: =SUM('Rolling Forecast'!L59:L63)/5 -> 168.42406 | H28: =SUM('Rolling Forecast'!K59:K63)/5 -> 98.980561 | I28: =SUM('Rolling Forecast'!M59:M63)/5 -> 73.7554 | J28: ='Capex & Depreciation'!M33/5 -> 0 | K28: 0 | L28: =E28-F28-G28-H28-I28-J28-K28 -> 266.30621 | M28: =N27 -> 6856.8873 | N28: =M28+L28 -> 7123.1935 | P28: 46377 | Q28: =N27 -> 6856.8873
P29: 46384 | Q29: =N28 -> 7123.1935
A31: Liquidity summary
A32: Metric | B32: Value | C32: Policy / Comparator | D32: Headroom | E32: Status | F32: Notes
A33: Minimum Ending Cash | B33: =MIN(N16:N28) -> 2218.9571 | C33: =$B$7 -> 1000 | D33: =B33-C33 -> 1218.9571 | E33: =IF(D33>=0,"Above policy","Below policy") -> Above policy | F33: Lowest point across 13 weeks
A34: Week 13 Ending Cash | B34: =N28 -> 7123.1935 | C34: =$B$7 -> 1000 | D34: =B34-C34 -> 6123.1935 | E34: =IF(D34>=0,"Above policy","Below policy") -> Above policy | F34: Closing Q4 liquidity

Sheet Investment Appraisal
A1: Capital Investment Appraisal — Warehouse Automation
A3: Illustrative business case using synthetic assumptions. Decision metrics: NPV, IRR and simple payback.
A5: Investment assumptions
A6: Initial Capex (£000) | B6: 900
A7: Project Life (Years) | B7: 5
A8: WACC | B8: 0.095
A9: Corporation Tax Rate | B9: 0.25
A10: Year 1 Incremental Revenue (£000) | B10: 800
A11: Revenue Growth | B11: 0.08
A12: Gross Margin | B12: 0.46
A13: Year 1 Cost Savings (£000) | B13: 250
A14: Cost Saving Growth | B14: 0.03
A15: Annual Maintenance (£000) | B15: 120
A18: 5-year discounted cash-flow business case (£000)
A19: Metric | B19: Year 0 | C19: Year 1 | D19: Year 2 | E19: Year 3 | F19: Year 4 | G19: Year 5
A20: Incremental Revenue | B20: 0 | C20: =$B$10 -> 800 | D20: =C20*(1+$B$11) -> 864 | E20: =D20*(1+$B$11) -> 933.12 | F20: =E20*(1+$B$11) -> 1007.7696 | G20: =F20*(1+$B$11) -> 1088.3912
A21: Gross Profit | B21: 0 | C21: =C20*$B$12 -> 368 | D21: =D20*$B$12 -> 397.44 | E21: =E20*$B$12 -> 429.2352 | F21: =F20*$B$12 -> 463.57402 | G21: =G20*$B$12 -> 500.65994
A22: Cost Savings | B22: 0 | C22: =$B$13 -> 250 | D22: =C22*(1+$B$14) -> 257.5 | E22: =D22*(1+$B$14) -> 265.225 | F22: =E22*(1+$B$14) -> 273.18175 | G22: =F22*(1+$B$14) -> 281.3772
A23: Maintenance | B23: 0 | C23: =-$B$15 -> -120 | D23: =-$B$15 -> -120 | E23: =-$B$15 -> -120 | F23: =-$B$15 -> -120 | G23: =-$B$15 -> -120
A24: EBITDA | B24: 0 | C24: =C21+C22+C23 -> 498 | D24: =D21+D22+D23 -> 534.94 | E24: =E21+E22+E23 -> 574.4602 | F24: =F21+F22+F23 -> 616.75577 | G24: =G21+G22+G23 -> 662.03714
A25: Depreciation | B25: 0 | C25: =-$B$6/$B$7 -> -180 | D25: =-$B$6/$B$7 -> -180 | E25: =-$B$6/$B$7 -> -180 | F25: =-$B$6/$B$7 -> -180 | G25: =-$B$6/$B$7 -> -180
A26: EBIT | B26: 0 | C26: =C24+C25 -> 318 | D26: =D24+D25 -> 354.94 | E26: =E24+E25 -> 394.4602 | F26: =F24+F25 -> 436.75577 | G26: =G24+G25 -> 482.03714
A27: Tax | B27: 0 | C27: =IF(C26>0,-C26*$B$9,0) -> -79.5 | D27: =IF(D26>0,-D26*$B$9,0) -> -88.735 | E27: =IF(E26>0,-E26*$B$9,0) -> -98.61505 | F27: =IF(F26>0,-F26*$B$9,0) -> -109.18894 | G27: =IF(G26>0,-G26*$B$9,0) -> -120.50928
A28: NOPAT | B28: 0 | C28: =C26+C27 -> 238.5 | D28: =D26+D27 -> 266.205 | E28: =E26+E27 -> 295.84515 | F28: =F26+F27 -> 327.56682 | G28: =G26+G27 -> 361.52785
A29: Add: Depreciation | B29: 0 | C29: =-C25 -> 180 | D29: =-D25 -> 180 | E29: =-E25 -> 180 | F29: =-F25 -> 180 | G29: =-G25 -> 180
A30: Initial / Replacement Capex | B30: 0 | C30: =0 -> 0 | D30: =0 -> 0 | E30: =0 -> 0 | F30: =0 -> 0 | G30: =0 -> 0
A31: Change in NWC | B31: 0 | C31: =-C20*5% -> -40 | D31: =-(D20-C20)*5% -> -3.2 | E31: =-(E20-D20)*5% -> -3.456 | F31: =-(F20-E20)*5% -> -3.73248 | G31: =-(G20-F20)*5%+G20*5% -> 50.38848
A32: Free Cash Flow | B32: =-$B$6 -> -900 | C32: =0 -> 0 | D32: =0 -> 0 | E32: =0 -> 0 | F32: =0 -> 0 | G32: =0 -> 0
A33: Discount Factor | B33: =0 -> 0 | C33: =C28+C29+C30+C31 -> 378.5 | D33: =D28+D29+D30+D31 -> 443.005 | E33: =E28+E29+E30+E31 -> 472.38915 | F33: =F28+F29+F30+F31 -> 503.83434 | G33: =G28+G29+G30+G31 -> 591.91633
A34: Present Value | B34: =-$B$6 -> -900 | C34: =C33 -> 378.5 | D34: =D33 -> 443.005 | E34: =E33 -> 472.38915 | F34: =F33 -> 503.83434 | G34: =G33 -> 591.91633
A35: Cumulative FCF | B35: =1 -> 1 | C35: =1/(1+$B$8)^1 -> 0.91324201 | D35: =1/(1+$B$8)^2 -> 0.83401097 | E35: =1/(1+$B$8)^3 -> 0.76165385 | F35: =1/(1+$B$8)^4 -> 0.69557429 | G35: =1/(1+$B$8)^5 -> 0.63522767
B36: =B34 -> -900 | C36: =C34*C35 -> 345.6621 | D36: =D34*D35 -> 369.47103 | E36: =E34*E35 -> 359.79702 | F36: =F34*F35 -> 350.45422 | G36: =G34*G35 -> 376.00163
B37: =B34 -> -900 | C37: =B37+C34 -> -521.5 | D37: =C37+D34 -> -78.495 | E37: =D37+E34 -> 393.89415 | F37: =E37+F34 -> 897.72849 | G37: =F37+G34 -> 1489.6448
A40: Investment decision summary | F40: NPV sensitivity (£000)
A41: Metric | B41: Result | C41: Threshold / Rule | D41: Interpretation | F41: Revenue Case | G41: 8.0% | H41: 9.5% | I41: 11.0%
A42: NPV (£000) | B42: =SUM(B36:G36) -> 901.38599 | C42: > 0 | D42: Value creation | F42: 90% | G42: =-$B$6+(C34*0.9)/(1+0.08)^1+(D34*0.9)/(1+0.08)^2+(E34*0.9)/(1+0.08)^3+(F34*0.9)/(1+0.08)^4+(G34*0.9)/(1+0.08)^5 -> 790.60291 | H42: =-$B$6+(C34*0.9)/(1+0.095)^1+(D34*0.9)/(1+0.095)^2+(E34*0.9)/(1+0.095)^3+(F34*0.9)/(1+0.095)^4+(G34*0.9)/(1+0.095)^5 -> 721.24739 | I42: =-$B$6+(C34*0.9)/(1+0.11)^1+(D34*0.9)/(1+0.11)^2+(E34*0.9)/(1+0.11)^3+(F34*0.9)/(1+0.11)^4+(G34*0.9)/(1+0.11)^5 -> 656.20394
A43: IRR | B43: =IRR(B34:G34) -> 0.40594909 | C43: > WACC | D43: Return vs hurdle rate | F43: 100% | G43: =-$B$6+(C34*1)/(1+0.08)^1+(D34*1)/(1+0.08)^2+(E34*1)/(1+0.08)^3+(F34*1)/(1+0.08)^4+(G34*1)/(1+0.08)^5 -> 978.44768 | H43: =-$B$6+(C34*1)/(1+0.095)^1+(D34*1)/(1+0.095)^2+(E34*1)/(1+0.095)^3+(F34*1)/(1+0.095)^4+(G34*1)/(1+0.095)^5 -> 901.38599 | I43: =-$B$6+(C34*1)/(1+0.11)^1+(D34*1)/(1+0.11)^2+(E34*1)/(1+0.11)^3+(F34*1)/(1+0.11)^4+(G34*1)/(1+0.11)^5 -> 829.11549
A44: Simple Payback | B44: =IF(C37>=0,"1 year",IF(D37>=0,"2 years",IF(E37>=0,"3 years",IF(F37>=0,"4 years",IF(G37>=0,"5 years",">5 years"))))) -> 3 years | C44: ≤ 5 years | D44: Liquidity / recovery | F44: 110% | G44: =-$B$6+(C34*1.1)/(1+0.08)^1+(D34*1.1)/(1+0.08)^2+(E34*1.1)/(1+0.08)^3+(F34*1.1)/(1+0.08)^4+(G34*1.1)/(1+0.08)^5 -> 1166.2924 | H44: =-$B$6+(C34*1.1)/(1+0.095)^1+(D34*1.1)/(1+0.095)^2+(E34*1.1)/(1+0.095)^3+(F34*1.1)/(1+0.095)^4+(G34*1.1)/(1+0.095)^5 -> 1081.5246 | I44: =-$B$6+(C34*1.1)/(1+0.11)^1+(D34*1.1)/(1+0.11)^2+(E34*1.1)/(1+0.11)^3+(F34*1.1)/(1+0.11)^4+(G34*1.1)/(1+0.11)^5 -> 1002.027
A45: Decision | B45: =IF(AND(B42>0,B43>$B$8),"Proceed","Do not proceed") -> Proceed | C45: Proceed only if NPV > 0 and IRR > WACC | D45: Portfolio case-study output

Sheet PVM Analysis
A1: FY2026 Price–Volume–Mix & Gross Margin Bridge
A3: Full-year Budget vs Rolling Forecast. PVM separates revenue variance into total volume, portfolio mix and price effects.
A5: Revenue Price–Volume–Mix bridge by division
A6: Division | B6: Budget Units | C6: Forecast Units | D6: Budget Mix % | E6: Forecast Mix % | F6: Budget ASP (£/unit) | G6: Forecast ASP (£/unit) | H6: Volume Effect (£000) | I6: Mix Effect (£000) | J6: Price Effect (£000) | K6: PVM Total (£000) | L6: Revenue Variance (£000) | M6: Control (£000) | N6: Primary Driver
A7: Personal Care | B7: =ROUND('Budget 2026'!D4+'Budget 2026'!D9+'Budget 2026'!D14+'Budget 2026'!D19+'Budget 2026'!D24+'Budget 2026'!D29+'Budget 2026'!D34+'Budget 2026'!D39+'Budget 2026'!D44+'Budget 2026'!D49+'Budget 2026'!D54+'Budget 2026'!D59,0) -> 1622196 | C7: =ROUND('Rolling Forecast'!D4+'Rolling Forecast'!D9+'Rolling Forecast'!D14+'Rolling Forecast'!D19+'Rolling Forecast'!D24+'Rolling Forecast'!D29+'Rolling Forecast'!D34+'Rolling Forecast'!D39+'Rolling Forecast'!D44+'Rolling Forecast'!D49+'Rolling Forecast'!D54+'Rolling Forecast'!D59,0) -> 1604404 | D7: =B7/$B$14 -> 0.29949365 | E7: =C7/$C$14 -> 0.29731579 | F7: =ROUND(('Budget 2026'!I4+'Budget 2026'!I9+'Budget 2026'!I14+'Budget 2026'!I19+'Budget 2026'!I24+'Budget 2026'!I29+'Budget 2026'!I34+'Budget 2026'!I39+'Budget 2026'!I44+'Budget 2026'!I49+'Budget 2026'!I54+'Budget 2026'!I59)*1000/B7,2) -> 8.88 | G7: =ROUND(('Rolling Forecast'!F4+'Rolling Forecast'!F9+'Rolling Forecast'!F14+'Rolling Forecast'!F19+'Rolling Forecast'!F24+'Rolling Forecast'!F29+'Rolling Forecast'!F34+'Rolling Forecast'!F39+'Rolling Forecast'!F44+'Rolling Forecast'!F49+'Rolling Forecast'!F54+'Rolling Forecast'!F59)*1000/C7,2) -> 8.86 | H7: =ROUND((SUM('Rolling Forecast'!D4:D63)-SUM('Budget 2026'!D4:D63))*(('Budget 2026'!D4+'Budget 2026'!D9+'Budget 2026'!D14+'Budget 2026'!D19+'Budget 2026'!D24+'Budget 2026'!D29+'Budget 2026'!D34+'Budget 2026'!D39+'Budget 2026'!D44+'Budget 2026'!D49+'Budget 2026'!D54+'Budget 2026'!D59)/SUM('Budget 2026'!D4:D63))*(('Budget 2026'!I4+'Budget 2026'!I9+'Budget 2026'!I14+'Budget 2026'!I19+'Budget 2026'!I24+'Budget 2026'!I29+'Budget 2026'!I34+'Budget 2026'!I39+'Budget 2026'!I44+'Budget 2026'!I49+'Budget 2026'!I54+'Budget 2026'!I59)*1000/('Budget 2026'!D4+'Budget 2026'!D9+'Budget 2026'!D14+'Budget 2026'!D19+'Budget 2026'!D24+'Budget 2026'!D29+'Budget 2026'!D34+'Budget 2026'!D39+'Budget 2026'!D44+'Budget 2026'!D49+'Budget 2026'!D54+'Budget 2026'!D59))/1000,2) -> -53.61 | I7: =ROUND(SUM('Rolling Forecast'!D4:D63)*((('Rolling Forecast'!D4+'Rolling Forecast'!D9+'Rolling Forecast'!D14+'Rolling Forecast'!D19+'Rolling Forecast'!D24+'Rolling Forecast'!D29+'Rolling Forecast'!D34+'Rolling Forecast'!D39+'Rolling Forecast'!D44+'Rolling Forecast'!D49+'Rolling Forecast'!D54+'Rolling Forecast'!D59)/SUM('Rolling Forecast'!D4:D63))-(('Budget 2026'!D4+'Budget 2026'!D9+'Budget 2026'!D14+'Budget 2026'!D19+'Budget 2026'!D24+'Budget 2026'!D29+'Budget 2026'!D34+'Budget 2026'!D39+'Budget 2026'!D44+'Budget 2026'!D49+'Budget 2026'!D54+'Budget 2026'!D59)/SUM('Budget 2026'!D4:D63)))*(('Budget 2026'!I4+'Budget 2026'!I9+'Budget 2026'!I14+'Budget 2026'!I19+'Budget 2026'!I24+'Budget 2026'!I29+'Budget 2026'!I34+'Budget 2026'!I39+'Budget 2026'!I44+'Budget 2026'!I49+'Budget 2026'!I54+'Budget 2026'!I59)*1000/('Budget 2026'!D4+'Budget 2026'!D9+'Budget 2026'!D14+'Budget 2026'!D19+'Budget 2026'!D24+'Budget 2026'!D29+'Budget 2026'!D34+'Budget 2026'!D39+'Budget 2026'!D44+'Budget 2026'!D49+'Budget 2026'!D54+'Budget 2026'!D59))/1000,2) -> -104.31 | J7: =ROUND(('Rolling Forecast'!D4+'Rolling Forecast'!D9+'Rolling Forecast'!D14+'Rolling Forecast'!D19+'Rolling Forecast'!D24+'Rolling Forecast'!D29+'Rolling Forecast'!D34+'Rolling Forecast'!D39+'Rolling Forecast'!D44+'Rolling Forecast'!D49+'Rolling Forecast'!D54+'Rolling Forecast'!D59)*((('Rolling Forecast'!F4+'Rolling Forecast'!F9+'Rolling Forecast'!F14+'Rolling Forecast'!F19+'Rolling Forecast'!F24+'Rolling Forecast'!F29+'Rolling Forecast'!F34+'Rolling Forecast'!F39+'Rolling Forecast'!F44+'Rolling Forecast'!F49+'Rolling Forecast'!F54+'Rolling Forecast'!F59)*1000/('Rolling Forecast'!D4+'Rolling Forecast'!D9+'Rolling Forecast'!D14+'Rolling Forecast'!D19+'Rolling Forecast'!D24+'Rolling Forecast'!D29+'Rolling Forecast'!D34+'Rolling Forecast'!D39+'Rolling Forecast'!D44+'Rolling Forecast'!D49+'Rolling Forecast'!D54+'Rolling Forecast'!D59))-(('Budget 2026'!I4+'Budget 2026'!I9+'Budget 2026'!I14+'Budget 2026'!I19+'Budget 2026'!I24+'Budget 2026'!I29+'Budget 2026'!I34+'Budget 2026'!I39+'Budget 2026'!I44+'Budget 2026'!I49+'Budget 2026'!I54+'Budget 2026'!I59)*1000/('Budget 2026'!D4+'Budget 2026'!D9+'Budget 2026'!D14+'Budget 2026'!D19+'Budget 2026'!D24+'Budget 2026'!D29+'Budget 2026'!D34+'Budget 2026'!D39+'Budget 2026'!D44+'Budget 2026'!D49+'Budget 2026'!D54+'Budget 2026'!D59)))/1000,2) -> -27.35 | K7: =ROUND(H7+I7+J7,2) -> -185.27 | L7: =ROUND(('Rolling Forecast'!F4+'Rolling Forecast'!F9+'Rolling Forecast'!F14+'Rolling Forecast'!F19+'Rolling Forecast'!F24+'Rolling Forecast'!F29+'Rolling Forecast'!F34+'Rolling Forecast'!F39+'Rolling Forecast'!F44+'Rolling Forecast'!F49+'Rolling Forecast'!F54+'Rolling Forecast'!F59)-('Budget 2026'!I4+'Budget 2026'!I9+'Budget 2026'!I14+'Budget 2026'!I19+'Budget 2026'!I24+'Budget 2026'!I29+'Budget 2026'!I34+'Budget 2026'!I39+'Budget 2026'!I44+'Budget 2026'!I49+'Budget 2026'!I54+'Budget 2026'!I59),2) -> -185.27 | M7: =ROUND(K7-L7,2) -> 0 | N7: =IF(ABS(H7)>=ABS(I7),IF(ABS(H7)>=ABS(J7),"Volume","Price"),IF(ABS(I7)>=ABS(J7),"Mix","Price")) -> Mix
A8: Home Care | B8: =ROUND('Budget 2026'!D5+'Budget 2026'!D10+'Budget 2026'!D15+'Budget 2026'!D20+'Budget 2026'!D25+'Budget 2026'!D30+'Budget 2026'!D35+'Budget 2026'!D40+'Budget 2026'!D45+'Budget 2026'!D50+'Budget 2026'!D55+'Budget 2026'!D60,0) -> 1263283 | C8: =ROUND('Rolling Forecast'!D5+'Rolling Forecast'!D10+'Rolling Forecast'!D15+'Rolling Forecast'!D20+'Rolling Forecast'!D25+'Rolling Forecast'!D30+'Rolling Forecast'!D35+'Rolling Forecast'!D40+'Rolling Forecast'!D45+'Rolling Forecast'!D50+'Rolling Forecast'!D55+'Rolling Forecast'!D60,0) -> 1269142 | D8: =B8/$B$14 -> 0.23323029 | E8: =C8/$C$14 -> 0.23518762 | F8: =ROUND(('Budget 2026'!I5+'Budget 2026'!I10+'Budget 2026'!I15+'Budget 2026'!I20+'Budget 2026'!I25+'Budget 2026'!I30+'Budget 2026'!I35+'Budget 2026'!I40+'Budget 2026'!I45+'Budget 2026'!I50+'Budget 2026'!I55+'Budget 2026'!I60)*1000/B8,2) -> 10.75 | G8: =ROUND(('Rolling Forecast'!F5+'Rolling Forecast'!F10+'Rolling Forecast'!F15+'Rolling Forecast'!F20+'Rolling Forecast'!F25+'Rolling Forecast'!F30+'Rolling Forecast'!F35+'Rolling Forecast'!F40+'Rolling Forecast'!F45+'Rolling Forecast'!F50+'Rolling Forecast'!F55+'Rolling Forecast'!F60)*1000/C8,2) -> 10.74 | H8: =ROUND((SUM('Rolling Forecast'!D4:D63)-SUM('Budget 2026'!D4:D63))*(('Budget 2026'!D5+'Budget 2026'!D10+'Budget 2026'!D15+'Budget 2026'!D20+'Budget 2026'!D25+'Budget 2026'!D30+'Budget 2026'!D35+'Budget 2026'!D40+'Budget 2026'!D45+'Budget 2026'!D50+'Budget 2026'!D55+'Budget 2026'!D60)/SUM('Budget 2026'!D4:D63))*(('Budget 2026'!I5+'Budget 2026'!I10+'Budget 2026'!I15+'Budget 2026'!I20+'Budget 2026'!I25+'Budget 2026'!I30+'Budget 2026'!I35+'Budget 2026'!I40+'Budget 2026'!I45+'Budget 2026'!I50+'Budget 2026'!I55+'Budget 2026'!I60)*1000/('Budget 2026'!D5+'Budget 2026'!D10+'Budget 2026'!D15+'Budget 2026'!D20+'Budget 2026'!D25+'Budget 2026'!D30+'Budget 2026'!D35+'Budget 2026'!D40+'Budget 2026'!D45+'Budget 2026'!D50+'Budget 2026'!D55+'Budget 2026'!D60))/1000,2) -> -50.57 | I8: =ROUND(SUM('Rolling Forecast'!D4:D63)*((('Rolling Forecast'!D5+'Rolling Forecast'!D10+'Rolling Forecast'!D15+'Rolling Forecast'!D20+'Rolling Forecast'!D25+'Rolling Forecast'!D30+'Rolling Forecast'!D35+'Rolling Forecast'!D40+'Rolling Forecast'!D45+'Rolling Forecast'!D50+'Rolling Forecast'!D55+'Rolling Forecast'!D60)/SUM('Rolling Forecast'!D4:D63))-(('Budget 2026'!D5+'Budget 2026'!D10+'Budget 2026'!D15+'Budget 2026'!D20+'Budget 2026'!D25+'Budget 2026'!D30+'Budget 2026'!D35+'Budget 2026'!D40+'Budget 2026'!D45+'Budget 2026'!D50+'Budget 2026'!D55+'Budget 2026'!D60)/SUM('Budget 2026'!D4:D63)))*(('Budget 2026'!I5+'Budget 2026'!I10+'Budget 2026'!I15+'Budget 2026'!I20+'Budget 2026'!I25+'Budget 2026'!I30+'Budget 2026'!I35+'Budget 2026'!I40+'Budget 2026'!I45+'Budget 2026'!I50+'Budget 2026'!I55+'Budget 2026'!I60)*1000/('Budget 2026'!D5+'Budget 2026'!D10+'Budget 2026'!D15+'Budget 2026'!D20+'Budget 2026'!D25+'Budget 2026'!D30+'Budget 2026'!D35+'Budget 2026'!D40+'Budget 2026'!D45+'Budget 2026'!D50+'Budget 2026'!D55+'Budget 2026'!D60))/1000,2) -> 113.56 | J8: =ROUND(('Rolling Forecast'!D5+'Rolling Forecast'!D10+'Rolling Forecast'!D15+'Rolling Forecast'!D20+'Rolling Forecast'!D25+'Rolling Forecast'!D30+'Rolling Forecast'!D35+'Rolling Forecast'!D40+'Rolling Forecast'!D45+'Rolling Forecast'!D50+'Rolling Forecast'!D55+'Rolling Forecast'!D60)*((('Rolling Forecast'!F5+'Rolling Forecast'!F10+'Rolling Forecast'!F15+'Rolling Forecast'!F20+'Rolling Forecast'!F25+'Rolling Forecast'!F30+'Rolling Forecast'!F35+'Rolling Forecast'!F40+'Rolling Forecast'!F45+'Rolling Forecast'!F50+'Rolling Forecast'!F55+'Rolling Forecast'!F60)*1000/('Rolling Forecast'!D5+'Rolling Forecast'!D10+'Rolling Forecast'!D15+'Rolling Forecast'!D20+'Rolling Forecast'!D25+'Rolling Forecast'!D30+'Rolling Forecast'!D35+'Rolling Forecast'!D40+'Rolling Forecast'!D45+'Rolling Forecast'!D50+'Rolling Forecast'!D55+'Rolling Forecast'!D60))-(('Budget 2026'!I5+'Budget 2026'!I10+'Budget 2026'!I15+'Budget 2026'!I20+'Budget 2026'!I25+'Budget 2026'!I30+'Budget 2026'!I35+'Budget 2026'!I40+'Budget 2026'!I45+'Budget 2026'!I50+'Budget 2026'!I55+'Budget 2026'!I60)*1000/('Budget 2026'!D5+'Budget 2026'!D10+'Budget 2026'!D15+'Budget 2026'!D20+'Budget 2026'!D25+'Budget 2026'!D30+'Budget 2026'!D35+'Budget 2026'!D40+'Budget 2026'!D45+'Budget 2026'!D50+'Budget 2026'!D55+'Budget 2026'!D60)))/1000,2) -> -17.13 | K8: =ROUND(H8+I8+J8,2) -> 45.86 | L8: =ROUND(('Rolling Forecast'!F5+'Rolling Forecast'!F10+'Rolling Forecast'!F15+'Rolling Forecast'!F20+'Rolling Forecast'!F25+'Rolling Forecast'!F30+'Rolling Forecast'!F35+'Rolling Forecast'!F40+'Rolling Forecast'!F45+'Rolling Forecast'!F50+'Rolling Forecast'!F55+'Rolling Forecast'!F60)-('Budget 2026'!I5+'Budget 2026'!I10+'Budget 2026'!I15+'Budget 2026'!I20+'Budget 2026'!I25+'Budget 2026'!I30+'Budget 2026'!I35+'Budget 2026'!I40+'Budget 2026'!I45+'Budget 2026'!I50+'Budget 2026'!I55+'Budget 2026'!I60),2) -> 45.85 | M8: =ROUND(K8-L8,2) -> 0.01 | N8: =IF(ABS(H8)>=ABS(I8),IF(ABS(H8)>=ABS(J8),"Volume","Price"),IF(ABS(I8)>=ABS(J8),"Mix","Price")) -> Mix
A9: Nutrition & Wellness | B9: =ROUND('Budget 2026'!D6+'Budget 2026'!D11+'Budget 2026'!D16+'Budget 2026'!D21+'Budget 2026'!D26+'Budget 2026'!D31+'Budget 2026'!D36+'Budget 2026'!D41+'Budget 2026'!D46+'Budget 2026'!D51+'Budget 2026'!D56+'Budget 2026'!D61,0) -> 1021772 | C9: =ROUND('Rolling Forecast'!D6+'Rolling Forecast'!D11+'Rolling Forecast'!D16+'Rolling Forecast'!D21+'Rolling Forecast'!D26+'Rolling Forecast'!D31+'Rolling Forecast'!D36+'Rolling Forecast'!D41+'Rolling Forecast'!D46+'Rolling Forecast'!D51+'Rolling Forecast'!D56+'Rolling Forecast'!D61,0) -> 1008855 | D9: =B9/$B$14 -> 0.18864196 | E9: =C9/$C$14 -> 0.18695324 | F9: =ROUND(('Budget 2026'!I6+'Budget 2026'!I11+'Budget 2026'!I16+'Budget 2026'!I21+'Budget 2026'!I26+'Budget 2026'!I31+'Budget 2026'!I36+'Budget 2026'!I41+'Budget 2026'!I46+'Budget 2026'!I51+'Budget 2026'!I56+'Budget 2026'!I61)*1000/B9,2) -> 15.7 | G9: =ROUND(('Rolling Forecast'!F6+'Rolling Forecast'!F11+'Rolling Forecast'!F16+'Rolling Forecast'!F21+'Rolling Forecast'!F26+'Rolling Forecast'!F31+'Rolling Forecast'!F36+'Rolling Forecast'!F41+'Rolling Forecast'!F46+'Rolling Forecast'!F51+'Rolling Forecast'!F56+'Rolling Forecast'!F61)*1000/C9,2) -> 15.62 | H9: =ROUND((SUM('Rolling Forecast'!D4:D63)-SUM('Budget 2026'!D4:D63))*(('Budget 2026'!D6+'Budget 2026'!D11+'Budget 2026'!D16+'Budget 2026'!D21+'Budget 2026'!D26+'Budget 2026'!D31+'Budget 2026'!D36+'Budget 2026'!D41+'Budget 2026'!D46+'Budget 2026'!D51+'Budget 2026'!D56+'Budget 2026'!D61)/SUM('Budget 2026'!D4:D63))*(('Budget 2026'!I6+'Budget 2026'!I11+'Budget 2026'!I16+'Budget 2026'!I21+'Budget 2026'!I26+'Budget 2026'!I31+'Budget 2026'!I36+'Budget 2026'!I41+'Budget 2026'!I46+'Budget 2026'!I51+'Budget 2026'!I56+'Budget 2026'!I61)*1000/('Budget 2026'!D6+'Budget 2026'!D11+'Budget 2026'!D16+'Budget 2026'!D21+'Budget 2026'!D26+'Budget 2026'!D31+'Budget 2026'!D36+'Budget 2026'!D41+'Budget 2026'!D46+'Budget 2026'!D51+'Budget 2026'!D56+'Budget 2026'!D61))/1000,2) -> -59.73 | I9: =ROUND(SUM('Rolling Forecast'!D4:D63)*((('Rolling Forecast'!D6+'Rolling Forecast'!D11+'Rolling Forecast'!D16+'Rolling Forecast'!D21+'Rolling Forecast'!D26+'Rolling Forecast'!D31+'Rolling Forecast'!D36+'Rolling Forecast'!D41+'Rolling Forecast'!D46+'Rolling Forecast'!D51+'Rolling Forecast'!D56+'Rolling Forecast'!D61)/SUM('Rolling Forecast'!D4:D63))-(('Budget 2026'!D6+'Budget 2026'!D11+'Budget 2026'!D16+'Budget 2026'!D21+'Budget 2026'!D26+'Budget 2026'!D31+'Budget 2026'!D36+'Budget 2026'!D41+'Budget 2026'!D46+'Budget 2026'!D51+'Budget 2026'!D56+'Budget 2026'!D61)/SUM('Budget 2026'!D4:D63)))*(('Budget 2026'!I6+'Budget 2026'!I11+'Budget 2026'!I16+'Budget 2026'!I21+'Budget 2026'!I26+'Budget 2026'!I31+'Budget 2026'!I36+'Budget 2026'!I41+'Budget 2026'!I46+'Budget 2026'!I51+'Budget 2026'!I56+'Budget 2026'!I61)*1000/('Budget 2026'!D6+'Budget 2026'!D11+'Budget 2026'!D16+'Budget 2026'!D21+'Budget 2026'!D26+'Budget 2026'!D31+'Budget 2026'!D36+'Budget 2026'!D41+'Budget 2026'!D46+'Budget 2026'!D51+'Budget 2026'!D56+'Budget 2026'!D61))/1000,2) -> -143.09 | J9: =ROUND(('Rolling Forecast'!D6+'Rolling Forecast'!D11+'Rolling Forecast'!D16+'Rolling Forecast'!D21+'Rolling Forecast'!D26+'Rolling Forecast'!D31+'Rolling Forecast'!D36+'Rolling Forecast'!D41+'Rolling Forecast'!D46+'Rolling Forecast'!D51+'Rolling Forecast'!D56+'Rolling Forecast'!D61)*((('Rolling Forecast'!F6+'Rolling Forecast'!F11+'Rolling Forecast'!F16+'Rolling Forecast'!F21+'Rolling Forecast'!F26+'Rolling Forecast'!F31+'Rolling Forecast'!F36+'Rolling Forecast'!F41+'Rolling Forecast'!F46+'Rolling Forecast'!F51+'Rolling Forecast'!F56+'Rolling Forecast'!F61)*1000/('Rolling Forecast'!D6+'Rolling Forecast'!D11+'Rolling Forecast'!D16+'Rolling Forecast'!D21+'Rolling Forecast'!D26+'Rolling Forecast'!D31+'Rolling Forecast'!D36+'Rolling Forecast'!D41+'Rolling Forecast'!D46+'Rolling Forecast'!D51+'Rolling Forecast'!D56+'Rolling Forecast'!D61))-(('Budget 2026'!I6+'Budget 2026'!I11+'Budget 2026'!I16+'Budget 2026'!I21+'Budget 2026'!I26+'Budget 2026'!I31+'Budget 2026'!I36+'Budget 2026'!I41+'Budget 2026'!I46+'Budget 2026'!I51+'Budget 2026'!I56+'Budget 2026'!I61)*1000/('Budget 2026'!D6+'Budget 2026'!D11+'Budget 2026'!D16+'Budget 2026'!D21+'Budget 2026'!D26+'Budget 2026'!D31+'Budget 2026'!D36+'Budget 2026'!D41+'Budget 2026'!D46+'Budget 2026'!D51+'Budget 2026'!D56+'Budget 2026'!D61)))/1000,2) -> -85.31 | K9: =ROUND(H9+I9+J9,2) -> -288.13 | L9: =ROUND(('Rolling Forecast'!F6+'Rolling Forecast'!F11+'Rolling Forecast'!F16+'Rolling Forecast'!F21+'Rolling Forecast'!F26+'Rolling Forecast'!F31+'Rolling Forecast'!F36+'Rolling Forecast'!F41+'Rolling Forecast'!F46+'Rolling Forecast'!F51+'Rolling Forecast'!F56+'Rolling Forecast'!F61)-('Budget 2026'!I6+'Budget 2026'!I11+'Budget 2026'!I16+'Budget 2026'!I21+'Budget 2026'!I26+'Budget 2026'!I31+'Budget 2026'!I36+'Budget 2026'!I41+'Budget 2026'!I46+'Budget 2026'!I51+'Budget 2026'!I56+'Budget 2026'!I61),2) -> -288.14 | M9: =ROUND(K9-L9,2) -> 0.01 | N9: =IF(ABS(H9)>=ABS(I9),IF(ABS(H9)>=ABS(J9),"Volume","Price"),IF(ABS(I9)>=ABS(J9),"Mix","Price")) -> Mix
A10: Baby & Kids | B10: =ROUND('Budget 2026'!D7+'Budget 2026'!D12+'Budget 2026'!D17+'Budget 2026'!D22+'Budget 2026'!D27+'Budget 2026'!D32+'Budget 2026'!D37+'Budget 2026'!D42+'Budget 2026'!D47+'Budget 2026'!D52+'Budget 2026'!D57+'Budget 2026'!D62,0) -> 853500 | C10: =ROUND('Rolling Forecast'!D7+'Rolling Forecast'!D12+'Rolling Forecast'!D17+'Rolling Forecast'!D22+'Rolling Forecast'!D27+'Rolling Forecast'!D32+'Rolling Forecast'!D37+'Rolling Forecast'!D42+'Rolling Forecast'!D47+'Rolling Forecast'!D52+'Rolling Forecast'!D57+'Rolling Forecast'!D62,0) -> 846135 | D10: =B10/$B$14 -> 0.15757518 | E10: =C10/$C$14 -> 0.15679922 | F10: =ROUND(('Budget 2026'!I7+'Budget 2026'!I12+'Budget 2026'!I17+'Budget 2026'!I22+'Budget 2026'!I27+'Budget 2026'!I32+'Budget 2026'!I37+'Budget 2026'!I42+'Budget 2026'!I47+'Budget 2026'!I52+'Budget 2026'!I57+'Budget 2026'!I62)*1000/B10,2) -> 13.09 | G10: =ROUND(('Rolling Forecast'!F7+'Rolling Forecast'!F12+'Rolling Forecast'!F17+'Rolling Forecast'!F22+'Rolling Forecast'!F27+'Rolling Forecast'!F32+'Rolling Forecast'!F37+'Rolling Forecast'!F42+'Rolling Forecast'!F47+'Rolling Forecast'!F52+'Rolling Forecast'!F57+'Rolling Forecast'!F62)*1000/C10,2) -> 13.08 | H10: =ROUND((SUM('Rolling Forecast'!D4:D63)-SUM('Budget 2026'!D4:D63))*(('Budget 2026'!D7+'Budget 2026'!D12+'Budget 2026'!D17+'Budget 2026'!D22+'Budget 2026'!D27+'Budget 2026'!D32+'Budget 2026'!D37+'Budget 2026'!D42+'Budget 2026'!D47+'Budget 2026'!D52+'Budget 2026'!D57+'Budget 2026'!D62)/SUM('Budget 2026'!D4:D63))*(('Budget 2026'!I7+'Budget 2026'!I12+'Budget 2026'!I17+'Budget 2026'!I22+'Budget 2026'!I27+'Budget 2026'!I32+'Budget 2026'!I37+'Budget 2026'!I42+'Budget 2026'!I47+'Budget 2026'!I52+'Budget 2026'!I57+'Budget 2026'!I62)*1000/('Budget 2026'!D7+'Budget 2026'!D12+'Budget 2026'!D17+'Budget 2026'!D22+'Budget 2026'!D27+'Budget 2026'!D32+'Budget 2026'!D37+'Budget 2026'!D42+'Budget 2026'!D47+'Budget 2026'!D52+'Budget 2026'!D57+'Budget 2026'!D62))/1000,2) -> -41.59 | I10: =ROUND(SUM('Rolling Forecast'!D4:D63)*((('Rolling Forecast'!D7+'Rolling Forecast'!D12+'Rolling Forecast'!D17+'Rolling Forecast'!D22+'Rolling Forecast'!D27+'Rolling Forecast'!D32+'Rolling Forecast'!D37+'Rolling Forecast'!D42+'Rolling Forecast'!D47+'Rolling Forecast'!D52+'Rolling Forecast'!D57+'Rolling Forecast'!D62)/SUM('Rolling Forecast'!D4:D63))-(('Budget 2026'!D7+'Budget 2026'!D12+'Budget 2026'!D17+'Budget 2026'!D22+'Budget 2026'!D27+'Budget 2026'!D32+'Budget 2026'!D37+'Budget 2026'!D42+'Budget 2026'!D47+'Budget 2026'!D52+'Budget 2026'!D57+'Budget 2026'!D62)/SUM('Budget 2026'!D4:D63)))*(('Budget 2026'!I7+'Budget 2026'!I12+'Budget 2026'!I17+'Budget 2026'!I22+'Budget 2026'!I27+'Budget 2026'!I32+'Budget 2026'!I37+'Budget 2026'!I42+'Budget 2026'!I47+'Budget 2026'!I52+'Budget 2026'!I57+'Budget 2026'!I62)*1000/('Budget 2026'!D7+'Budget 2026'!D12+'Budget 2026'!D17+'Budget 2026'!D22+'Budget 2026'!D27+'Budget 2026'!D32+'Budget 2026'!D37+'Budget 2026'!D42+'Budget 2026'!D47+'Budget 2026'!D52+'Budget 2026'!D57+'Budget 2026'!D62))/1000,2) -> -54.8 | J10: =ROUND(('Rolling Forecast'!D7+'Rolling Forecast'!D12+'Rolling Forecast'!D17+'Rolling Forecast'!D22+'Rolling Forecast'!D27+'Rolling Forecast'!D32+'Rolling Forecast'!D37+'Rolling Forecast'!D42+'Rolling Forecast'!D47+'Rolling Forecast'!D52+'Rolling Forecast'!D57+'Rolling Forecast'!D62)*((('Rolling Forecast'!F7+'Rolling Forecast'!F12+'Rolling Forecast'!F17+'Rolling Forecast'!F22+'Rolling Forecast'!F27+'Rolling Forecast'!F32+'Rolling Forecast'!F37+'Rolling Forecast'!F42+'Rolling Forecast'!F47+'Rolling Forecast'!F52+'Rolling Forecast'!F57+'Rolling Forecast'!F62)*1000/('Rolling Forecast'!D7+'Rolling Forecast'!D12+'Rolling Forecast'!D17+'Rolling Forecast'!D22+'Rolling Forecast'!D27+'Rolling Forecast'!D32+'Rolling Forecast'!D37+'Rolling Forecast'!D42+'Rolling Forecast'!D47+'Rolling Forecast'!D52+'Rolling Forecast'!D57+'Rolling Forecast'!D62))-(('Budget 2026'!I7+'Budget 2026'!I12+'Budget 2026'!I17+'Budget 2026'!I22+'Budget 2026'!I27+'Budget 2026'!I32+'Budget 2026'!I37+'Budget 2026'!I42+'Budget 2026'!I47+'Budget 2026'!I52+'Budget 2026'!I57+'Budget 2026'!I62)*1000/('Budget 2026'!D7+'Budget 2026'!D12+'Budget 2026'!D17+'Budget 2026'!D22+'Budget 2026'!D27+'Budget 2026'!D32+'Budget 2026'!D37+'Budget 2026'!D42+'Budget 2026'!D47+'Budget 2026'!D52+'Budget 2026'!D57+'Budget 2026'!D62)))/1000,2) -> -4.65 | K10: =ROUND(H10+I10+J10,2) -> -101.04 | L10: =ROUND(('Rolling Forecast'!F7+'Rolling Forecast'!F12+'Rolling Forecast'!F17+'Rolling Forecast'!F22+'Rolling Forecast'!F27+'Rolling Forecast'!F32+'Rolling Forecast'!F37+'Rolling Forecast'!F42+'Rolling Forecast'!F47+'Rolling Forecast'!F52+'Rolling Forecast'!F57+'Rolling Forecast'!F62)-('Budget 2026'!I7+'Budget 2026'!I12+'Budget 2026'!I17+'Budget 2026'!I22+'Budget 2026'!I27+'Budget 2026'!I32+'Budget 2026'!I37+'Budget 2026'!I42+'Budget 2026'!I47+'Budget 2026'!I52+'Budget 2026'!I57+'Budget 2026'!I62),2) -> -101.04 | M10: =ROUND(K10-L10,2) -> 0 | N10: =IF(ABS(H10)>=ABS(I10),IF(ABS(H10)>=ABS(J10),"Volume","Price"),IF(ABS(I10)>=ABS(J10),"Mix","Price")) -> Mix
A11: Leisure & Lifestyle | B11: =ROUND('Budget 2026'!D8+'Budget 2026'!D13+'Budget 2026'!D18+'Budget 2026'!D23+'Budget 2026'!D28+'Budget 2026'!D33+'Budget 2026'!D38+'Budget 2026'!D43+'Budget 2026'!D48+'Budget 2026'!D53+'Budget 2026'!D58+'Budget 2026'!D63,0) -> 655711 | C11: =ROUND('Rolling Forecast'!D8+'Rolling Forecast'!D13+'Rolling Forecast'!D18+'Rolling Forecast'!D23+'Rolling Forecast'!D28+'Rolling Forecast'!D33+'Rolling Forecast'!D38+'Rolling Forecast'!D43+'Rolling Forecast'!D48+'Rolling Forecast'!D53+'Rolling Forecast'!D58+'Rolling Forecast'!D63,0) -> 667760 | D11: =B11/$B$14 -> 0.12105891 | E11: =C11/$C$14 -> 0.12374414 | F11: =ROUND(('Budget 2026'!I8+'Budget 2026'!I13+'Budget 2026'!I18+'Budget 2026'!I23+'Budget 2026'!I28+'Budget 2026'!I33+'Budget 2026'!I38+'Budget 2026'!I43+'Budget 2026'!I48+'Budget 2026'!I53+'Budget 2026'!I58+'Budget 2026'!I63)*1000/B11,2) -> 20.52 | G11: =ROUND(('Rolling Forecast'!F8+'Rolling Forecast'!F13+'Rolling Forecast'!F18+'Rolling Forecast'!F23+'Rolling Forecast'!F28+'Rolling Forecast'!F33+'Rolling Forecast'!F38+'Rolling Forecast'!F43+'Rolling Forecast'!F48+'Rolling Forecast'!F53+'Rolling Forecast'!F58+'Rolling Forecast'!F63)*1000/C11,2) -> 20.5 | H11: =ROUND((SUM('Rolling Forecast'!D4:D63)-SUM('Budget 2026'!D4:D63))*(('Budget 2026'!D8+'Budget 2026'!D13+'Budget 2026'!D18+'Budget 2026'!D23+'Budget 2026'!D28+'Budget 2026'!D33+'Budget 2026'!D38+'Budget 2026'!D43+'Budget 2026'!D48+'Budget 2026'!D53+'Budget 2026'!D58+'Budget 2026'!D63)/SUM('Budget 2026'!D4:D63))*(('Budget 2026'!I8+'Budget 2026'!I13+'Budget 2026'!I18+'Budget 2026'!I23+'Budget 2026'!I28+'Budget 2026'!I33+'Budget 2026'!I38+'Budget 2026'!I43+'Budget 2026'!I48+'Budget 2026'!I53+'Budget 2026'!I58+'Budget 2026'!I63)*1000/('Budget 2026'!D8+'Budget 2026'!D13+'Budget 2026'!D18+'Budget 2026'!D23+'Budget 2026'!D28+'Budget 2026'!D33+'Budget 2026'!D38+'Budget 2026'!D43+'Budget 2026'!D48+'Budget 2026'!D53+'Budget 2026'!D58+'Budget 2026'!D63))/1000,2) -> -50.1 | I11: =ROUND(SUM('Rolling Forecast'!D4:D63)*((('Rolling Forecast'!D8+'Rolling Forecast'!D13+'Rolling Forecast'!D18+'Rolling Forecast'!D23+'Rolling Forecast'!D28+'Rolling Forecast'!D33+'Rolling Forecast'!D38+'Rolling Forecast'!D43+'Rolling Forecast'!D48+'Rolling Forecast'!D53+'Rolling Forecast'!D58+'Rolling Forecast'!D63)/SUM('Rolling Forecast'!D4:D63))-(('Budget 2026'!D8+'Budget 2026'!D13+'Budget 2026'!D18+'Budget 2026'!D23+'Budget 2026'!D28+'Budget 2026'!D33+'Budget 2026'!D38+'Budget 2026'!D43+'Budget 2026'!D48+'Budget 2026'!D53+'Budget 2026'!D58+'Budget 2026'!D63)/SUM('Budget 2026'!D4:D63)))*(('Budget 2026'!I8+'Budget 2026'!I13+'Budget 2026'!I18+'Budget 2026'!I23+'Budget 2026'!I28+'Budget 2026'!I33+'Budget 2026'!I38+'Budget 2026'!I43+'Budget 2026'!I48+'Budget 2026'!I53+'Budget 2026'!I58+'Budget 2026'!I63)*1000/('Budget 2026'!D8+'Budget 2026'!D13+'Budget 2026'!D18+'Budget 2026'!D23+'Budget 2026'!D28+'Budget 2026'!D33+'Budget 2026'!D38+'Budget 2026'!D43+'Budget 2026'!D48+'Budget 2026'!D53+'Budget 2026'!D58+'Budget 2026'!D63))/1000,2) -> 297.39 | J11: =ROUND(('Rolling Forecast'!D8+'Rolling Forecast'!D13+'Rolling Forecast'!D18+'Rolling Forecast'!D23+'Rolling Forecast'!D28+'Rolling Forecast'!D33+'Rolling Forecast'!D38+'Rolling Forecast'!D43+'Rolling Forecast'!D48+'Rolling Forecast'!D53+'Rolling Forecast'!D58+'Rolling Forecast'!D63)*((('Rolling Forecast'!F8+'Rolling Forecast'!F13+'Rolling Forecast'!F18+'Rolling Forecast'!F23+'Rolling Forecast'!F28+'Rolling Forecast'!F33+'Rolling Forecast'!F38+'Rolling Forecast'!F43+'Rolling Forecast'!F48+'Rolling Forecast'!F53+'Rolling Forecast'!F58+'Rolling Forecast'!F63)*1000/('Rolling Forecast'!D8+'Rolling Forecast'!D13+'Rolling Forecast'!D18+'Rolling Forecast'!D23+'Rolling Forecast'!D28+'Rolling Forecast'!D33+'Rolling Forecast'!D38+'Rolling Forecast'!D43+'Rolling Forecast'!D48+'Rolling Forecast'!D53+'Rolling Forecast'!D58+'Rolling Forecast'!D63))-(('Budget 2026'!I8+'Budget 2026'!I13+'Budget 2026'!I18+'Budget 2026'!I23+'Budget 2026'!I28+'Budget 2026'!I33+'Budget 2026'!I38+'Budget 2026'!I43+'Budget 2026'!I48+'Budget 2026'!I53+'Budget 2026'!I58+'Budget 2026'!I63)*1000/('Budget 2026'!D8+'Budget 2026'!D13+'Budget 2026'!D18+'Budget 2026'!D23+'Budget 2026'!D28+'Budget 2026'!D33+'Budget 2026'!D38+'Budget 2026'!D43+'Budget 2026'!D48+'Budget 2026'!D53+'Budget 2026'!D58+'Budget 2026'!D63)))/1000,2) -> -17.71 | K11: =ROUND(H11+I11+J11,2) -> 229.58 | L11: =ROUND(('Rolling Forecast'!F8+'Rolling Forecast'!F13+'Rolling Forecast'!F18+'Rolling Forecast'!F23+'Rolling Forecast'!F28+'Rolling Forecast'!F33+'Rolling Forecast'!F38+'Rolling Forecast'!F43+'Rolling Forecast'!F48+'Rolling Forecast'!F53+'Rolling Forecast'!F58+'Rolling Forecast'!F63)-('Budget 2026'!I8+'Budget 2026'!I13+'Budget 2026'!I18+'Budget 2026'!I23+'Budget 2026'!I28+'Budget 2026'!I33+'Budget 2026'!I38+'Budget 2026'!I43+'Budget 2026'!I48+'Budget 2026'!I53+'Budget 2026'!I58+'Budget 2026'!I63),2) -> 229.57 | M11: =ROUND(K11-L11,2) -> 0.01 | N11: =IF(ABS(H11)>=ABS(I11),IF(ABS(H11)>=ABS(J11),"Volume","Price"),IF(ABS(I11)>=ABS(J11),"Mix","Price")) -> Mix
A12: TOTAL | B12: =ROUND(SUM(B7:B11),2) -> 5416462 | C12: =ROUND(SUM(C7:C11),2) -> 5396296 | D12: =SUM(D7:D11) -> 1 | E12: =SUM(E7:E11) -> 1 | F12: =ROUND(SUM('Budget 2026'!I4:I63)*1000/B12,2) -> 12.67 | G12: =ROUND(SUM('Rolling Forecast'!F4:F63)*1000/C12,2) -> 12.67 | H12: =ROUND(SUM(H7:H11),2) -> -255.6 | I12: =ROUND(SUM(I7:I11),2) -> 108.75 | J12: =ROUND(SUM(J7:J11),2) -> -152.15 | K12: =ROUND(SUM(K7:K11),2) -> -299 | L12: =ROUND(SUM(L7:L11),2) -> -299.03 | M12: =ROUND(K12-L12,2) -> 0.03 | N12: Bridge check
A13: Portfolio helper | B13: Budget | C13: Forecast
A14: Total Units | B14: =ROUND(SUM('Budget 2026'!D4:D63),0) -> 5416462 | C14: =ROUND(SUM('Rolling Forecast'!D4:D63),0) -> 5396296
A15: Weighted ASP | B15: =ROUND(SUM('Budget 2026'!I4:I63)*1000/B14,2) -> 12.67 | C15: =ROUND(SUM('Rolling Forecast'!F4:F63)*1000/C14,2) -> 12.67
A18: Gross profit bridge: revenue PVM plus unit-cost effects
A19: Division | B19: Budget Unit Cost | C19: Forecast Unit Cost | D19: Revenue PVM (£000) | E19: COGS Volume (£000) | F19: COGS Mix (£000) | G19: Unit Cost Effect (£000) | H19: Calculated GP Var (£000) | I19: Actual GP Var (£000) | J19: Control (£000) | K19: Budget GP (£000) | L19: Forecast GP (£000) | M19: Budget GP % | N19: Forecast GP %
A20: Personal Care | B20: =ROUND(('Budget 2026'!J4+'Budget 2026'!J9+'Budget 2026'!J14+'Budget 2026'!J19+'Budget 2026'!J24+'Budget 2026'!J29+'Budget 2026'!J34+'Budget 2026'!J39+'Budget 2026'!J44+'Budget 2026'!J49+'Budget 2026'!J54+'Budget 2026'!J59)*1000/('Budget 2026'!D4+'Budget 2026'!D9+'Budget 2026'!D14+'Budget 2026'!D19+'Budget 2026'!D24+'Budget 2026'!D29+'Budget 2026'!D34+'Budget 2026'!D39+'Budget 2026'!D44+'Budget 2026'!D49+'Budget 2026'!D54+'Budget 2026'!D59),2) -> 4.57 | C20: =ROUND(('Rolling Forecast'!H4+'Rolling Forecast'!H9+'Rolling Forecast'!H14+'Rolling Forecast'!H19+'Rolling Forecast'!H24+'Rolling Forecast'!H29+'Rolling Forecast'!H34+'Rolling Forecast'!H39+'Rolling Forecast'!H44+'Rolling Forecast'!H49+'Rolling Forecast'!H54+'Rolling Forecast'!H59)*1000/('Rolling Forecast'!D4+'Rolling Forecast'!D9+'Rolling Forecast'!D14+'Rolling Forecast'!D19+'Rolling Forecast'!D24+'Rolling Forecast'!D29+'Rolling Forecast'!D34+'Rolling Forecast'!D39+'Rolling Forecast'!D44+'Rolling Forecast'!D49+'Rolling Forecast'!D54+'Rolling Forecast'!D59),2) -> 4.58 | D20: =K7 -> -185.27 | E20: =ROUND((-(SUM('Rolling Forecast'!D4:D63)-SUM('Budget 2026'!D4:D63))*(('Budget 2026'!D4+'Budget 2026'!D9+'Budget 2026'!D14+'Budget 2026'!D19+'Budget 2026'!D24+'Budget 2026'!D29+'Budget 2026'!D34+'Budget 2026'!D39+'Budget 2026'!D44+'Budget 2026'!D49+'Budget 2026'!D54+'Budget 2026'!D59)/SUM('Budget 2026'!D4:D63))*(('Budget 2026'!J4+'Budget 2026'!J9+'Budget 2026'!J14+'Budget 2026'!J19+'Budget 2026'!J24+'Budget 2026'!J29+'Budget 2026'!J34+'Budget 2026'!J39+'Budget 2026'!J44+'Budget 2026'!J49+'Budget 2026'!J54+'Budget 2026'!J59)*1000/('Budget 2026'!D4+'Budget 2026'!D9+'Budget 2026'!D14+'Budget 2026'!D19+'Budget 2026'!D24+'Budget 2026'!D29+'Budget 2026'!D34+'Budget 2026'!D39+'Budget 2026'!D44+'Budget 2026'!D49+'Budget 2026'!D54+'Budget 2026'!D59))/1000),2) -> 27.58 | F20: =ROUND((-SUM('Rolling Forecast'!D4:D63)*((('Rolling Forecast'!D4+'Rolling Forecast'!D9+'Rolling Forecast'!D14+'Rolling Forecast'!D19+'Rolling Forecast'!D24+'Rolling Forecast'!D29+'Rolling Forecast'!D34+'Rolling Forecast'!D39+'Rolling Forecast'!D44+'Rolling Forecast'!D49+'Rolling Forecast'!D54+'Rolling Forecast'!D59)/SUM('Rolling Forecast'!D4:D63))-(('Budget 2026'!D4+'Budget 2026'!D9+'Budget 2026'!D14+'Budget 2026'!D19+'Budget 2026'!D24+'Budget 2026'!D29+'Budget 2026'!D34+'Budget 2026'!D39+'Budget 2026'!D44+'Budget 2026'!D49+'Budget 2026'!D54+'Budget 2026'!D59)/SUM('Budget 2026'!D4:D63)))*(('Budget 2026'!J4+'Budget 2026'!J9+'Budget 2026'!J14+'Budget 2026'!J19+'Budget 2026'!J24+'Budget 2026'!J29+'Budget 2026'!J34+'Budget 2026'!J39+'Budget 2026'!J44+'Budget 2026'!J49+'Budget 2026'!J54+'Budget 2026'!J59)*1000/('Budget 2026'!D4+'Budget 2026'!D9+'Budget 2026'!D14+'Budget 2026'!D19+'Budget 2026'!D24+'Budget 2026'!D29+'Budget 2026'!D34+'Budget 2026'!D39+'Budget 2026'!D44+'Budget 2026'!D49+'Budget 2026'!D54+'Budget 2026'!D59))/1000),2) -> 53.67 | G20: =ROUND((-('Rolling Forecast'!D4+'Rolling Forecast'!D9+'Rolling Forecast'!D14+'Rolling Forecast'!D19+'Rolling Forecast'!D24+'Rolling Forecast'!D29+'Rolling Forecast'!D34+'Rolling Forecast'!D39+'Rolling Forecast'!D44+'Rolling Forecast'!D49+'Rolling Forecast'!D54+'Rolling Forecast'!D59)*((('Rolling Forecast'!H4+'Rolling Forecast'!H9+'Rolling Forecast'!H14+'Rolling Forecast'!H19+'Rolling Forecast'!H24+'Rolling Forecast'!H29+'Rolling Forecast'!H34+'Rolling Forecast'!H39+'Rolling Forecast'!H44+'Rolling Forecast'!H49+'Rolling Forecast'!H54+'Rolling Forecast'!H59)*1000/('Rolling Forecast'!D4+'Rolling Forecast'!D9+'Rolling Forecast'!D14+'Rolling Forecast'!D19+'Rolling Forecast'!D24+'Rolling Forecast'!D29+'Rolling Forecast'!D34+'Rolling Forecast'!D39+'Rolling Forecast'!D44+'Rolling Forecast'!D49+'Rolling Forecast'!D54+'Rolling Forecast'!D59))-(('Budget 2026'!J4+'Budget 2026'!J9+'Budget 2026'!J14+'Budget 2026'!J19+'Budget 2026'!J24+'Budget 2026'!J29+'Budget 2026'!J34+'Budget 2026'!J39+'Budget 2026'!J44+'Budget 2026'!J49+'Budget 2026'!J54+'Budget 2026'!J59)*1000/('Budget 2026'!D4+'Budget 2026'!D9+'Budget 2026'!D14+'Budget 2026'!D19+'Budget 2026'!D24+'Budget 2026'!D29+'Budget 2026'!D34+'Budget 2026'!D39+'Budget 2026'!D44+'Budget 2026'!D49+'Budget 2026'!D54+'Budget 2026'!D59)))/1000),2) -> -22.66 | H20: =ROUND((('Rolling Forecast'!F4+'Rolling Forecast'!F9+'Rolling Forecast'!F14+'Rolling Forecast'!F19+'Rolling Forecast'!F24+'Rolling Forecast'!F29+'Rolling Forecast'!F34+'Rolling Forecast'!F39+'Rolling Forecast'!F44+'Rolling Forecast'!F49+'Rolling Forecast'!F54+'Rolling Forecast'!F59)-('Budget 2026'!I4+'Budget 2026'!I9+'Budget 2026'!I14+'Budget 2026'!I19+'Budget 2026'!I24+'Budget 2026'!I29+'Budget 2026'!I34+'Budget 2026'!I39+'Budget 2026'!I44+'Budget 2026'!I49+'Budget 2026'!I54+'Budget 2026'!I59))+(-(SUM('Rolling Forecast'!D4:D63)-SUM('Budget 2026'!D4:D63))*(('Budget 2026'!D4+'Budget 2026'!D9+'Budget 2026'!D14+'Budget 2026'!D19+'Budget 2026'!D24+'Budget 2026'!D29+'Budget 2026'!D34+'Budget 2026'!D39+'Budget 2026'!D44+'Budget 2026'!D49+'Budget 2026'!D54+'Budget 2026'!D59)/SUM('Budget 2026'!D4:D63))*(('Budget 2026'!J4+'Budget 2026'!J9+'Budget 2026'!J14+'Budget 2026'!J19+'Budget 2026'!J24+'Budget 2026'!J29+'Budget 2026'!J34+'Budget 2026'!J39+'Budget 2026'!J44+'Budget 2026'!J49+'Budget 2026'!J54+'Budget 2026'!J59)*1000/('Budget 2026'!D4+'Budget 2026'!D9+'Budget 2026'!D14+'Budget 2026'!D19+'Budget 2026'!D24+'Budget 2026'!D29+'Budget 2026'!D34+'Budget 2026'!D39+'Budget 2026'!D44+'Budget 2026'!D49+'Budget 2026'!D54+'Budget 2026'!D59))/1000)+(-SUM('Rolling Forecast'!D4:D63)*((('Rolling Forecast'!D4+'Rolling Forecast'!D9+'Rolling Forecast'!D14+'Rolling Forecast'!D19+'Rolling Forecast'!D24+'Rolling Forecast'!D29+'Rolling Forecast'!D34+'Rolling Forecast'!D39+'Rolling Forecast'!D44+'Rolling Forecast'!D49+'Rolling Forecast'!D54+'Rolling Forecast'!D59)/SUM('Rolling Forecast'!D4:D63))-(('Budget 2026'!D4+'Budget 2026'!D9+'Budget 2026'!D14+'Budget 2026'!D19+'Budget 2026'!D24+'Budget 2026'!D29+'Budget 2026'!D34+'Budget 2026'!D39+'Budget 2026'!D44+'Budget 2026'!D49+'Budget 2026'!D54+'Budget 2026'!D59)/SUM('Budget 2026'!D4:D63)))*(('Budget 2026'!J4+'Budget 2026'!J9+'Budget 2026'!J14+'Budget 2026'!J19+'Budget 2026'!J24+'Budget 2026'!J29+'Budget 2026'!J34+'Budget 2026'!J39+'Budget 2026'!J44+'Budget 2026'!J49+'Budget 2026'!J54+'Budget 2026'!J59)*1000/('Budget 2026'!D4+'Budget 2026'!D9+'Budget 2026'!D14+'Budget 2026'!D19+'Budget 2026'!D24+'Budget 2026'!D29+'Budget 2026'!D34+'Budget 2026'!D39+'Budget 2026'!D44+'Budget 2026'!D49+'Budget 2026'!D54+'Budget 2026'!D59))/1000)+(-('Rolling Forecast'!D4+'Rolling Forecast'!D9+'Rolling Forecast'!D14+'Rolling Forecast'!D19+'Rolling Forecast'!D24+'Rolling Forecast'!D29+'Rolling Forecast'!D34+'Rolling Forecast'!D39+'Rolling Forecast'!D44+'Rolling Forecast'!D49+'Rolling Forecast'!D54+'Rolling Forecast'!D59)*((('Rolling Forecast'!H4+'Rolling Forecast'!H9+'Rolling Forecast'!H14+'Rolling Forecast'!H19+'Rolling Forecast'!H24+'Rolling Forecast'!H29+'Rolling Forecast'!H34+'Rolling Forecast'!H39+'Rolling Forecast'!H44+'Rolling Forecast'!H49+'Rolling Forecast'!H54+'Rolling Forecast'!H59)*1000/('Rolling Forecast'!D4+'Rolling Forecast'!D9+'Rolling Forecast'!D14+'Rolling Forecast'!D19+'Rolling Forecast'!D24+'Rolling Forecast'!D29+'Rolling Forecast'!D34+'Rolling Forecast'!D39+'Rolling Forecast'!D44+'Rolling Forecast'!D49+'Rolling Forecast'!D54+'Rolling Forecast'!D59))-(('Budget 2026'!J4+'Budget 2026'!J9+'Budget 2026'!J14+'Budget 2026'!J19+'Budget 2026'!J24+'Budget 2026'!J29+'Budget 2026'!J34+'Budget 2026'!J39+'Budget 2026'!J44+'Budget 2026'!J49+'Budget 2026'!J54+'Budget 2026'!J59)*1000/('Budget 2026'!D4+'Budget 2026'!D9+'Budget 2026'!D14+'Budget 2026'!D19+'Budget 2026'!D24+'Budget 2026'!D29+'Budget 2026'!D34+'Budget 2026'!D39+'Budget 2026'!D44+'Budget 2026'!D49+'Budget 2026'!D54+'Budget 2026'!D59)))/1000),2) -> -126.68 | I20: =ROUND(('Rolling Forecast'!I4+'Rolling Forecast'!I9+'Rolling Forecast'!I14+'Rolling Forecast'!I19+'Rolling Forecast'!I24+'Rolling Forecast'!I29+'Rolling Forecast'!I34+'Rolling Forecast'!I39+'Rolling Forecast'!I44+'Rolling Forecast'!I49+'Rolling Forecast'!I54+'Rolling Forecast'!I59)-('Budget 2026'!K4+'Budget 2026'!K9+'Budget 2026'!K14+'Budget 2026'!K19+'Budget 2026'!K24+'Budget 2026'!K29+'Budget 2026'!K34+'Budget 2026'!K39+'Budget 2026'!K44+'Budget 2026'!K49+'Budget 2026'!K54+'Budget 2026'!K59),2) -> -126.68 | J20: =ROUND(H20-I20,2) -> 0 | K20: =ROUND(('Budget 2026'!K4+'Budget 2026'!K9+'Budget 2026'!K14+'Budget 2026'!K19+'Budget 2026'!K24+'Budget 2026'!K29+'Budget 2026'!K34+'Budget 2026'!K39+'Budget 2026'!K44+'Budget 2026'!K49+'Budget 2026'!K54+'Budget 2026'!K59),0) -> 6991 | L20: =ROUND(('Rolling Forecast'!I4+'Rolling Forecast'!I9+'Rolling Forecast'!I14+'Rolling Forecast'!I19+'Rolling Forecast'!I24+'Rolling Forecast'!I29+'Rolling Forecast'!I34+'Rolling Forecast'!I39+'Rolling Forecast'!I44+'Rolling Forecast'!I49+'Rolling Forecast'!I54+'Rolling Forecast'!I59),0) -> 6864 | M20: =K20/('Budget 2026'!I4+'Budget 2026'!I9+'Budget 2026'!I14+'Budget 2026'!I19+'Budget 2026'!I24+'Budget 2026'!I29+'Budget 2026'!I34+'Budget 2026'!I39+'Budget 2026'!I44+'Budget 2026'!I49+'Budget 2026'!I54+'Budget 2026'!I59) -> 0.48553666 | N20: =L20/('Rolling Forecast'!F4+'Rolling Forecast'!F9+'Rolling Forecast'!F14+'Rolling Forecast'!F19+'Rolling Forecast'!F24+'Rolling Forecast'!F29+'Rolling Forecast'!F34+'Rolling Forecast'!F39+'Rolling Forecast'!F44+'Rolling Forecast'!F49+'Rolling Forecast'!F54+'Rolling Forecast'!F59) -> 0.48293043
A21: Home Care | B21: =ROUND(('Budget 2026'!J5+'Budget 2026'!J10+'Budget 2026'!J15+'Budget 2026'!J20+'Budget 2026'!J25+'Budget 2026'!J30+'Budget 2026'!J35+'Budget 2026'!J40+'Budget 2026'!J45+'Budget 2026'!J50+'Budget 2026'!J55+'Budget 2026'!J60)*1000/('Budget 2026'!D5+'Budget 2026'!D10+'Budget 2026'!D15+'Budget 2026'!D20+'Budget 2026'!D25+'Budget 2026'!D30+'Budget 2026'!D35+'Budget 2026'!D40+'Budget 2026'!D45+'Budget 2026'!D50+'Budget 2026'!D55+'Budget 2026'!D60),2) -> 5.97 | C21: =ROUND(('Rolling Forecast'!H5+'Rolling Forecast'!H10+'Rolling Forecast'!H15+'Rolling Forecast'!H20+'Rolling Forecast'!H25+'Rolling Forecast'!H30+'Rolling Forecast'!H35+'Rolling Forecast'!H40+'Rolling Forecast'!H45+'Rolling Forecast'!H50+'Rolling Forecast'!H55+'Rolling Forecast'!H60)*1000/('Rolling Forecast'!D5+'Rolling Forecast'!D10+'Rolling Forecast'!D15+'Rolling Forecast'!D20+'Rolling Forecast'!D25+'Rolling Forecast'!D30+'Rolling Forecast'!D35+'Rolling Forecast'!D40+'Rolling Forecast'!D45+'Rolling Forecast'!D50+'Rolling Forecast'!D55+'Rolling Forecast'!D60),2) -> 5.97 | D21: =K8 -> 45.86 | E21: =ROUND((-(SUM('Rolling Forecast'!D4:D63)-SUM('Budget 2026'!D4:D63))*(('Budget 2026'!D5+'Budget 2026'!D10+'Budget 2026'!D15+'Budget 2026'!D20+'Budget 2026'!D25+'Budget 2026'!D30+'Budget 2026'!D35+'Budget 2026'!D40+'Budget 2026'!D45+'Budget 2026'!D50+'Budget 2026'!D55+'Budget 2026'!D60)/SUM('Budget 2026'!D4:D63))*(('Budget 2026'!J5+'Budget 2026'!J10+'Budget 2026'!J15+'Budget 2026'!J20+'Budget 2026'!J25+'Budget 2026'!J30+'Budget 2026'!J35+'Budget 2026'!J40+'Budget 2026'!J45+'Budget 2026'!J50+'Budget 2026'!J55+'Budget 2026'!J60)*1000/('Budget 2026'!D5+'Budget 2026'!D10+'Budget 2026'!D15+'Budget 2026'!D20+'Budget 2026'!D25+'Budget 2026'!D30+'Budget 2026'!D35+'Budget 2026'!D40+'Budget 2026'!D45+'Budget 2026'!D50+'Budget 2026'!D55+'Budget 2026'!D60))/1000),2) -> 28.09 | F21: =ROUND((-SUM('Rolling Forecast'!D4:D63)*((('Rolling Forecast'!D5+'Rolling Forecast'!D10+'Rolling Forecast'!D15+'Rolling Forecast'!D20+'Rolling Forecast'!D25+'Rolling Forecast'!D30+'Rolling Forecast'!D35+'Rolling Forecast'!D40+'Rolling Forecast'!D45+'Rolling Forecast'!D50+'Rolling Forecast'!D55+'Rolling Forecast'!D60)/SUM('Rolling Forecast'!D4:D63))-(('Budget 2026'!D5+'Budget 2026'!D10+'Budget 2026'!D15+'Budget 2026'!D20+'Budget 2026'!D25+'Budget 2026'!D30+'Budget 2026'!D35+'Budget 2026'!D40+'Budget 2026'!D45+'Budget 2026'!D50+'Budget 2026'!D55+'Budget 2026'!D60)/SUM('Budget 2026'!D4:D63)))*(('Budget 2026'!J5+'Budget 2026'!J10+'Budget 2026'!J15+'Budget 2026'!J20+'Budget 2026'!J25+'Budget 2026'!J30+'Budget 2026'!J35+'Budget 2026'!J40+'Budget 2026'!J45+'Budget 2026'!J50+'Budget 2026'!J55+'Budget 2026'!J60)*1000/('Budget 2026'!D5+'Budget 2026'!D10+'Budget 2026'!D15+'Budget 2026'!D20+'Budget 2026'!D25+'Budget 2026'!D30+'Budget 2026'!D35+'Budget 2026'!D40+'Budget 2026'!D45+'Budget 2026'!D50+'Budget 2026'!D55+'Budget 2026'!D60))/1000),2) -> -63.07 | G21: =ROUND((-('Rolling Forecast'!D5+'Rolling Forecast'!D10+'Rolling Forecast'!D15+'Rolling Forecast'!D20+'Rolling Forecast'!D25+'Rolling Forecast'!D30+'Rolling Forecast'!D35+'Rolling Forecast'!D40+'Rolling Forecast'!D45+'Rolling Forecast'!D50+'Rolling Forecast'!D55+'Rolling Forecast'!D60)*((('Rolling Forecast'!H5+'Rolling Forecast'!H10+'Rolling Forecast'!H15+'Rolling Forecast'!H20+'Rolling Forecast'!H25+'Rolling Forecast'!H30+'Rolling Forecast'!H35+'Rolling Forecast'!H40+'Rolling Forecast'!H45+'Rolling Forecast'!H50+'Rolling Forecast'!H55+'Rolling Forecast'!H60)*1000/('Rolling Forecast'!D5+'Rolling Forecast'!D10+'Rolling Forecast'!D15+'Rolling Forecast'!D20+'Rolling Forecast'!D25+'Rolling Forecast'!D30+'Rolling Forecast'!D35+'Rolling Forecast'!D40+'Rolling Forecast'!D45+'Rolling Forecast'!D50+'Rolling Forecast'!D55+'Rolling Forecast'!D60))-(('Budget 2026'!J5+'Budget 2026'!J10+'Budget 2026'!J15+'Budget 2026'!J20+'Budget 2026'!J25+'Budget 2026'!J30+'Budget 2026'!J35+'Budget 2026'!J40+'Budget 2026'!J45+'Budget 2026'!J50+'Budget 2026'!J55+'Budget 2026'!J60)*1000/('Budget 2026'!D5+'Budget 2026'!D10+'Budget 2026'!D15+'Budget 2026'!D20+'Budget 2026'!D25+'Budget 2026'!D30+'Budget 2026'!D35+'Budget 2026'!D40+'Budget 2026'!D45+'Budget 2026'!D50+'Budget 2026'!D55+'Budget 2026'!D60)))/1000),2) -> 6.3 | H21: =ROUND((('Rolling Forecast'!F5+'Rolling Forecast'!F10+'Rolling Forecast'!F15+'Rolling Forecast'!F20+'Rolling Forecast'!F25+'Rolling Forecast'!F30+'Rolling Forecast'!F35+'Rolling Forecast'!F40+'Rolling Forecast'!F45+'Rolling Forecast'!F50+'Rolling Forecast'!F55+'Rolling Forecast'!F60)-('Budget 2026'!I5+'Budget 2026'!I10+'Budget 2026'!I15+'Budget 2026'!I20+'Budget 2026'!I25+'Budget 2026'!I30+'Budget 2026'!I35+'Budget 2026'!I40+'Budget 2026'!I45+'Budget 2026'!I50+'Budget 2026'!I55+'Budget 2026'!I60))+(-(SUM('Rolling Forecast'!D4:D63)-SUM('Budget 2026'!D4:D63))*(('Budget 2026'!D5+'Budget 2026'!D10+'Budget 2026'!D15+'Budget 2026'!D20+'Budget 2026'!D25+'Budget 2026'!D30+'Budget 2026'!D35+'Budget 2026'!D40+'Budget 2026'!D45+'Budget 2026'!D50+'Budget 2026'!D55+'Budget 2026'!D60)/SUM('Budget 2026'!D4:D63))*(('Budget 2026'!J5+'Budget 2026'!J10+'Budget 2026'!J15+'Budget 2026'!J20+'Budget 2026'!J25+'Budget 2026'!J30+'Budget 2026'!J35+'Budget 2026'!J40+'Budget 2026'!J45+'Budget 2026'!J50+'Budget 2026'!J55+'Budget 2026'!J60)*1000/('Budget 2026'!D5+'Budget 2026'!D10+'Budget 2026'!D15+'Budget 2026'!D20+'Budget 2026'!D25+'Budget 2026'!D30+'Budget 2026'!D35+'Budget 2026'!D40+'Budget 2026'!D45+'Budget 2026'!D50+'Budget 2026'!D55+'Budget 2026'!D60))/1000)+(-SUM('Rolling Forecast'!D4:D63)*((('Rolling Forecast'!D5+'Rolling Forecast'!D10+'Rolling Forecast'!D15+'Rolling Forecast'!D20+'Rolling Forecast'!D25+'Rolling Forecast'!D30+'Rolling Forecast'!D35+'Rolling Forecast'!D40+'Rolling Forecast'!D45+'Rolling Forecast'!D50+'Rolling Forecast'!D55+'Rolling Forecast'!D60)/SUM('Rolling Forecast'!D4:D63))-(('Budget 2026'!D5+'Budget 2026'!D10+'Budget 2026'!D15+'Budget 2026'!D20+'Budget 2026'!D25+'Budget 2026'!D30+'Budget 2026'!D35+'Budget 2026'!D40+'Budget 2026'!D45+'Budget 2026'!D50+'Budget 2026'!D55+'Budget 2026'!D60)/SUM('Budget 2026'!D4:D63)))*(('Budget 2026'!J5+'Budget 2026'!J10+'Budget 2026'!J15+'Budget 2026'!J20+'Budget 2026'!J25+'Budget 2026'!J30+'Budget 2026'!J35+'Budget 2026'!J40+'Budget 2026'!J45+'Budget 2026'!J50+'Budget 2026'!J55+'Budget 2026'!J60)*1000/('Budget 2026'!D5+'Budget 2026'!D10+'Budget 2026'!D15+'Budget 2026'!D20+'Budget 2026'!D25+'Budget 2026'!D30+'Budget 2026'!D35+'Budget 2026'!D40+'Budget 2026'!D45+'Budget 2026'!D50+'Budget 2026'!D55+'Budget 2026'!D60))/1000)+(-('Rolling Forecast'!D5+'Rolling Forecast'!D10+'Rolling Forecast'!D15+'Rolling Forecast'!D20+'Rolling Forecast'!D25+'Rolling Forecast'!D30+'Rolling Forecast'!D35+'Rolling Forecast'!D40+'Rolling Forecast'!D45+'Rolling Forecast'!D50+'Rolling Forecast'!D55+'Rolling Forecast'!D60)*((('Rolling Forecast'!H5+'Rolling Forecast'!H10+'Rolling Forecast'!H15+'Rolling Forecast'!H20+'Rolling Forecast'!H25+'Rolling Forecast'!H30+'Rolling Forecast'!H35+'Rolling Forecast'!H40+'Rolling Forecast'!H45+'Rolling Forecast'!H50+'Rolling Forecast'!H55+'Rolling Forecast'!H60)*1000/('Rolling Forecast'!D5+'Rolling Forecast'!D10+'Rolling Forecast'!D15+'Rolling Forecast'!D20+'Rolling Forecast'!D25+'Rolling Forecast'!D30+'Rolling Forecast'!D35+'Rolling Forecast'!D40+'Rolling Forecast'!D45+'Rolling Forecast'!D50+'Rolling Forecast'!D55+'Rolling Forecast'!D60))-(('Budget 2026'!J5+'Budget 2026'!J10+'Budget 2026'!J15+'Budget 2026'!J20+'Budget 2026'!J25+'Budget 2026'!J30+'Budget 2026'!J35+'Budget 2026'!J40+'Budget 2026'!J45+'Budget 2026'!J50+'Budget 2026'!J55+'Budget 2026'!J60)*1000/('Budget 2026'!D5+'Budget 2026'!D10+'Budget 2026'!D15+'Budget 2026'!D20+'Budget 2026'!D25+'Budget 2026'!D30+'Budget 2026'!D35+'Budget 2026'!D40+'Budget 2026'!D45+'Budget 2026'!D50+'Budget 2026'!D55+'Budget 2026'!D60)))/1000),2) -> 17.16 | I21: =ROUND(('Rolling Forecast'!I5+'Rolling Forecast'!I10+'Rolling Forecast'!I15+'Rolling Forecast'!I20+'Rolling Forecast'!I25+'Rolling Forecast'!I30+'Rolling Forecast'!I35+'Rolling Forecast'!I40+'Rolling Forecast'!I45+'Rolling Forecast'!I50+'Rolling Forecast'!I55+'Rolling Forecast'!I60)-('Budget 2026'!K5+'Budget 2026'!K10+'Budget 2026'!K15+'Budget 2026'!K20+'Budget 2026'!K25+'Budget 2026'!K30+'Budget 2026'!K35+'Budget 2026'!K40+'Budget 2026'!K45+'Budget 2026'!K50+'Budget 2026'!K55+'Budget 2026'!K60),2) -> 17.16 | J21: =ROUND(H21-I21,2) -> 0 | K21: =ROUND(('Budget 2026'!K5+'Budget 2026'!K10+'Budget 2026'!K15+'Budget 2026'!K20+'Budget 2026'!K25+'Budget 2026'!K30+'Budget 2026'!K35+'Budget 2026'!K40+'Budget 2026'!K45+'Budget 2026'!K50+'Budget 2026'!K55+'Budget 2026'!K60),0) -> 6038 | L21: =ROUND(('Rolling Forecast'!I5+'Rolling Forecast'!I10+'Rolling Forecast'!I15+'Rolling Forecast'!I20+'Rolling Forecast'!I25+'Rolling Forecast'!I30+'Rolling Forecast'!I35+'Rolling Forecast'!I40+'Rolling Forecast'!I45+'Rolling Forecast'!I50+'Rolling Forecast'!I55+'Rolling Forecast'!I60),0) -> 6055 | M21: =K21/('Budget 2026'!I5+'Budget 2026'!I10+'Budget 2026'!I15+'Budget 2026'!I20+'Budget 2026'!I25+'Budget 2026'!I30+'Budget 2026'!I35+'Budget 2026'!I40+'Budget 2026'!I45+'Budget 2026'!I50+'Budget 2026'!I55+'Budget 2026'!I60) -> 0.44455621 | N21: =L21/('Rolling Forecast'!F5+'Rolling Forecast'!F10+'Rolling Forecast'!F15+'Rolling Forecast'!F20+'Rolling Forecast'!F25+'Rolling Forecast'!F30+'Rolling Forecast'!F35+'Rolling Forecast'!F40+'Rolling Forecast'!F45+'Rolling Forecast'!F50+'Rolling Forecast'!F55+'Rolling Forecast'!F60) -> 0.44430787
A22: Nutrition & Wellness | B22: =ROUND(('Budget 2026'!J6+'Budget 2026'!J11+'Budget 2026'!J16+'Budget 2026'!J21+'Budget 2026'!J26+'Budget 2026'!J31+'Budget 2026'!J36+'Budget 2026'!J41+'Budget 2026'!J46+'Budget 2026'!J51+'Budget 2026'!J56+'Budget 2026'!J61)*1000/('Budget 2026'!D6+'Budget 2026'!D11+'Budget 2026'!D16+'Budget 2026'!D21+'Budget 2026'!D26+'Budget 2026'!D31+'Budget 2026'!D36+'Budget 2026'!D41+'Budget 2026'!D46+'Budget 2026'!D51+'Budget 2026'!D56+'Budget 2026'!D61),2) -> 8.24 | C22: =ROUND(('Rolling Forecast'!H6+'Rolling Forecast'!H11+'Rolling Forecast'!H16+'Rolling Forecast'!H21+'Rolling Forecast'!H26+'Rolling Forecast'!H31+'Rolling Forecast'!H36+'Rolling Forecast'!H41+'Rolling Forecast'!H46+'Rolling Forecast'!H51+'Rolling Forecast'!H56+'Rolling Forecast'!H61)*1000/('Rolling Forecast'!D6+'Rolling Forecast'!D11+'Rolling Forecast'!D16+'Rolling Forecast'!D21+'Rolling Forecast'!D26+'Rolling Forecast'!D31+'Rolling Forecast'!D36+'Rolling Forecast'!D41+'Rolling Forecast'!D46+'Rolling Forecast'!D51+'Rolling Forecast'!D56+'Rolling Forecast'!D61),2) -> 8.21 | D22: =K9 -> -288.13 | E22: =ROUND((-(SUM('Rolling Forecast'!D4:D63)-SUM('Budget 2026'!D4:D63))*(('Budget 2026'!D6+'Budget 2026'!D11+'Budget 2026'!D16+'Budget 2026'!D21+'Budget 2026'!D26+'Budget 2026'!D31+'Budget 2026'!D36+'Budget 2026'!D41+'Budget 2026'!D46+'Budget 2026'!D51+'Budget 2026'!D56+'Budget 2026'!D61)/SUM('Budget 2026'!D4:D63))*(('Budget 2026'!J6+'Budget 2026'!J11+'Budget 2026'!J16+'Budget 2026'!J21+'Budget 2026'!J26+'Budget 2026'!J31+'Budget 2026'!J36+'Budget 2026'!J41+'Budget 2026'!J46+'Budget 2026'!J51+'Budget 2026'!J56+'Budget 2026'!J61)*1000/('Budget 2026'!D6+'Budget 2026'!D11+'Budget 2026'!D16+'Budget 2026'!D21+'Budget 2026'!D26+'Budget 2026'!D31+'Budget 2026'!D36+'Budget 2026'!D41+'Budget 2026'!D46+'Budget 2026'!D51+'Budget 2026'!D56+'Budget 2026'!D61))/1000),2) -> 31.34 | F22: =ROUND((-SUM('Rolling Forecast'!D4:D63)*((('Rolling Forecast'!D6+'Rolling Forecast'!D11+'Rolling Forecast'!D16+'Rolling Forecast'!D21+'Rolling Forecast'!D26+'Rolling Forecast'!D31+'Rolling Forecast'!D36+'Rolling Forecast'!D41+'Rolling Forecast'!D46+'Rolling Forecast'!D51+'Rolling Forecast'!D56+'Rolling Forecast'!D61)/SUM('Rolling Forecast'!D4:D63))-(('Budget 2026'!D6+'Budget 2026'!D11+'Budget 2026'!D16+'Budget 2026'!D21+'Budget 2026'!D26+'Budget 2026'!D31+'Budget 2026'!D36+'Budget 2026'!D41+'Budget 2026'!D46+'Budget 2026'!D51+'Budget 2026'!D56+'Budget 2026'!D61)/SUM('Budget 2026'!D4:D63)))*(('Budget 2026'!J6+'Budget 2026'!J11+'Budget 2026'!J16+'Budget 2026'!J21+'Budget 2026'!J26+'Budget 2026'!J31+'Budget 2026'!J36+'Budget 2026'!J41+'Budget 2026'!J46+'Budget 2026'!J51+'Budget 2026'!J56+'Budget 2026'!J61)*1000/('Budget 2026'!D6+'Budget 2026'!D11+'Budget 2026'!D16+'Budget 2026'!D21+'Budget 2026'!D26+'Budget 2026'!D31+'Budget 2026'!D36+'Budget 2026'!D41+'Budget 2026'!D46+'Budget 2026'!D51+'Budget 2026'!D56+'Budget 2026'!D61))/1000),2) -> 75.07 | G22: =ROUND((-('Rolling Forecast'!D6+'Rolling Forecast'!D11+'Rolling Forecast'!D16+'Rolling Forecast'!D21+'Rolling Forecast'!D26+'Rolling Forecast'!D31+'Rolling Forecast'!D36+'Rolling Forecast'!D41+'Rolling Forecast'!D46+'Rolling Forecast'!D51+'Rolling Forecast'!D56+'Rolling Forecast'!D61)*((('Rolling Forecast'!H6+'Rolling Forecast'!H11+'Rolling Forecast'!H16+'Rolling Forecast'!H21+'Rolling Forecast'!H26+'Rolling Forecast'!H31+'Rolling Forecast'!H36+'Rolling Forecast'!H41+'Rolling Forecast'!H46+'Rolling Forecast'!H51+'Rolling Forecast'!H56+'Rolling Forecast'!H61)*1000/('Rolling Forecast'!D6+'Rolling Forecast'!D11+'Rolling Forecast'!D16+'Rolling Forecast'!D21+'Rolling Forecast'!D26+'Rolling Forecast'!D31+'Rolling Forecast'!D36+'Rolling Forecast'!D41+'Rolling Forecast'!D46+'Rolling Forecast'!D51+'Rolling Forecast'!D56+'Rolling Forecast'!D61))-(('Budget 2026'!J6+'Budget 2026'!J11+'Budget 2026'!J16+'Budget 2026'!J21+'Budget 2026'!J26+'Budget 2026'!J31+'Budget 2026'!J36+'Budget 2026'!J41+'Budget 2026'!J46+'Budget 2026'!J51+'Budget 2026'!J56+'Budget 2026'!J61)*1000/('Budget 2026'!D6+'Budget 2026'!D11+'Budget 2026'!D16+'Budget 2026'!D21+'Budget 2026'!D26+'Budget 2026'!D31+'Budget 2026'!D36+'Budget 2026'!D41+'Budget 2026'!D46+'Budget 2026'!D51+'Budget 2026'!D56+'Budget 2026'!D61)))/1000),2) -> 31.33 | H22: =ROUND((('Rolling Forecast'!F6+'Rolling Forecast'!F11+'Rolling Forecast'!F16+'Rolling Forecast'!F21+'Rolling Forecast'!F26+'Rolling Forecast'!F31+'Rolling Forecast'!F36+'Rolling Forecast'!F41+'Rolling Forecast'!F46+'Rolling Forecast'!F51+'Rolling Forecast'!F56+'Rolling Forecast'!F61)-('Budget 2026'!I6+'Budget 2026'!I11+'Budget 2026'!I16+'Budget 2026'!I21+'Budget 2026'!I26+'Budget 2026'!I31+'Budget 2026'!I36+'Budget 2026'!I41+'Budget 2026'!I46+'Budget 2026'!I51+'Budget 2026'!I56+'Budget 2026'!I61))+(-(SUM('Rolling Forecast'!D4:D63)-SUM('Budget 2026'!D4:D63))*(('Budget 2026'!D6+'Budget 2026'!D11+'Budget 2026'!D16+'Budget 2026'!D21+'Budget 2026'!D26+'Budget 2026'!D31+'Budget 2026'!D36+'Budget 2026'!D41+'Budget 2026'!D46+'Budget 2026'!D51+'Budget 2026'!D56+'Budget 2026'!D61)/SUM('Budget 2026'!D4:D63))*(('Budget 2026'!J6+'Budget 2026'!J11+'Budget 2026'!J16+'Budget 2026'!J21+'Budget 2026'!J26+'Budget 2026'!J31+'Budget 2026'!J36+'Budget 2026'!J41+'Budget 2026'!J46+'Budget 2026'!J51+'Budget 2026'!J56+'Budget 2026'!J61)*1000/('Budget 2026'!D6+'Budget 2026'!D11+'Budget 2026'!D16+'Budget 2026'!D21+'Budget 2026'!D26+'Budget 2026'!D31+'Budget 2026'!D36+'Budget 2026'!D41+'Budget 2026'!D46+'Budget 2026'!D51+'Budget 2026'!D56+'Budget 2026'!D61))/1000)+(-SUM('Rolling Forecast'!D4:D63)*((('Rolling Forecast'!D6+'Rolling Forecast'!D11+'Rolling Forecast'!D16+'Rolling Forecast'!D21+'Rolling Forecast'!D26+'Rolling Forecast'!D31+'Rolling Forecast'!D36+'Rolling Forecast'!D41+'Rolling Forecast'!D46+'Rolling Forecast'!D51+'Rolling Forecast'!D56+'Rolling Forecast'!D61)/SUM('Rolling Forecast'!D4:D63))-(('Budget 2026'!D6+'Budget 2026'!D11+'Budget 2026'!D16+'Budget 2026'!D21+'Budget 2026'!D26+'Budget 2026'!D31+'Budget 2026'!D36+'Budget 2026'!D41+'Budget 2026'!D46+'Budget 2026'!D51+'Budget 2026'!D56+'Budget 2026'!D61)/SUM('Budget 2026'!D4:D63)))*(('Budget 2026'!J6+'Budget 2026'!J11+'Budget 2026'!J16+'Budget 2026'!J21+'Budget 2026'!J26+'Budget 2026'!J31+'Budget 2026'!J36+'Budget 2026'!J41+'Budget 2026'!J46+'Budget 2026'!J51+'Budget 2026'!J56+'Budget 2026'!J61)*1000/('Budget 2026'!D6+'Budget 2026'!D11+'Budget 2026'!D16+'Budget 2026'!D21+'Budget 2026'!D26+'Budget 2026'!D31+'Budget 2026'!D36+'Budget 2026'!D41+'Budget 2026'!D46+'Budget 2026'!D51+'Budget 2026'!D56+'Budget 2026'!D61))/1000)+(-('Rolling Forecast'!D6+'Rolling Forecast'!D11+'Rolling Forecast'!D16+'Rolling Forecast'!D21+'Rolling Forecast'!D26+'Rolling Forecast'!D31+'Rolling Forecast'!D36+'Rolling Forecast'!D41+'Rolling Forecast'!D46+'Rolling Forecast'!D51+'Rolling Forecast'!D56+'Rolling Forecast'!D61)*((('Rolling Forecast'!H6+'Rolling Forecast'!H11+'Rolling Forecast'!H16+'Rolling Forecast'!H21+'Rolling Forecast'!H26+'Rolling Forecast'!H31+'Rolling Forecast'!H36+'Rolling Forecast'!H41+'Rolling Forecast'!H46+'Rolling Forecast'!H51+'Rolling Forecast'!H56+'Rolling Forecast'!H61)*1000/('Rolling Forecast'!D6+'Rolling Forecast'!D11+'Rolling Forecast'!D16+'Rolling Forecast'!D21+'Rolling Forecast'!D26+'Rolling Forecast'!D31+'Rolling Forecast'!D36+'Rolling Forecast'!D41+'Rolling Forecast'!D46+'Rolling Forecast'!D51+'Rolling Forecast'!D56+'Rolling Forecast'!D61))-(('Budget 2026'!J6+'Budget 2026'!J11+'Budget 2026'!J16+'Budget 2026'!J21+'Budget 2026'!J26+'Budget 2026'!J31+'Budget 2026'!J36+'Budget 2026'!J41+'Budget 2026'!J46+'Budget 2026'!J51+'Budget 2026'!J56+'Budget 2026'!J61)*1000/('Budget 2026'!D6+'Budget 2026'!D11+'Budget 2026'!D16+'Budget 2026'!D21+'Budget 2026'!D26+'Budget 2026'!D31+'Budget 2026'!D36+'Budget 2026'!D41+'Budget 2026'!D46+'Budget 2026'!D51+'Budget 2026'!D56+'Budget 2026'!D61)))/1000),2) -> -150.4 | I22: =ROUND(('Rolling Forecast'!I6+'Rolling Forecast'!I11+'Rolling Forecast'!I16+'Rolling Forecast'!I21+'Rolling Forecast'!I26+'Rolling Forecast'!I31+'Rolling Forecast'!I36+'Rolling Forecast'!I41+'Rolling Forecast'!I46+'Rolling Forecast'!I51+'Rolling Forecast'!I56+'Rolling Forecast'!I61)-('Budget 2026'!K6+'Budget 2026'!K11+'Budget 2026'!K16+'Budget 2026'!K21+'Budget 2026'!K26+'Budget 2026'!K31+'Budget 2026'!K36+'Budget 2026'!K41+'Budget 2026'!K46+'Budget 2026'!K51+'Budget 2026'!K56+'Budget 2026'!K61),2) -> -150.4 | J22: =ROUND(H22-I22,2) -> 0 | K22: =ROUND(('Budget 2026'!K6+'Budget 2026'!K11+'Budget 2026'!K16+'Budget 2026'!K21+'Budget 2026'!K26+'Budget 2026'!K31+'Budget 2026'!K36+'Budget 2026'!K41+'Budget 2026'!K46+'Budget 2026'!K51+'Budget 2026'!K56+'Budget 2026'!K61),0) -> 7626 | L22: =ROUND(('Rolling Forecast'!I6+'Rolling Forecast'!I11+'Rolling Forecast'!I16+'Rolling Forecast'!I21+'Rolling Forecast'!I26+'Rolling Forecast'!I31+'Rolling Forecast'!I36+'Rolling Forecast'!I41+'Rolling Forecast'!I46+'Rolling Forecast'!I51+'Rolling Forecast'!I56+'Rolling Forecast'!I61),0) -> 7476 | M22: =K22/('Budget 2026'!I6+'Budget 2026'!I11+'Budget 2026'!I16+'Budget 2026'!I21+'Budget 2026'!I26+'Budget 2026'!I31+'Budget 2026'!I36+'Budget 2026'!I41+'Budget 2026'!I46+'Budget 2026'!I51+'Budget 2026'!I56+'Budget 2026'!I61) -> 0.47532734 | N22: =L22/('Rolling Forecast'!F6+'Rolling Forecast'!F11+'Rolling Forecast'!F16+'Rolling Forecast'!F21+'Rolling Forecast'!F26+'Rolling Forecast'!F31+'Rolling Forecast'!F36+'Rolling Forecast'!F41+'Rolling Forecast'!F46+'Rolling Forecast'!F51+'Rolling Forecast'!F56+'Rolling Forecast'!F61) -> 0.47449964
A23: Baby & Kids | B23: =ROUND(('Budget 2026'!J7+'Budget 2026'!J12+'Budget 2026'!J17+'Budget 2026'!J22+'Budget 2026'!J27+'Budget 2026'!J32+'Budget 2026'!J37+'Budget 2026'!J42+'Budget 2026'!J47+'Budget 2026'!J52+'Budget 2026'!J57+'Budget 2026'!J62)*1000/('Budget 2026'!D7+'Budget 2026'!D12+'Budget 2026'!D17+'Budget 2026'!D22+'Budget 2026'!D27+'Budget 2026'!D32+'Budget 2026'!D37+'Budget 2026'!D42+'Budget 2026'!D47+'Budget 2026'!D52+'Budget 2026'!D57+'Budget 2026'!D62),2) -> 6.86 | C23: =ROUND(('Rolling Forecast'!H7+'Rolling Forecast'!H12+'Rolling Forecast'!H17+'Rolling Forecast'!H22+'Rolling Forecast'!H27+'Rolling Forecast'!H32+'Rolling Forecast'!H37+'Rolling Forecast'!H42+'Rolling Forecast'!H47+'Rolling Forecast'!H52+'Rolling Forecast'!H57+'Rolling Forecast'!H62)*1000/('Rolling Forecast'!D7+'Rolling Forecast'!D12+'Rolling Forecast'!D17+'Rolling Forecast'!D22+'Rolling Forecast'!D27+'Rolling Forecast'!D32+'Rolling Forecast'!D37+'Rolling Forecast'!D42+'Rolling Forecast'!D47+'Rolling Forecast'!D52+'Rolling Forecast'!D57+'Rolling Forecast'!D62),2) -> 6.85 | D23: =K10 -> -101.04 | E23: =ROUND((-(SUM('Rolling Forecast'!D4:D63)-SUM('Budget 2026'!D4:D63))*(('Budget 2026'!D7+'Budget 2026'!D12+'Budget 2026'!D17+'Budget 2026'!D22+'Budget 2026'!D27+'Budget 2026'!D32+'Budget 2026'!D37+'Budget 2026'!D42+'Budget 2026'!D47+'Budget 2026'!D52+'Budget 2026'!D57+'Budget 2026'!D62)/SUM('Budget 2026'!D4:D63))*(('Budget 2026'!J7+'Budget 2026'!J12+'Budget 2026'!J17+'Budget 2026'!J22+'Budget 2026'!J27+'Budget 2026'!J32+'Budget 2026'!J37+'Budget 2026'!J42+'Budget 2026'!J47+'Budget 2026'!J52+'Budget 2026'!J57+'Budget 2026'!J62)*1000/('Budget 2026'!D7+'Budget 2026'!D12+'Budget 2026'!D17+'Budget 2026'!D22+'Budget 2026'!D27+'Budget 2026'!D32+'Budget 2026'!D37+'Budget 2026'!D42+'Budget 2026'!D47+'Budget 2026'!D52+'Budget 2026'!D57+'Budget 2026'!D62))/1000),2) -> 21.8 | F23: =ROUND((-SUM('Rolling Forecast'!D4:D63)*((('Rolling Forecast'!D7+'Rolling Forecast'!D12+'Rolling Forecast'!D17+'Rolling Forecast'!D22+'Rolling Forecast'!D27+'Rolling Forecast'!D32+'Rolling Forecast'!D37+'Rolling Forecast'!D42+'Rolling Forecast'!D47+'Rolling Forecast'!D52+'Rolling Forecast'!D57+'Rolling Forecast'!D62)/SUM('Rolling Forecast'!D4:D63))-(('Budget 2026'!D7+'Budget 2026'!D12+'Budget 2026'!D17+'Budget 2026'!D22+'Budget 2026'!D27+'Budget 2026'!D32+'Budget 2026'!D37+'Budget 2026'!D42+'Budget 2026'!D47+'Budget 2026'!D52+'Budget 2026'!D57+'Budget 2026'!D62)/SUM('Budget 2026'!D4:D63)))*(('Budget 2026'!J7+'Budget 2026'!J12+'Budget 2026'!J17+'Budget 2026'!J22+'Budget 2026'!J27+'Budget 2026'!J32+'Budget 2026'!J37+'Budget 2026'!J42+'Budget 2026'!J47+'Budget 2026'!J52+'Budget 2026'!J57+'Budget 2026'!J62)*1000/('Budget 2026'!D7+'Budget 2026'!D12+'Budget 2026'!D17+'Budget 2026'!D22+'Budget 2026'!D27+'Budget 2026'!D32+'Budget 2026'!D37+'Budget 2026'!D42+'Budget 2026'!D47+'Budget 2026'!D52+'Budget 2026'!D57+'Budget 2026'!D62))/1000),2) -> 28.72 | G23: =ROUND((-('Rolling Forecast'!D7+'Rolling Forecast'!D12+'Rolling Forecast'!D17+'Rolling Forecast'!D22+'Rolling Forecast'!D27+'Rolling Forecast'!D32+'Rolling Forecast'!D37+'Rolling Forecast'!D42+'Rolling Forecast'!D47+'Rolling Forecast'!D52+'Rolling Forecast'!D57+'Rolling Forecast'!D62)*((('Rolling Forecast'!H7+'Rolling Forecast'!H12+'Rolling Forecast'!H17+'Rolling Forecast'!H22+'Rolling Forecast'!H27+'Rolling Forecast'!H32+'Rolling Forecast'!H37+'Rolling Forecast'!H42+'Rolling Forecast'!H47+'Rolling Forecast'!H52+'Rolling Forecast'!H57+'Rolling Forecast'!H62)*1000/('Rolling Forecast'!D7+'Rolling Forecast'!D12+'Rolling Forecast'!D17+'Rolling Forecast'!D22+'Rolling Forecast'!D27+'Rolling Forecast'!D32+'Rolling Forecast'!D37+'Rolling Forecast'!D42+'Rolling Forecast'!D47+'Rolling Forecast'!D52+'Rolling Forecast'!D57+'Rolling Forecast'!D62))-(('Budget 2026'!J7+'Budget 2026'!J12+'Budget 2026'!J17+'Budget 2026'!J22+'Budget 2026'!J27+'Budget 2026'!J32+'Budget 2026'!J37+'Budget 2026'!J42+'Budget 2026'!J47+'Budget 2026'!J52+'Budget 2026'!J57+'Budget 2026'!J62)*1000/('Budget 2026'!D7+'Budget 2026'!D12+'Budget 2026'!D17+'Budget 2026'!D22+'Budget 2026'!D27+'Budget 2026'!D32+'Budget 2026'!D37+'Budget 2026'!D42+'Budget 2026'!D47+'Budget 2026'!D52+'Budget 2026'!D57+'Budget 2026'!D62)))/1000),2) -> 7.21 | H23: =ROUND((('Rolling Forecast'!F7+'Rolling Forecast'!F12+'Rolling Forecast'!F17+'Rolling Forecast'!F22+'Rolling Forecast'!F27+'Rolling Forecast'!F32+'Rolling Forecast'!F37+'Rolling Forecast'!F42+'Rolling Forecast'!F47+'Rolling Forecast'!F52+'Rolling Forecast'!F57+'Rolling Forecast'!F62)-('Budget 2026'!I7+'Budget 2026'!I12+'Budget 2026'!I17+'Budget 2026'!I22+'Budget 2026'!I27+'Budget 2026'!I32+'Budget 2026'!I37+'Budget 2026'!I42+'Budget 2026'!I47+'Budget 2026'!I52+'Budget 2026'!I57+'Budget 2026'!I62))+(-(SUM('Rolling Forecast'!D4:D63)-SUM('Budget 2026'!D4:D63))*(('Budget 2026'!D7+'Budget 2026'!D12+'Budget 2026'!D17+'Budget 2026'!D22+'Budget 2026'!D27+'Budget 2026'!D32+'Budget 2026'!D37+'Budget 2026'!D42+'Budget 2026'!D47+'Budget 2026'!D52+'Budget 2026'!D57+'Budget 2026'!D62)/SUM('Budget 2026'!D4:D63))*(('Budget 2026'!J7+'Budget 2026'!J12+'Budget 2026'!J17+'Budget 2026'!J22+'Budget 2026'!J27+'Budget 2026'!J32+'Budget 2026'!J37+'Budget 2026'!J42+'Budget 2026'!J47+'Budget 2026'!J52+'Budget 2026'!J57+'Budget 2026'!J62)*1000/('Budget 2026'!D7+'Budget 2026'!D12+'Budget 2026'!D17+'Budget 2026'!D22+'Budget 2026'!D27+'Budget 2026'!D32+'Budget 2026'!D37+'Budget 2026'!D42+'Budget 2026'!D47+'Budget 2026'!D52+'Budget 2026'!D57+'Budget 2026'!D62))/1000)+(-SUM('Rolling Forecast'!D4:D63)*((('Rolling Forecast'!D7+'Rolling Forecast'!D12+'Rolling Forecast'!D17+'Rolling Forecast'!D22+'Rolling Forecast'!D27+'Rolling Forecast'!D32+'Rolling Forecast'!D37+'Rolling Forecast'!D42+'Rolling Forecast'!D47+'Rolling Forecast'!D52+'Rolling Forecast'!D57+'Rolling Forecast'!D62)/SUM('Rolling Forecast'!D4:D63))-(('Budget 2026'!D7+'Budget 2026'!D12+'Budget 2026'!D17+'Budget 2026'!D22+'Budget 2026'!D27+'Budget 2026'!D32+'Budget 2026'!D37+'Budget 2026'!D42+'Budget 2026'!D47+'Budget 2026'!D52+'Budget 2026'!D57+'Budget 2026'!D62)/SUM('Budget 2026'!D4:D63)))*(('Budget 2026'!J7+'Budget 2026'!J12+'Budget 2026'!J17+'Budget 2026'!J22+'Budget 2026'!J27+'Budget 2026'!J32+'Budget 2026'!J37+'Budget 2026'!J42+'Budget 2026'!J47+'Budget 2026'!J52+'Budget 2026'!J57+'Budget 2026'!J62)*1000/('Budget 2026'!D7+'Budget 2026'!D12+'Budget 2026'!D17+'Budget 2026'!D22+'Budget 2026'!D27+'Budget 2026'!D32+'Budget 2026'!D37+'Budget 2026'!D42+'Budget 2026'!D47+'Budget 2026'!D52+'Budget 2026'!D57+'Budget 2026'!D62))/1000)+(-('Rolling Forecast'!D7+'Rolling Forecast'!D12+'Rolling Forecast'!D17+'Rolling Forecast'!D22+'Rolling Forecast'!D27+'Rolling Forecast'!D32+'Rolling Forecast'!D37+'Rolling Forecast'!D42+'Rolling Forecast'!D47+'Rolling Forecast'!D52+'Rolling Forecast'!D57+'Rolling Forecast'!D62)*((('Rolling Forecast'!H7+'Rolling Forecast'!H12+'Rolling Forecast'!H17+'Rolling Forecast'!H22+'Rolling Forecast'!H27+'Rolling Forecast'!H32+'Rolling Forecast'!H37+'Rolling Forecast'!H42+'Rolling Forecast'!H47+'Rolling Forecast'!H52+'Rolling Forecast'!H57+'Rolling Forecast'!H62)*1000/('Rolling Forecast'!D7+'Rolling Forecast'!D12+'Rolling Forecast'!D17+'Rolling Forecast'!D22+'Rolling Forecast'!D27+'Rolling Forecast'!D32+'Rolling Forecast'!D37+'Rolling Forecast'!D42+'Rolling Forecast'!D47+'Rolling Forecast'!D52+'Rolling Forecast'!D57+'Rolling Forecast'!D62))-(('Budget 2026'!J7+'Budget 2026'!J12+'Budget 2026'!J17+'Budget 2026'!J22+'Budget 2026'!J27+'Budget 2026'!J32+'Budget 2026'!J37+'Budget 2026'!J42+'Budget 2026'!J47+'Budget 2026'!J52+'Budget 2026'!J57+'Budget 2026'!J62)*1000/('Budget 2026'!D7+'Budget 2026'!D12+'Budget 2026'!D17+'Budget 2026'!D22+'Budget 2026'!D27+'Budget 2026'!D32+'Budget 2026'!D37+'Budget 2026'!D42+'Budget 2026'!D47+'Budget 2026'!D52+'Budget 2026'!D57+'Budget 2026'!D62)))/1000),2) -> -43.3 | I23: =ROUND(('Rolling Forecast'!I7+'Rolling Forecast'!I12+'Rolling Forecast'!I17+'Rolling Forecast'!I22+'Rolling Forecast'!I27+'Rolling Forecast'!I32+'Rolling Forecast'!I37+'Rolling Forecast'!I42+'Rolling Forecast'!I47+'Rolling Forecast'!I52+'Rolling Forecast'!I57+'Rolling Forecast'!I62)-('Budget 2026'!K7+'Budget 2026'!K12+'Budget 2026'!K17+'Budget 2026'!K22+'Budget 2026'!K27+'Budget 2026'!K32+'Budget 2026'!K37+'Budget 2026'!K42+'Budget 2026'!K47+'Budget 2026'!K52+'Budget 2026'!K57+'Budget 2026'!K62),2) -> -43.3 | J23: =ROUND(H23-I23,2) -> 0 | K23: =ROUND(('Budget 2026'!K7+'Budget 2026'!K12+'Budget 2026'!K17+'Budget 2026'!K22+'Budget 2026'!K27+'Budget 2026'!K32+'Budget 2026'!K37+'Budget 2026'!K42+'Budget 2026'!K47+'Budget 2026'!K52+'Budget 2026'!K57+'Budget 2026'!K62),0) -> 5315 | L23: =ROUND(('Rolling Forecast'!I7+'Rolling Forecast'!I12+'Rolling Forecast'!I17+'Rolling Forecast'!I22+'Rolling Forecast'!I27+'Rolling Forecast'!I32+'Rolling Forecast'!I37+'Rolling Forecast'!I42+'Rolling Forecast'!I47+'Rolling Forecast'!I52+'Rolling Forecast'!I57+'Rolling Forecast'!I62),0) -> 5272 | M23: =K23/('Budget 2026'!I7+'Budget 2026'!I12+'Budget 2026'!I17+'Budget 2026'!I22+'Budget 2026'!I27+'Budget 2026'!I32+'Budget 2026'!I37+'Budget 2026'!I42+'Budget 2026'!I47+'Budget 2026'!I52+'Budget 2026'!I57+'Budget 2026'!I62) -> 0.47578698 | N23: =L23/('Rolling Forecast'!F7+'Rolling Forecast'!F12+'Rolling Forecast'!F17+'Rolling Forecast'!F22+'Rolling Forecast'!F27+'Rolling Forecast'!F32+'Rolling Forecast'!F37+'Rolling Forecast'!F42+'Rolling Forecast'!F47+'Rolling Forecast'!F52+'Rolling Forecast'!F57+'Rolling Forecast'!F62) -> 0.4762451
